Workbook

Sheet Exemple BH_V2
A1: CODE | B1: TRIAL | C1: PARAMETER | D1: 0 | E1: 1 | F1: 2 | G1: 3 | H1: 4 | I1: 5 | J1: 6 | K1: 7 | L1: 8 | M1: 9 | N1: 10 | O1: 11 | P1: 12 | Q1: 13 | R1: 14 | S1: 15 | T1: 16 | U1: 17 | V1: 18 | W1: 19 | X1: 20 | Y1: 21 | Z1: 22 | AA1: 23 | AB1: 24 | AC1: 25 | AD1: 26 | AE1: 27 | AF1: 28 | AG1: 29 | AH1: 30 | AI1: 31 | AJ1: 32 | AK1: 33 | AL1: 34 | AM1: 35 | AN1: 36 | AO1: 37 | AP1: 38 | AQ1: 39 | AR1: 40 | AS1: 41 | AT1: 42 | AU1: 43 | AV1: 44 | AW1: 45 | AX1: 46 | AY1: 47 | AZ1: 48 | BA1: 49 | BB1: 50 | BC1: 51 | BD1: 52 | BE1: 53 | BF1: 54 | BG1: 55 | BH1: 56 | BI1: 57 | BJ1: 58 | BK1: 59 | BL1: 60 | BM1: 61 | BN1: 62 | BO1: 63 | BP1: 64 | BQ1: 65 | BR1: 66 | BS1: 67 | BT1: 68 | BU1: 69 | BV1: 70 | BW1: 71 | BX1: 72 | BY1: 73 | BZ1: 74 | CA1: 75 | CB1: 76 | CC1: 77 | CD1: 78 | CE1: 79 | CF1: 80 | CG1: 81 | CH1: 82 | CI1: 83 | CJ1: 84 | CK1: 85 | CL1: 86 | CM1: 87 | CN1: 88 | CO1: 89 | CP1: 90 | CQ1: 91 | CR1: 92 | CS1: 93 | CT1: 94 | CU1: 95 | CV1: 96 | CW1: 97 | CX1: 98 | CY1: 99 | CZ1: 100 | DA1: 101 | DB1: 102 | DC1: 103 | DD1: 104 | DE1: 105 | DF1: 106 | DG1: 107 | DH1: 108 | DI1: 109 | DJ1: 110 | DK1: 111 | DL1: 112 | DM1: 113 | DN1: 114 | DO1: 115 | DP1: 116 | DQ1: 117 | DR1: 118 | DS1: 119 | DT1: 120
A2: 18 | B2: 1 | C2: DEFLATOR | D2: 1 | E2: 1.0010941 | F2: 0.99962838 | G2: 0.99948463 | H2: 0.99975926 | I2: 0.9956829 | J2: 0.98608358 | K2: 0.9733013 | L2: 0.95884773 | M2: 0.94329196 | N2: 0.92618496 | O2: 0.90863767 | P2: 0.89167494 | Q2: 0.87745895 | R2: 0.8649745 | S2: 0.85363899 | T2: 0.84188851 | U2: 0.83291749 | V2: 0.82570456 | W2: 0.81980234 | X2: 0.81328231 | Y2: 0.80827287 | Z2: 0.80284504 | AA2: 0.79744191 | AB2: 0.79329389 | AC2: 0.78839799 | AD2: 0.78358581 | AE2: 0.78015327 | AF2: 0.77804277 | AG2: 0.77561966 | AH2: 0.76908826 | AI2: 0.76240139 | AJ2: 0.75666174 | AK2: 0.75274204 | AL2: 0.74956594 | AM2: 0.74654038 | AN2: 0.74254647 | AO2: 0.73587517 | AP2: 0.72815735 | AQ2: 0.71991219 | AR2: 0.71033531 | AS2: 0.69975291 | AT2: 0.69248607 | AU2: 0.68691743 | AV2: 0.67871461 | AW2: 0.67096399 | AX2: 0.66397374 | AY2: 0.65395371 | AZ2: 0.64484537 | BA2: 0.63652376 | BB2: 0.63144291 | BC2: 0.62439294 | BD2: 0.61512494 | BE2: 0.60345875 | BF2: 0.58856447 | BG2: 0.57297194 | BH2: 0.55806314 | BI2: 0.54348902 | BJ2: 0.53039868 | BK2: 0.51650248 | BL2: 0.50217187 | BM2: 0.48889989 | BN2: 0.47668372 | BO2: 0.46379107 | BP2: 0.45197246 | BQ2: 0.4410039 | BR2: 0.43027652 | BS2: 0.41958486 | BT2: 0.40986575 | BU2: 0.40103722 | BV2: 0.39304507 | BW2: 0.3861654 | BX2: 0.38014393 | BY2: 0.37528953 | BZ2: 0.37250085 | CA2: 0.36891815 | CB2: 0.36424715 | CC2: 0.35955972 | CD2: 0.35464168 | CE2: 0.34801374 | CF2: 0.34119156 | CG2: 0.33516337 | CH2: 0.32924351 | CI2: 0.32320591 | CJ2: 0.31803475 | CK2: 0.3123978 | CL2: 0.30652875 | CM2: 0.30191245 | CN2: 0.29761866 | CO2: 0.29309235 | CP2: 0.28872496 | CQ2: 0.28634888 | CR2: 0.28441273 | CS2: 0.28161143 | CT2: 0.27803702 | CU2: 0.27386079 | CV2: 0.26929402 | CW2: 0.26382515 | CX2: 0.25814313 | CY2: 0.2516882 | CZ2: 0.24495265 | DA2: 0.23870148 | DB2: 0.23248277 | DC2: 0.22655829 | DD2: 0.22166726 | DE2: 0.2169402 | DF2: 0.21314569 | DG2: 0.20945607 | DH2: 0.20503343 | DI2: 0.20102327 | DJ2: 0.19713292 | DK2: 0.19310838 | DL2: 0.18936232 | DM2: 0.18537238 | DN2: 0.18068072 | DO2: 0.17588822 | DP2: 0.17117757 | DQ2: 0.16642862 | DR2: 0.16147831 | DS2: 0.15617376 | DT2: 0.15168478
A3: 0 | B3: 1 | C3: ZC_1 | D3: 1.0016623 | E3: 1.001471 | F3: 1.0012205 | G3: 0.99851264 | H3: 0.99580476 | I3: 0.98416337 | J3: 0.97252197 | K3: 0.97048214 | L3: 0.96844231 | M3: 0.96594474 | N3: 0.96344717 | O3: 0.96278986 | P3: 0.96213255 | Q3: 0.96724475 | R3: 0.97235696 | S3: 0.97468001 | T3: 0.97700306 | U3: 0.98337115 | V3: 0.98973925 | W3: 0.98955314 | X3: 0.98936704 | Y3: 0.98543799 | Z3: 0.98150894 | AA3: 0.98505906 | AB3: 0.98860919 | AC3: 0.9900223 | AD3: 0.99143541 | AE3: 0.99366715 | AF3: 0.99589889 | AG3: 0.98893635 | AH3: 0.98197381 | AI3: 0.98564249 | AJ3: 0.98931117 | AK3: 0.98980808 | AL3: 0.990305 | AM3: 0.98569922 | AN3: 0.98109345 | AO3: 0.97774894 | AP3: 0.97440442 | AQ3: 0.97067967 | AR3: 0.96695492 | AS3: 0.97550472 | AT3: 0.98405452 | AU3: 0.9811135 | AV3: 0.97817248 | AW3: 0.97649856 | AX3: 0.97482463 | AY3: 0.97264979 | AZ3: 0.97047494 | BA3: 0.97662424 | BB3: 0.98277353 | BC3: 0.97284214 | BD3: 0.96291075 | BE3: 0.95397943 | BF3: 0.94504811 | BG3: 0.94743782 | BH3: 0.94982753 | BI3: 0.94874264 | BJ3: 0.94765775 | BK3: 0.94668339 | BL3: 0.94570904 | BM3: 0.94840809 | BN3: 0.95110714 | BO3: 0.94960836 | BP3: 0.94810958 | BQ3: 0.94964661 | BR3: 0.95118363 | BS3: 0.9516832 | BT3: 0.95218278 | BU3: 0.95663588 | BV3: 0.96108899 | BW3: 0.96512899 | BX3: 0.969169 | BY3: 0.97653336 | BZ3: 0.98389772 | CA3: 0.97858902 | CB3: 0.97328032 | CC3: 0.97107809 | CD3: 0.96887585 | CE3: 0.96362124 | CF3: 0.95836663 | CG3: 0.95991775 | CH3: 0.96146888 | CI3: 0.96568574 | CJ3: 0.9699026 | CK3: 0.96755645 | CL3: 0.9652103 | CM3: 0.96763562 | CN3: 0.97006093 | CO3: 0.97400524 | CP3: 0.97794954 | CQ3: 0.98058792 | CR3: 0.9832263 | CS3: 0.97580792 | CT3: 0.96838955 | CU3: 0.96520592 | CV3: 0.96202229 | CW3: 0.95743814 | CX3: 0.95285398 | CY3: 0.95126902 | CZ3: 0.94968406 | DA3: 0.94898597 | DB3: 0.94828789 | DC3: 0.95384332 | DD3: 0.95939875 | DE3: 0.9630709 | DF3: 0.96674305 | DG3: 0.9622728 | DH3: 0.95780256 | DI3: 0.95788687 | DJ3: 0.95797119 | DK3: 0.96115034 | DL3: 0.96432949 | DM3: 0.95592877 | DN3: 0.94752805 | DO3: 0.94727171 | DP3: 0.94701537 | DQ3: 0.94091323 | DR3: 0.93481108 | DS3: 0.94011401 | DT3: 0.94541693
A4: 0 | B4: 1 | C4: ZC_2 | D4: 1.002568 | E4: 1.0019066 | F4: 1.0011897 | G4: 0.9952111 | H4: 0.98923251 | I4: 0.96645162 | J4: 0.94367073 | K4: 0.93942258 | L4: 0.93517444 | M4: 0.93043733 | N4: 0.92570022 | O4: 0.92445305 | P4: 0.92320587 | Q4: 0.93329727 | R4: 0.94338868 | S4: 0.94811393 | T4: 0.95283917 | U4: 0.96536723 | V4: 0.97789529 | W4: 0.97770273 | X4: 0.97751017 | Y4: 0.96977128 | Z4: 0.9620324 | AA4: 0.96946785 | AB4: 0.9769033 | AC4: 0.98008742 | AD4: 0.98327155 | AE4: 0.98775744 | AF4: 0.99224333 | AG4: 0.97827041 | AH4: 0.9642975 | AI4: 0.97071636 | AJ4: 0.97713523 | AK4: 0.97779144 | AL4: 0.97844766 | AM4: 0.96888332 | AN4: 0.95931898 | AO4: 0.95258266 | AP4: 0.94584634 | AQ4: 0.93892462 | AR4: 0.93200289 | AS4: 0.94839545 | AT4: 0.96478801 | AU4: 0.95952944 | AV4: 0.95427088 | AW4: 0.95075453 | AX4: 0.94723818 | AY4: 0.94346611 | AZ4: 0.93969405 | BA4: 0.95145701 | BB4: 0.96321997 | BC4: 0.9441824 | BD4: 0.92514484 | BE4: 0.90824726 | BF4: 0.89134969 | BG4: 0.89596652 | BH4: 0.90058334 | BI4: 0.89855128 | BJ4: 0.89651921 | BK4: 0.89455684 | BL4: 0.89259447 | BM4: 0.8978133 | BN4: 0.90303213 | BO4: 0.90037337 | BP4: 0.89771462 | BQ4: 0.90032162 | BR4: 0.90292862 | BS4: 0.90403108 | BT4: 0.90513353 | BU4: 0.91359488 | BV4: 0.92205623 | BW4: 0.92980218 | BX4: 0.93754813 | BY4: 0.95163352 | BZ4: 0.96571892 | CA4: 0.95580065 | CB4: 0.94588239 | CC4: 0.94109713 | CD4: 0.93631188 | CE4: 0.92684025 | CF4: 0.91736862 | CG4: 0.91995981 | CH4: 0.922551 | CI4: 0.93062518 | CJ4: 0.93869935 | CK4: 0.93441075 | CL4: 0.93012215 | CM4: 0.93457991 | CN4: 0.93903767 | CO4: 0.9468804 | CP4: 0.95472313 | CQ4: 0.95941166 | CR4: 0.96410019 | CS4: 0.95020344 | CT4: 0.93630669 | CU4: 0.93000209 | CV4: 0.92369749 | CW4: 0.91499978 | CX4: 0.90630207 | CY4: 0.90308345 | CZ4: 0.89986484 | DA4: 0.89901654 | DB4: 0.89816824 | DC4: 0.90845619 | DD4: 0.91874413 | DE4: 0.92550628 | DF4: 0.93226843 | DG4: 0.92424654 | DH4: 0.91622465 | DI4: 0.91588706 | DJ4: 0.91554948 | DK4: 0.92186429 | DL4: 0.92817909 | DM4: 0.91226237 | DN4: 0.89634565 | DO4: 0.89560358 | DP4: 0.8948615 | DQ4: 0.88373758 | DR4: 0.87261366 | DS4: 0.88223409 | DT4: 0.89185452
A5: 0 | B5: 1 | C5: ZC_3 | D5: 1.0021081 | E5: 1.0005469 | F5: 0.99875115 | G5: 0.98951368 | H5: 0.98027621 | I5: 0.94667303 | J5: 0.91306985 | K5: 0.90684479 | L5: 0.90061973 | M5: 0.89386575 | N5: 0.88711177 | O5: 0.88561257 | P5: 0.88411337 | Q5: 0.89895866 | R5: 0.91380396 | S5: 0.92086052 | T5: 0.92791709 | U5: 0.94643598 | V5: 0.96495486 | W5: 0.96469869 | X5: 0.96444251 | Y5: 0.95356369 | Z5: 0.94268486 | AA5: 0.95422476 | AB5: 0.96576465 | AC5: 0.97074025 | AD5: 0.97571586 | AE5: 0.98210722 | AF5: 0.98849859 | AG5: 0.96702296 | AH5: 0.94554734 | AI5: 0.95426708 | AJ5: 0.96298682 | AK5: 0.96322597 | AL5: 0.96346512 | AM5: 0.94896839 | AN5: 0.93447166 | AO5: 0.92483255 | AP5: 0.91519344 | AQ5: 0.90525048 | AR5: 0.89530751 | AS5: 0.91935903 | AT5: 0.94341055 | AU5: 0.93571644 | AV5: 0.92802233 | AW5: 0.92321033 | AX5: 0.91839833 | AY5: 0.913029 | AZ5: 0.90765968 | BA5: 0.92473147 | BB5: 0.94180326 | BC5: 0.91438333 | BD5: 0.8869634 | BE5: 0.86316016 | BF5: 0.83935691 | BG5: 0.84591956 | BH5: 0.85248222 | BI5: 0.84949751 | BJ5: 0.8465128 | BK5: 0.84382702 | BL5: 0.84114124 | BM5: 0.84871344 | BN5: 0.85628564 | BO5: 0.85234051 | BP5: 0.84839539 | BQ5: 0.8520868 | BR5: 0.85577821 | BS5: 0.85742391 | BT5: 0.85906961 | BU5: 0.87110932 | BV5: 0.88314902 | BW5: 0.89409319 | BX5: 0.90503737 | BY5: 0.92573762 | BZ5: 0.94643788 | CA5: 0.9316789 | CB5: 0.91691993 | CC5: 0.91031939 | CD5: 0.90371886 | CE5: 0.89008805 | CF5: 0.87645724 | CG5: 0.87997974 | CH5: 0.88350224 | CI5: 0.8952789 | CJ5: 0.90705557 | CK5: 0.90080901 | CL5: 0.89456246 | CM5: 0.90108716 | CN5: 0.90761187 | CO5: 0.91863594 | CP5: 0.92966001 | CQ5: 0.93671311 | CR5: 0.94376621 | CS5: 0.92365058 | CT5: 0.90353496 | CU5: 0.89440543 | CV5: 0.88527589 | CW5: 0.87269724 | CX5: 0.86011859 | CY5: 0.85590875 | CZ5: 0.85169891 | DA5: 0.85051359 | DB5: 0.84932826 | DC5: 0.86356172 | DD5: 0.87779518 | DE5: 0.88782879 | DF5: 0.89786241 | DG5: 0.88616337 | DH5: 0.87446434 | DI5: 0.87399276 | DJ5: 0.87352117 | DK5: 0.88265936 | DL5: 0.89179756 | DM5: 0.8689626 | DN5: 0.84612765 | DO5: 0.84521169 | DP5: 0.84429573 | DQ5: 0.82862936 | DR5: 0.81296298 | DS5: 0.82678479 | DT5: 0.84060659
A6: 0 | B6: 1 | C6: ZC_4 | D6: 0.99947957 | E6: 0.99679274 | F6: 0.99386545 | G6: 0.98114499 | H6: 0.96842454 | I6: 0.92477099 | J6: 0.88111745 | K6: 0.87311261 | L6: 0.86510777 | M6: 0.85681924 | N6: 0.84853072 | O6: 0.84702073 | P6: 0.84551075 | Q6: 0.86475232 | R6: 0.88399389 | S6: 0.89335856 | T6: 0.90272322 | U6: 0.92682631 | V6: 0.95092941 | W6: 0.95109796 | X6: 0.95126651 | Y6: 0.93778376 | Z6: 0.92430102 | AA6: 0.93984324 | AB6: 0.95538547 | AC6: 0.96180919 | AD6: 0.96823291 | AE6: 0.97571287 | AF6: 0.98319284 | AG6: 0.95423297 | AH6: 0.9252731 | AI6: 0.9356012 | AJ6: 0.94592929 | AK6: 0.94550808 | AL6: 0.94508687 | AM6: 0.92623182 | AN6: 0.90737678 | AO6: 0.89497877 | AP6: 0.88258075 | AQ6: 0.87033341 | AR6: 0.85808606 | AS6: 0.8888594 | AT6: 0.91963273 | AU6: 0.91009112 | AV6: 0.9005495 | AW6: 0.89442275 | AX6: 0.88829599 | AY6: 0.88157523 | AZ6: 0.87485446 | BA6: 0.89679704 | BB6: 0.91873962 | BC6: 0.88380186 | BD6: 0.8488641 | BE6: 0.8190399 | BF6: 0.78921569 | BG6: 0.79733155 | BH6: 0.8054474 | BI6: 0.80176804 | BJ6: 0.79808867 | BK6: 0.79492778 | BL6: 0.79176689 | BM6: 0.80111549 | BN6: 0.81046409 | BO6: 0.80554634 | BP6: 0.80062859 | BQ6: 0.8052702 | BR6: 0.80991182 | BS6: 0.81204362 | BT6: 0.81417542 | BU6: 0.82921724 | BV6: 0.84425907 | BW6: 0.85841988 | BX6: 0.87258069 | BY6: 0.89886028 | BZ6: 0.92513987 | CA6: 0.90645035 | CB6: 0.88776084 | CC6: 0.87916193 | CD6: 0.87056302 | CE6: 0.8532109 | CF6: 0.83585878 | CG6: 0.84039732 | CH6: 0.84493585 | CI6: 0.85986499 | CJ6: 0.87479413 | CK6: 0.86698342 | CL6: 0.85917271 | CM6: 0.86716856 | CN6: 0.87516441 | CO6: 0.88952475 | CP6: 0.90388508 | CQ6: 0.91293194 | CR6: 0.92197881 | CS6: 0.89614502 | CT6: 0.87031123 | CU6: 0.85842776 | CV6: 0.8465443 | CW6: 0.8309744 | CX6: 0.81540449 | CY6: 0.81013884 | CZ6: 0.80487318 | DA6: 0.80318202 | DB6: 0.80149085 | DC6: 0.81961914 | DD6: 0.83774743 | DE6: 0.8502448 | DF6: 0.86274217 | DG6: 0.84800099 | DH6: 0.83325981 | DI6: 0.8326772 | DJ6: 0.8320946 | DK6: 0.84349658 | DL6: 0.85489855 | DM6: 0.82623551 | DN6: 0.79757246 | DO6: 0.79626995 | DP6: 0.79496743 | DQ6: 0.77594273 | DR6: 0.75691803 | DS6: 0.7735658 | DT6: 0.79021357
A7: 0 | B7: 1 | C7: ZC_5 | D7: 0.99445428 | E7: 0.99034668 | F7: 0.98597933 | G7: 0.96997465 | H7: 0.95396997 | I7: 0.90104653 | J7: 0.84812309 | K7: 0.83878987 | L7: 0.82945664 | M7: 0.82001548 | N7: 0.81057432 | O7: 0.80915228 | P7: 0.80773025 | Q7: 0.83107145 | R7: 0.85441265 | S7: 0.86584529 | T7: 0.87727794 | U7: 0.90709037 | V7: 0.9369028 | W7: 0.93786637 | X7: 0.93882993 | Y7: 0.92293179 | Z7: 0.90703365 | AA7: 0.92613228 | AB7: 0.9452309 | AC7: 0.95230618 | AD7: 0.95938145 | AE7: 0.96758922 | AF7: 0.975797 | AG7: 0.93920134 | AH7: 0.90260569 | AI7: 0.91415884 | AJ7: 0.925712 | AK7: 0.9248988 | AL7: 0.9240856 | AM7: 0.90111409 | AN7: 0.87814258 | AO7: 0.86366558 | AP7: 0.84918857 | AQ7: 0.83465593 | AR7: 0.82012328 | AS7: 0.85733591 | AT7: 0.89454854 | AU7: 0.88319111 | AV7: 0.87183368 | AW7: 0.86461322 | AX7: 0.85739275 | AY7: 0.8494495 | AZ7: 0.84150626 | BA7: 0.8680097 | BB7: 0.89451315 | BC7: 0.852787 | BD7: 0.81106084 | BE7: 0.77593108 | BF7: 0.74080132 | BG7: 0.75035046 | BH7: 0.7598996 | BI7: 0.75576727 | BJ7: 0.75163493 | BK7: 0.74783695 | BL7: 0.74403896 | BM7: 0.75502946 | BN7: 0.76601997 | BO7: 0.76028249 | BP7: 0.75454501 | BQ7: 0.76001101 | BR7: 0.765477 | BS7: 0.76789031 | BT7: 0.77030361 | BU7: 0.78827519 | BV7: 0.80624676 | BW7: 0.82279704 | BX7: 0.83934732 | BY7: 0.87126059 | BZ7: 0.90317386 | CA7: 0.88052404 | CB7: 0.85787421 | CC7: 0.84747168 | CD7: 0.83706915 | CE7: 0.8166011 | CF7: 0.79613305 | CG7: 0.80139816 | CH7: 0.80666327 | CI7: 0.82459916 | CJ7: 0.84253505 | CK7: 0.83294485 | CL7: 0.82335465 | CM7: 0.83305955 | CN7: 0.84276445 | CO7: 0.85996711 | CP7: 0.87716977 | CQ7: 0.88805991 | CR7: 0.89895005 | CS7: 0.86768483 | CT7: 0.83641961 | CU7: 0.82250915 | CV7: 0.8085987 | CW7: 0.790229 | CX7: 0.7718593 | CY7: 0.76548483 | CZ7: 0.75911036 | DA7: 0.75739931 | DB7: 0.75568826 | DC7: 0.77676431 | DD7: 0.79784035 | DE7: 0.81273701 | DF7: 0.82763367 | DG7: 0.81021455 | DH7: 0.79279542 | DI7: 0.79188583 | DJ7: 0.79097624 | DK7: 0.80460158 | DL7: 0.81822691 | DM7: 0.78427913 | DN7: 0.75033135 | DO7: 0.74916299 | DP7: 0.74799462 | DQ7: 0.72551641 | DR7: 0.70303819 | DS7: 0.72269902 | DT7: 0.74235985
A8: 0 | B8: 1 | C8: ZC_6 | D8: 0.98650877 | E8: 0.98106034 | F8: 0.97535236 | G8: 0.9562465 | H8: 0.93714064 | I8: 0.87600981 | J8: 0.81487898 | K8: 0.80457231 | L8: 0.79426563 | M8: 0.78390678 | N8: 0.77354792 | O8: 0.77234624 | P8: 0.77114455 | Q8: 0.79810453 | R8: 0.8250645 | S8: 0.83882023 | T8: 0.85257595 | U8: 0.88813979 | V8: 0.92370362 | W8: 0.92550466 | X8: 0.9273057 | Y8: 0.90882609 | Z8: 0.89034648 | AA8: 0.91211878 | AB8: 0.93389107 | AC8: 0.94127458 | AD8: 0.94865809 | AE8: 0.95698253 | AF8: 0.96530696 | AG8: 0.92132782 | AH8: 0.87734868 | AI8: 0.89022672 | AJ8: 0.90310475 | AK8: 0.90181334 | AL8: 0.90052194 | AM8: 0.87422239 | AN8: 0.84792285 | AO8: 0.83135784 | AP8: 0.81479282 | AQ8: 0.79861129 | AR8: 0.78242976 | AS8: 0.82527788 | AT8: 0.868126 | AU8: 0.85522222 | AV8: 0.84231844 | AW8: 0.83411066 | AX8: 0.82590288 | AY8: 0.81698731 | AZ8: 0.80807174 | BA8: 0.83870582 | BB8: 0.86933991 | BC8: 0.82141805 | BD8: 0.7734962 | BE8: 0.73397223 | BF8: 0.69444826 | BG8: 0.70532543 | BH8: 0.7162026 | BI8: 0.71146843 | BJ8: 0.70673426 | BK8: 0.70252658 | BL8: 0.6983189 | BM8: 0.71069841 | BN8: 0.72307792 | BO8: 0.71666149 | BP8: 0.71024506 | BQ8: 0.71627745 | BR8: 0.72230983 | BS8: 0.725249 | BT8: 0.72818816 | BU8: 0.74825196 | BV8: 0.76831577 | BW8: 0.78744767 | BX8: 0.80657957 | BY8: 0.84328334 | BZ8: 0.87998711 | CA8: 0.85372989 | CB8: 0.82747266 | CC8: 0.81563957 | CD8: 0.80380649 | CE8: 0.78044272 | CF8: 0.75707896 | CG8: 0.76315512 | CH8: 0.76923128 | CI8: 0.78945891 | CJ8: 0.80968655 | CK8: 0.79889499 | CL8: 0.78810344 | CM8: 0.79914681 | CN8: 0.81019018 | CO8: 0.82995688 | CP8: 0.84972358 | CQ8: 0.8620771 | CR8: 0.87443062 | CS8: 0.83868544 | CT8: 0.80294026 | CU8: 0.78705419 | CV8: 0.77116812 | CW8: 0.75019193 | CX8: 0.72921573 | CY8: 0.722295 | CZ8: 0.71537428 | DA8: 0.71326727 | DB8: 0.71116027 | DC8: 0.73494186 | DD8: 0.75872345 | DE8: 0.77572624 | DF8: 0.79272904 | DG8: 0.77275343 | DH8: 0.75277783 | DI8: 0.75180333 | DJ8: 0.75082882 | DK8: 0.76615518 | DL8: 0.78148153 | DM8: 0.7434623 | DN8: 0.70544307 | DO8: 0.7037436 | DP8: 0.70204414 | DQ8: 0.67738008 | DR8: 0.65271603 | DS8: 0.67441959 | DT8: 0.69612316
A9: 0 | B9: 1 | C9: ZC_7 | D9: 0.97564521 | E9: 0.96916105 | F9: 0.96218282 | G9: 0.94045906 | H9: 0.9187353 | I9: 0.85035208 | J9: 0.78196887 | K9: 0.77090136 | L9: 0.75983386 | M9: 0.74881448 | N9: 0.73779509 | O9: 0.73675121 | P9: 0.73570732 | Q9: 0.76628593 | R9: 0.79686454 | S9: 0.81309684 | T9: 0.82932913 | U9: 0.87041163 | V9: 0.91149413 | W9: 0.91382807 | X9: 0.916162 | Y9: 0.89453226 | Z9: 0.87290251 | AA9: 0.89689246 | AB9: 0.92088241 | AC9: 0.9279941 | AD9: 0.93510578 | AE9: 0.94325077 | AF9: 0.95139575 | AG9: 0.90083295 | AH9: 0.85027016 | AI9: 0.86422249 | AJ9: 0.87817483 | AK9: 0.87685699 | AL9: 0.87553914 | AM9: 0.84601 | AN9: 0.81648086 | AO9: 0.7984349 | AP9: 0.78038895 | AQ9: 0.7626809 | AR9: 0.74497285 | AS9: 0.79288364 | AT9: 0.84079443 | AU9: 0.82650019 | AV9: 0.81220596 | AW9: 0.80323647 | AX9: 0.79426699 | AY9: 0.78450521 | AZ9: 0.77474343 | BA9: 0.80894985 | BB9: 0.84315628 | BC9: 0.78987477 | BD9: 0.73659326 | BE9: 0.69351272 | BF9: 0.65043218 | BG9: 0.66219319 | BH9: 0.6739542 | BI9: 0.66883911 | BJ9: 0.66372401 | BK9: 0.65919333 | BL9: 0.65466265 | BM9: 0.66819883 | BN9: 0.68173501 | BO9: 0.67463804 | BP9: 0.66754106 | BQ9: 0.6743073 | BR9: 0.68107354 | BS9: 0.68406319 | BT9: 0.68705285 | BU9: 0.70931621 | BV9: 0.73157957 | BW9: 0.75267497 | BX9: 0.77377037 | BY9: 0.81477426 | BZ9: 0.85577816 | CA9: 0.82644574 | CB9: 0.79711332 | CC9: 0.78385091 | CD9: 0.77058849 | CE9: 0.74488767 | CF9: 0.71918685 | CG9: 0.72562832 | CH9: 0.7320698 | CI9: 0.75464581 | CJ9: 0.77722181 | CK9: 0.7652062 | CL9: 0.75319058 | CM9: 0.76540968 | CN9: 0.77762879 | CO9: 0.79947282 | CP9: 0.82131686 | CQ9: 0.83542433 | CR9: 0.84953181 | CS9: 0.80957151 | CT9: 0.76961121 | CU9: 0.75180882 | CV9: 0.73400644 | CW9: 0.71120307 | CX9: 0.6883997 | CY9: 0.68066582 | CZ9: 0.67293195 | DA9: 0.67067842 | DB9: 0.66842489 | DC9: 0.69448192 | DD9: 0.72053895 | DE9: 0.73914187 | DF9: 0.75774478 | DG9: 0.73578478 | DH9: 0.71382478 | DI9: 0.71258332 | DJ9: 0.71134186 | DK9: 0.72857476 | DL9: 0.74580766 | DM9: 0.70372101 | DN9: 0.66163436 | DO9: 0.66010847 | DP9: 0.65858258 | DQ9: 0.63179885 | DR9: 0.60501512 | DS9: 0.62831338 | DT9: 0.65161164
A10: 0 | B10: 1 | C10: ZC_8 | D10: 0.9622231 | E10: 0.95514106 | F10: 0.94726107 | G10: 0.92332252 | H10: 0.89938398 | I10: 0.82453485 | J10: 0.74968572 | K10: 0.7380936 | L10: 0.72650148 | M10: 0.71487994 | N10: 0.7032584 | O10: 0.7027178 | P10: 0.70217719 | Q10: 0.7363102 | R10: 0.7704432 | S10: 0.78903236 | T10: 0.80762151 | U10: 0.85368297 | V10: 0.89974442 | W10: 0.90188405 | X10: 0.90402368 | Y10: 0.87914416 | Z10: 0.85426464 | AA10: 0.87977575 | AB10: 0.90528685 | AC10: 0.91186014 | AD10: 0.91843342 | AE10: 0.92660881 | AF10: 0.93478419 | AG10: 0.87812191 | AH10: 0.82145963 | AI10: 0.83675063 | AJ10: 0.85204163 | AK10: 0.85045462 | AL10: 0.84886761 | AM10: 0.81683542 | AN10: 0.78480322 | AO10: 0.7653735 | AP10: 0.74594377 | AQ10: 0.72702684 | AR10: 0.7081099 | AS10: 0.76042794 | AT10: 0.81274599 | AU10: 0.79733411 | AV10: 0.78192223 | AW10: 0.77229542 | AX10: 0.76266861 | AY10: 0.75206295 | AZ10: 0.74145729 | BA10: 0.77894251 | BB10: 0.81642773 | BC10: 0.75858167 | BD10: 0.70073561 | BE10: 0.65453387 | BF10: 0.60833214 | BG10: 0.62090215 | BH10: 0.63347216 | BI10: 0.62806251 | BJ10: 0.62265286 | BK10: 0.61787704 | BL10: 0.61310122 | BM10: 0.627457 | BN10: 0.64181277 | BO10: 0.63441191 | BP10: 0.62701105 | BQ10: 0.63401395 | BR10: 0.64101686 | BS10: 0.64443028 | BT10: 0.64784369 | BU10: 0.67169148 | BV10: 0.69553927 | BW10: 0.71831638 | BX10: 0.74109348 | BY10: 0.78610278 | BZ10: 0.83111208 | CA10: 0.79886049 | CB10: 0.76660891 | CC10: 0.75227036 | CD10: 0.73793181 | CE10: 0.70991597 | CF10: 0.68190014 | CG10: 0.68896624 | CH10: 0.69603234 | CI10: 0.72047383 | CJ10: 0.74491532 | CK10: 0.73184336 | CL10: 0.71877139 | CM10: 0.73181681 | CN10: 0.74486224 | CO10: 0.76892878 | CP10: 0.79299532 | CQ10: 0.80848896 | CR10: 0.8239826 | CS10: 0.78008646 | CT10: 0.73619032 | CU10: 0.7171301 | CV10: 0.69806989 | CW10: 0.67338924 | CX10: 0.64870859 | CY10: 0.64048518 | CZ10: 0.63226178 | DA10: 0.62989835 | DB10: 0.62753492 | DC10: 0.65526551 | DD10: 0.68299609 | DE10: 0.70315459 | DF10: 0.7233131 | DG10: 0.6994705 | DH10: 0.67562791 | DI10: 0.67457467 | DJ10: 0.67352144 | DK10: 0.69172902 | DL10: 0.7099366 | DM10: 0.66510511 | DN10: 0.62027362 | DO10: 0.6185174 | DP10: 0.61676117 | DQ10: 0.58834468 | DR10: 0.55992818 | DS10: 0.58462494 | DT10: 0.60932169
A11: 0 | B11: 1 | C11: ZC_9 | D11: 0.94679282 | E11: 0.93970819 | F11: 0.93121654 | G11: 0.90532289 | H11: 0.87942923 | I11: 0.79889764 | J11: 0.71836605 | K11: 0.70629132 | L11: 0.6942166 | M11: 0.68243348 | N11: 0.67065037 | O11: 0.67084016 | P11: 0.67102995 | Q11: 0.70843346 | R11: 0.74583698 | S11: 0.76638232 | T11: 0.78692767 | U11: 0.83701351 | V11: 0.88709935 | W11: 0.88875872 | X11: 0.89041809 | Y11: 0.8620131 | Z11: 0.83360812 | AA11: 0.86022314 | AB11: 0.88683817 | AC11: 0.89309933 | AD11: 0.8993605 | AE11: 0.90742147 | AF11: 0.91548244 | AG11: 0.85373185 | AH11: 0.79198126 | AI11: 0.80821188 | AJ11: 0.82444251 | AK11: 0.82297711 | AL11: 0.8215117 | AM11: 0.78718229 | AN11: 0.75285289 | AO11: 0.73233441 | AP11: 0.71181593 | AQ11: 0.69189556 | AR11: 0.67197519 | AS11: 0.72818734 | AT11: 0.78439949 | AU11: 0.76802072 | AV11: 0.75164196 | AW11: 0.74134087 | AX11: 0.73103978 | AY11: 0.71982563 | AZ11: 0.70861148 | BA11: 0.74910927 | BB11: 0.78960706 | BC11: 0.72758596 | BD11: 0.66556486 | BE11: 0.61697482 | BF11: 0.56838478 | BG11: 0.58159259 | BH11: 0.5948004 | BI11: 0.58917365 | BJ11: 0.5835469 | BK11: 0.57848346 | BL11: 0.57342001 | BM11: 0.58864486 | BN11: 0.60386971 | BO11: 0.59589902 | BP11: 0.58792834 | BQ11: 0.5954642 | BR11: 0.60300005 | BS11: 0.60652843 | BT11: 0.6100568 | BU11: 0.63518874 | BV11: 0.66032068 | BW11: 0.6846726 | BX11: 0.70902452 | BY11: 0.75740751 | BZ11: 0.80579049 | CA11: 0.77113116 | CB11: 0.73647183 | CC11: 0.72087929 | CD11: 0.70528674 | CE11: 0.6756396 | CF11: 0.64599246 | CG11: 0.65343477 | CH11: 0.66087708 | CI11: 0.68689852 | CJ11: 0.71291997 | CK11: 0.69877279 | CL11: 0.6846256 | CM11: 0.69872609 | CN11: 0.71282657 | CO11: 0.73866147 | CP11: 0.76449637 | CQ11: 0.78100851 | CR11: 0.79752065 | CS11: 0.75058171 | CT11: 0.70364278 | CU11: 0.68316098 | CV11: 0.66267919 | CW11: 0.63664227 | CX11: 0.61060536 | CY11: 0.60200399 | CZ11: 0.59340263 | DA11: 0.59078556 | DB11: 0.5881685 | DC11: 0.61740063 | DD11: 0.64663276 | DE11: 0.66788558 | DF11: 0.6891384 | DG11: 0.66413427 | DH11: 0.63913014 | DI11: 0.63765497 | DJ11: 0.63617981 | DK11: 0.65578833 | DL11: 0.67539684 | DM11: 0.62797217 | DN11: 0.5805475 | DO11: 0.57859865 | DP11: 0.57664979 | DQ11: 0.54721447 | DR11: 0.51777914 | DS11: 0.54331638 | DT11: 0.56885361
A12: 0 | B12: 1 | C12: ZC_10 | D12: 0.93039436 | E12: 0.92334566 | F12: 0.91439073 | G12: 0.88684219 | H12: 0.85929365 | I12: 0.77362745 | J12: 0.68796125 | K12: 0.67582524 | L12: 0.66368924 | M12: 0.65205072 | N12: 0.6404122 | O12: 0.64131057 | P12: 0.64220893 | Q12: 0.68236603 | R12: 0.72252312 | S12: 0.7442798 | T12: 0.76603648 | U12: 0.81956479 | V12: 0.87309311 | W12: 0.8737737 | X12: 0.87445429 | Y12: 0.84259072 | Z12: 0.81072715 | AA12: 0.83848609 | AB12: 0.86624502 | AC12: 0.87207953 | AD12: 0.87791403 | AE12: 0.8862603 | AF12: 0.89460658 | AG12: 0.82810092 | AH12: 0.76159527 | AI12: 0.77897337 | AJ12: 0.79635148 | AK12: 0.79488831 | AL12: 0.79342515 | AM12: 0.75720729 | AN12: 0.72098943 | AO12: 0.69956716 | AP12: 0.67814488 | AQ12: 0.65751067 | AR12: 0.63687646 | AS12: 0.69640096 | AT12: 0.75592546 | AU12: 0.73860911 | AV12: 0.72129276 | AW12: 0.71053079 | AX12: 0.69976882 | AY12: 0.6881707 | AZ12: 0.67657257 | BA12: 0.71944961 | BB12: 0.76232665 | BC12: 0.69687666 | BD12: 0.63142666 | BE12: 0.5810025 | BF12: 0.53057835 | BG12: 0.54427034 | BH12: 0.55796233 | BI12: 0.55208081 | BJ12: 0.54619928 | BK12: 0.54113244 | BL12: 0.53606559 | BM12: 0.55163785 | BN12: 0.5672101 | BO12: 0.55913055 | BP12: 0.55105099 | BQ12: 0.5587905 | BR12: 0.56653001 | BS12: 0.57014048 | BT12: 0.57375095 | BU12: 0.60003164 | BV12: 0.62631233 | BW12: 0.65184067 | BX12: 0.677369 | BY12: 0.72885964 | BZ12: 0.78035028 | CA12: 0.74325199 | CB12: 0.70615369 | CC12: 0.68981303 | CD12: 0.67347237 | CE12: 0.64234329 | CF12: 0.61121421 | CG12: 0.61895922 | CH12: 0.62670424 | CI12: 0.65386069 | CJ12: 0.68101715 | CK12: 0.66630516 | CL12: 0.65159317 | CM12: 0.66642628 | CN12: 0.68125939 | CO12: 0.70841559 | CP12: 0.73557179 | CQ12: 0.75338333 | CR12: 0.77119486 | CS12: 0.72124566 | CT12: 0.67129645 | CU12: 0.64981511 | CV12: 0.62833377 | CW12: 0.60123272 | CX12: 0.57413168 | CY12: 0.56508592 | CZ12: 0.55604015 | DA12: 0.55338222 | DB12: 0.55072429 | DC12: 0.58093574 | DD12: 0.61114719 | DE12: 0.63367452 | DF12: 0.65620186 | DG12: 0.62969687 | DH12: 0.60319188 | DI12: 0.60192287 | DJ12: 0.60065387 | DK12: 0.62102433 | DL12: 0.64139479 | DM12: 0.59195239 | DN12: 0.54250998 | DO12: 0.54058664 | DP12: 0.5386633 | DQ12: 0.50839447 | DR12: 0.47812565 | DS12: 0.50437137 | DT12: 0.53061708
A13: 0 | B13: 1 | C13: ZC_11 | D13: 0.91347174 | E13: 0.90643746 | F13: 0.89721476 | G13: 0.86808877 | H13: 0.83896277 | I13: 0.74907109 | J13: 0.65917941 | K13: 0.64727361 | L13: 0.63536781 | M13: 0.62392249 | N13: 0.61247717 | O13: 0.61383096 | P13: 0.61518474 | Q13: 0.65727531 | R13: 0.69936588 | S13: 0.72196079 | T13: 0.74455571 | U13: 0.80070343 | V13: 0.85685115 | W13: 0.85636199 | X13: 0.85587283 | Y13: 0.82108916 | Z13: 0.7863055 | AA13: 0.81492407 | AB13: 0.84354264 | AC13: 0.84935971 | AD13: 0.85517679 | AE13: 0.86351057 | AF13: 0.87184435 | AG13: 0.8015236 | AH13: 0.73120286 | AI13: 0.74946065 | AJ13: 0.76771844 | AK13: 0.76635006 | AL13: 0.76498168 | AM13: 0.72716838 | AN13: 0.68935509 | AO13: 0.66730167 | AP13: 0.64524825 | AQ13: 0.62407454 | AR13: 0.60290083 | AS13: 0.66507408 | AT13: 0.72724732 | AU13: 0.70925018 | AV13: 0.69125303 | AW13: 0.68023439 | AX13: 0.66921575 | AY13: 0.65710509 | AZ13: 0.64499442 | BA13: 0.69000363 | BB13: 0.73501283 | BC13: 0.66670842 | BD13: 0.598404 | BE13: 0.54664427 | BF13: 0.49488454 | BG13: 0.50882193 | BH13: 0.52275932 | BI13: 0.51689651 | BJ13: 0.51103369 | BK13: 0.50570091 | BL13: 0.50036813 | BM13: 0.51646856 | BN13: 0.53256898 | BO13: 0.524232 | BP13: 0.51589502 | BQ13: 0.52376783 | BR13: 0.53164063 | BS13: 0.5354251 | BT13: 0.53920957 | BU13: 0.56625633 | BV13: 0.5933031 | BW13: 0.61992781 | BX13: 0.64655251 | BY13: 0.70038272 | BZ13: 0.75421293 | CA13: 0.71534357 | CB13: 0.67647421 | CC13: 0.6593663 | CD13: 0.64225839 | CE13: 0.60994692 | CF13: 0.57763546 | CG13: 0.58546135 | CH13: 0.59328723 | CI13: 0.62166547 | CJ13: 0.65004371 | CK13: 0.63472524 | CL13: 0.61940676 | CM13: 0.63466351 | CN13: 0.64992025 | CO13: 0.67855088 | CP13: 0.7071815 | CQ13: 0.72573486 | CR13: 0.74428823 | CS13: 0.69197701 | CT13: 0.6396658 | CU13: 0.6173882 | CV13: 0.5951106 | CW13: 0.56704921 | CX13: 0.53898782 | CY13: 0.52976507 | CZ13: 0.52054233 | DA13: 0.51770959 | DB13: 0.51487686 | DC13: 0.54612402 | DD13: 0.57737118 | DE13: 0.60036465 | DF13: 0.62335813 | DG13: 0.59621403 | DH13: 0.56906994 | DI13: 0.56763065 | DJ13: 0.56619136 | DK13: 0.58712489 | DL13: 0.60805843 | DM13: 0.55729937 | DN13: 0.50654032 | DO13: 0.50448295 | DP13: 0.50242558 | DQ13: 0.47182204 | DR13: 0.4412185 | DS13: 0.46771869 | DT13: 0.49421888
... A481: 8 | B481: 10 | C481: PROP_TOTAL_RETURN | D481: 0 | E481: 0 | F481: -0.18256564 | G481: 0 | H481: 0.070399834 | I481: 0 | J481: 0.44142503 | K481: 0 | L481: 0.0017892965 | M481: 0 | N481: 0.19718805 | O481: 0 | P481: 0.19062456 | Q481: 0 | R481: -0.13692579 | S481: 0 | T481: -0.10136496 | U481: 0 | V481: 0.13784138 | W481: 0 | X481: 0.017423594 | Y481: 0 | Z481: 0.071447568 | AA481: 0 | AB481: -0.15567354 | AC481: 0 | AD481: -0.17527456 | AE481: 0 | AF481: -0.01814679 | AG481: 0 | AH481: -0.048922741 | AI481: 0 | AJ481: -0.092221296 | AK481: 0 | AL481: -0.21525938 | AM481: 0 | AN481: 0.087352092 | AO481: 0 | AP481: -0.11876179 | AQ481: 0 | AR481: -0.052757636 | AS481: 0 | AT481: 0.0629038 | AU481: 0 | AV481: 0.020867257 | AW481: 0 | AX481: 0.11516553 | AY481: 0 | AZ481: -0.033149879 | BA481: 0 | BB481: -0.16433016 | BC481: 0 | BD481: -0.076240221 | BE481: 0 | BF481: -0.14248177 | BG481: 0 | BH481: 0.11176595 | BI481: 0 | BJ481: -0.11422413 | BK481: 0 | BL481: -0.0028076489 | BM481: 0 | BN481: -0.13954493 | BO481: 0 | BP481: -0.11854748 | BQ481: 0 | BR481: -0.041218463 | BS481: 0 | BT481: -0.055593821 | BU481: 0 | BV481: 0.032182713 | BW481: 0 | BX481: -0.17965817 | BY481: 0 | BZ481: -0.082674659 | CA481: 0 | CB481: 0.12636789 | CC481: 0 | CD481: -0.1445577 | CE481: 0 | CF481: 0.11251565 | CG481: 0 | CH481: -0.10750173 | CI481: 0 | CJ481: -0.23399973 | CK481: 0 | CL481: 0.16235194 | CM481: 0 | CN481: -0.20356174 | CO481: 0 | CP481: -0.069129317 | CQ481: 0 | CR481: -0.13611795 | CS481: 0 | CT481: -0.16687548 | CU481: 0 | CV481: -0.031580594 | CW481: 0 | CX481: -0.13454032 | CY481: 0 | CZ481: -0.17900507 | DA481: 0 | DB481: -0.11935894 | DC481: 0 | DD481: -0.10630694 | DE481: 0 | DF481: 0.093209524 | DG481: 0 | DH481: 0.25409069 | DI481: 0 | DJ481: 0.27190132 | DK481: 0 | DL481: -0.060204676 | DM481: 0 | DN481: 0.14668686 | DO481: 0 | DP481: -0.030329249 | DQ481: 0 | DR481: -0.058079294 | DS481: 0 | DT481: -0.070138882

Sheet ZC_1
A1: ZC_1 | B1: 1.0016623 | C1: 1.001471 | D1: 1.0012205 | E1: 0.99851264 | F1: 0.99580476 | G1: 0.98416337 | H1: 0.97252197 | I1: 0.97048214 | J1: 0.96844231 | K1: 0.96594474 | L1: 0.96344717 | M1: 0.96278986 | N1: 0.96213255 | O1: 0.96724475 | P1: 0.97235696 | Q1: 0.97468001 | R1: 0.97700306 | S1: 0.98337115 | T1: 0.98973925 | U1: 0.98955314 | V1: 0.98936704 | W1: 0.98543799 | X1: 0.98150894 | Y1: 0.98505906 | Z1: 0.98860919 | AA1: 0.9900223 | AB1: 0.99143541 | AC1: 0.99366715 | AD1: 0.99589889 | AE1: 0.98893635 | AF1: 0.98197381 | AG1: 0.98564249 | AH1: 0.98931117 | AI1: 0.98980808 | AJ1: 0.990305 | AK1: 0.98569922 | AL1: 0.98109345 | AM1: 0.97774894 | AN1: 0.97440442 | AO1: 0.97067967 | AP1: 0.96695492 | AQ1: 0.97550472 | AR1: 0.98405452 | AS1: 0.9811135 | AT1: 0.97817248 | AU1: 0.97649856 | AV1: 0.97482463 | AW1: 0.97264979 | AX1: 0.97047494 | AY1: 0.97662424 | AZ1: 0.98277353 | BA1: 0.97284214 | BB1: 0.96291075 | BC1: 0.95397943 | BD1: 0.94504811 | BE1: 0.94743782 | BF1: 0.94982753 | BG1: 0.94874264 | BH1: 0.94765775 | BI1: 0.94668339 | BJ1: 0.94570904 | BK1: 0.94840809 | BL1: 0.95110714 | BM1: 0.94960836 | BN1: 0.94810958 | BO1: 0.94964661 | BP1: 0.95118363 | BQ1: 0.9516832 | BR1: 0.95218278 | BS1: 0.95663588 | BT1: 0.96108899 | BU1: 0.96512899 | BV1: 0.969169 | BW1: 0.97653336 | BX1: 0.98389772 | BY1: 0.97858902 | BZ1: 0.97328032 | CA1: 0.97107809 | CB1: 0.96887585 | CC1: 0.96362124 | CD1: 0.95836663 | CE1: 0.95991775 | CF1: 0.96146888 | CG1: 0.96568574 | CH1: 0.9699026 | CI1: 0.96755645 | CJ1: 0.9652103 | CK1: 0.96763562 | CL1: 0.97006093 | CM1: 0.97400524 | CN1: 0.97794954 | CO1: 0.98058792 | CP1: 0.9832263 | CQ1: 0.97580792 | CR1: 0.96838955 | CS1: 0.96520592 | CT1: 0.96202229 | CU1: 0.95743814 | CV1: 0.95285398 | CW1: 0.95126902 | CX1: 0.94968406 | CY1: 0.94898597 | CZ1: 0.94828789 | DA1: 0.95384332 | DB1: 0.95939875 | DC1: 0.9630709 | DD1: 0.96674305 | DE1: 0.9622728 | DF1: 0.95780256 | DG1: 0.95788687 | DH1: 0.95797119 | DI1: 0.96115034 | DJ1: 0.96432949 | DK1: 0.95592877 | DL1: 0.94752805 | DM1: 0.94727171 | DN1: 0.94701537 | DO1: 0.94091323 | DP1: 0.93481108 | DQ1: 0.94011401 | DR1: 0.94541693
A2: ZC_1 | B2: 1.0016623 | C2: 0.99623495 | D2: 0.99074842 | E2: 0.98527207 | F2: 0.97979572 | G2: 0.98325853 | H2: 0.98672135 | I2: 0.98207878 | J2: 0.9774362 | K2: 0.96943093 | L2: 0.96142565 | M2: 0.9663443 | N2: 0.97126294 | O2: 0.96786698 | P2: 0.96447103 | Q2: 0.95488786 | R2: 0.9453047 | S2: 0.94259288 | T2: 0.93988107 | U2: 0.93440586 | V2: 0.92893066 | W2: 0.93344566 | X2: 0.93796066 | Y2: 0.93057544 | Z2: 0.92319022 | AA2: 0.92487391 | AB2: 0.92655761 | AC2: 0.93024194 | AD2: 0.93392628 | AE2: 0.93528943 | AF2: 0.93665258 | AG2: 0.93106771 | AH2: 0.92548285 | AI2: 0.91827168 | AJ2: 0.9110605 | AK2: 0.91030275 | AL2: 0.909545 | AM2: 0.90486718 | AN2: 0.90018935 | AO2: 0.89757419 | AP2: 0.89495903 | AQ2: 0.88936491 | AR2: 0.88377078 | AS2: 0.87862747 | AT2: 0.87348416 | AU2: 0.8740502 | AV2: 0.87461623 | AW2: 0.87706592 | AX2: 0.8795156 | AY2: 0.88242674 | AZ2: 0.88533788 | BA2: 0.87822138 | BB2: 0.87110488 | BC2: 0.87723682 | BD2: 0.88336877 | BE2: 0.88447014 | BF2: 0.88557152 | BG2: 0.88270247 | BH2: 0.87983342 | BI2: 0.88181413 | BJ2: 0.88379485 | BK2: 0.88598222 | BL2: 0.88816958 | BM2: 0.88505798 | BN2: 0.88194639 | BO2: 0.87956678 | BP2: 0.87718718 | BQ2: 0.87536883 | BR2: 0.87355048 | BS2: 0.86588865 | BT2: 0.85822683 | BU2: 0.85857253 | BV2: 0.85891824 | BW2: 0.861713 | BX2: 0.86450777 | BY2: 0.86527462 | BZ2: 0.86604147 | CA2: 0.8652417 | CB2: 0.86444193 | CC2: 0.86053996 | CD2: 0.856638 | CE2: 0.85743897 | CF2: 0.85823994 | CG2: 0.85669816 | CH2: 0.85515639 | CI2: 0.86131012 | CJ2: 0.86746384 | CK2: 0.86934372 | CL2: 0.8712236 | CM2: 0.86966895 | CN2: 0.86811429 | CO2: 0.86813821 | CP2: 0.86816213 | CQ2: 0.86577051 | CR2: 0.86337888 | CS2: 0.86514056 | CT2: 0.86690223 | CU2: 0.86589894 | CV2: 0.86489564 | CW2: 0.86839022 | CX2: 0.87188481 | CY2: 0.8671568 | CZ2: 0.86242879 | DA2: 0.86126256 | DB2: 0.86009634 | DC2: 0.86760737 | DD2: 0.8751184 | DE2: 0.87877884 | DF2: 0.88243929 | DG2: 0.87692371 | DH2: 0.87140814 | DI2: 0.87162217 | DJ2: 0.8718362 | DK2: 0.87449576 | DL2: 0.87715531 | DM2: 0.87645957 | DN2: 0.87576383 | DO2: 0.87377243 | DP2: 0.87178103 | DQ2: 0.87333473 | DR2: 0.87488843
A3: ZC_1 | B3: 1.0016623 | C3: 1.0018048 | D3: 1.0018881 | E3: 1.0040796 | F3: 1.0062711 | G3: 1.0079076 | H3: 1.0095442 | I3: 1.0109328 | J3: 1.0123214 | K3: 1.0083291 | L3: 1.0043369 | M3: 1.0081107 | N3: 1.0118845 | O3: 1.0119777 | P3: 1.0120709 | Q3: 1.0076486 | R3: 1.0032263 | S3: 0.99402483 | T3: 0.9848234 | U3: 0.98404036 | V3: 0.98325733 | W3: 0.98505011 | X3: 0.98684289 | Y3: 0.98114827 | Z3: 0.97545366 | AA3: 0.96989027 | AB3: 0.96432688 | AC3: 0.96257573 | AD3: 0.96082458 | AE3: 0.9574612 | AF3: 0.95409783 | AG3: 0.95524551 | AH3: 0.95639319 | AI3: 0.95665306 | AJ3: 0.95691293 | AK3: 0.95479441 | AL3: 0.95267588 | AM3: 0.95040236 | AN3: 0.94812885 | AO3: 0.94951344 | AP3: 0.95089803 | AQ3: 0.94375592 | AR3: 0.9366138 | AS3: 0.93354118 | AT3: 0.93046855 | AU3: 0.93407348 | AV3: 0.93767842 | AW3: 0.94021545 | AX3: 0.94275248 | AY3: 0.94382527 | AZ3: 0.94489806 | BA3: 0.94789383 | BB3: 0.9508896 | BC3: 0.95481552 | BD3: 0.95874144 | BE3: 0.95565608 | BF3: 0.95257073 | BG3: 0.94842792 | BH3: 0.94428511 | BI3: 0.94281526 | BJ3: 0.9413454 | BK3: 0.94289453 | BL3: 0.94444366 | BM3: 0.94672836 | BN3: 0.94901307 | BO3: 0.94504608 | BP3: 0.9410791 | BQ3: 0.93904241 | BR3: 0.93700572 | BS3: 0.94309199 | BT3: 0.94917826 | BU3: 0.95441923 | BV3: 0.95966019 | BW3: 0.95611656 | BX3: 0.95257293 | BY3: 0.94414675 | BZ3: 0.93572058 | CA3: 0.93706575 | CB3: 0.93841093 | CC3: 0.9368234 | CD3: 0.93523588 | CE3: 0.9257569 | CF3: 0.91627793 | CG3: 0.92250721 | CH3: 0.92873648 | CI3: 0.93182456 | CJ3: 0.93491264 | CK3: 0.93366937 | CL3: 0.93242611 | CM3: 0.93169507 | CN3: 0.93096403 | CO3: 0.92937812 | CP3: 0.92779222 | CQ3: 0.92451397 | CR3: 0.92123572 | CS3: 0.9169265 | CT3: 0.91261729 | CU3: 0.90901452 | CV3: 0.90541176 | CW3: 0.90517669 | CX3: 0.90494163 | CY3: 0.90412984 | CZ3: 0.90331804 | DA3: 0.90105149 | DB3: 0.89878494 | DC3: 0.89717345 | DD3: 0.89556196 | DE3: 0.8954363 | DF3: 0.89531065 | DG3: 0.90269176 | DH3: 0.91007288 | DI3: 0.90921751 | DJ3: 0.90836214 | DK3: 0.90223642 | DL3: 0.8961107 | DM3: 0.89099944 | DN3: 0.88588818 | DO3: 0.88215036 | DP3: 0.87841253 | DQ3: 0.88102971 | DR3: 0.88364689
A4: ZC_1 | B4: 1.0016623 | C4: 0.99825139 | D4: 0.9947813 | E4: 0.99785101 | F4: 1.0009207 | G4: 0.99722347 | H4: 0.99352622 | I4: 0.99272509 | J4: 0.99192396 | K4: 0.99515614 | L4: 0.99838831 | M4: 0.9936683 | N4: 0.98894829 | O4: 0.98468439 | P4: 0.98042049 | Q4: 0.97859653 | R4: 0.97677257 | S4: 0.97708944 | T4: 0.97740632 | U4: 0.97691606 | V4: 0.97642579 | W4: 0.97952596 | X4: 0.98262612 | Y4: 0.98109667 | Z4: 0.97956722 | AA4: 0.97340108 | AB4: 0.96723493 | AC4: 0.96497574 | AD4: 0.96271656 | AE4: 0.96772734 | AF4: 0.97273813 | AG4: 0.96299384 | AH4: 0.95324954 | AI4: 0.95292249 | AJ4: 0.95259543 | AK4: 0.9492512 | AL4: 0.94590697 | AM4: 0.94247485 | AN4: 0.93904274 | AO4: 0.93818275 | AP4: 0.93732276 | AQ4: 0.93034044 | AR4: 0.92335811 | AS4: 0.92032217 | AT4: 0.91728623 | AU4: 0.90960013 | AV4: 0.90191403 | AW4: 0.8993561 | AX4: 0.89679817 | AY4: 0.89503496 | AZ4: 0.89327175 | BA4: 0.89870665 | BB4: 0.90414156 | BC4: 0.90851368 | BD4: 0.91288579 | BE4: 0.91182183 | BF4: 0.91075786 | BG4: 0.91091193 | BH4: 0.91106599 | BI4: 0.90980018 | BJ4: 0.90853437 | BK4: 0.90391856 | BL4: 0.89930275 | BM4: 0.8994559 | BN4: 0.89960906 | BO4: 0.89446637 | BP4: 0.88932368 | BQ4: 0.88781592 | BR4: 0.88630816 | BS4: 0.88547961 | BT4: 0.88465106 | BU4: 0.88734689 | BV4: 0.89004273 | BW4: 0.8948127 | BX4: 0.89958268 | BY4: 0.90802836 | BZ4: 0.91647403 | CA4: 0.91781024 | CB4: 0.91914645 | CC4: 0.91921655 | CD4: 0.91928665 | CE4: 0.92358317 | CF4: 0.9278797 | CG4: 0.93007858 | CH4: 0.93227747 | CI4: 0.9384056 | CJ4: 0.94453373 | CK4: 0.94286084 | CL4: 0.94118796 | CM4: 0.93808469 | CN4: 0.93498143 | CO4: 0.9388523 | CP4: 0.94272316 | CQ4: 0.93946236 | CR4: 0.93620155 | CS4: 0.93453454 | CT4: 0.93286753 | CU4: 0.93518815 | CV4: 0.93750877 | CW4: 0.93618613 | CX4: 0.93486349 | CY4: 0.93398784 | CZ4: 0.93311218 | DA4: 0.93111836 | DB4: 0.92912453 | DC4: 0.93072842 | DD4: 0.9323323 | DE4: 0.93191275 | DF4: 0.93149321 | DG4: 0.93101254 | DH4: 0.93053188 | DI4: 0.93492916 | DJ4: 0.93932645 | DK4: 0.93927479 | DL4: 0.93922313 | DM4: 0.9356265 | DN4: 0.93202987 | DO4: 0.92850695 | DP4: 0.92498402 | DQ4: 0.92152973 | DR4: 0.91807545
A5: ZC_1 | B5: 1.0016623 | C5: 0.99792522 | D5: 0.99412896 | E5: 0.99848306 | F5: 1.0028372 | G5: 1.0116264 | H5: 1.0204156 | I5: 1.0126768 | J5: 1.0049379 | K5: 1.0020592 | L5: 0.99918041 | M5: 0.99234271 | N5: 0.985505 | O5: 0.98092868 | P5: 0.97635235 | Q5: 0.96786698 | R5: 0.9593816 | S5: 0.95404565 | T5: 0.9487097 | U5: 0.94572949 | V5: 0.94274928 | W5: 0.94072546 | X5: 0.93870165 | Y5: 0.9357966 | Z5: 0.93289155 | AA5: 0.93269458 | AB5: 0.93249762 | AC5: 0.93244863 | AD5: 0.93239964 | AE5: 0.93707974 | AF5: 0.94175983 | AG5: 0.94539114 | AH5: 0.94902244 | AI5: 0.94563838 | AJ5: 0.94225432 | AK5: 0.94231479 | AL5: 0.94237527 | AM5: 0.94120737 | AN5: 0.94003948 | AO5: 0.93497956 | AP5: 0.92991965 | AQ5: 0.93038653 | AR5: 0.93085341 | AS5: 0.92712889 | AT5: 0.92340437 | AU5: 0.91879317 | AV5: 0.91418198 | AW5: 0.90654914 | AX5: 0.89891631 | AY5: 0.89623104 | AZ5: 0.89354576 | BA5: 0.89063212 | BB5: 0.88771849 | BC5: 0.88943519 | BD5: 0.8911519 | BE5: 0.88655575 | BF5: 0.8819596 | BG5: 0.88428751 | BH5: 0.88661542 | BI5: 0.88264942 | BJ5: 0.87868341 | BK5: 0.87731937 | BL5: 0.87595533 | BM5: 0.87123517 | BN5: 0.866515 | BO5: 0.86539024 | BP5: 0.86426549 | BQ5: 0.85889327 | BR5: 0.85352106 | BS5: 0.85940524 | BT5: 0.86528943 | BU5: 0.86421009 | BV5: 0.86313075 | BW5: 0.86106256 | BX5: 0.85899437 | BY5: 0.85635707 | BZ5: 0.85371977 | CA5: 0.8521458 | CB5: 0.85057183 | CC5: 0.85114396 | CD5: 0.85171609 | CE5: 0.85223365 | CF5: 0.8527512 | CG5: 0.85528133 | CH5: 0.85781145 | CI5: 0.85873281 | CJ5: 0.85965416 | CK5: 0.85689267 | CL5: 0.85413118 | CM5: 0.85401885 | CN5: 0.85390651 | CO5: 0.84933032 | CP5: 0.84475412 | CQ5: 0.83649193 | CR5: 0.82822975 | CS5: 0.82503379 | CT5: 0.82183784 | CU5: 0.8219082 | CV5: 0.82197855 | CW5: 0.82279619 | CX5: 0.82361384 | CY5: 0.82330576 | CZ5: 0.82299767 | DA5: 0.82415416 | DB5: 0.82531064 | DC5: 0.82270818 | DD5: 0.82010572 | DE5: 0.81653918 | DF5: 0.81297263 | DG5: 0.81280591 | DH5: 0.81263918 | DI5: 0.81203987 | DJ5: 0.81144057 | DK5: 0.80848105 | DL5: 0.80552152 | DM5: 0.80568137 | DN5: 0.80584122 | DO5: 0.81041277 | DP5: 0.81498433 | DQ5: 0.81603114 | DR5: 0.81707796
A6: ZC_1 | B6: 1.0016623 | C6: 1.0010891 | D6: 1.0004567 | E6: 1.0018532 | F6: 1.0032497 | G6: 1.012654 | H6: 1.0220582 | I6: 1.0214895 | J6: 1.0209209 | K6: 1.0201755 | L6: 1.0194302 | M6: 1.016891 | N6: 1.0143519 | O6: 1.0058968 | P6: 0.9974417 | Q6: 0.99264543 | R6: 0.98784917 | S6: 0.97962737 | T6: 0.97140556 | U6: 0.96997317 | V6: 0.96854077 | W6: 0.9711603 | X6: 0.97377984 | Y6: 0.96893777 | Z6: 0.96409571 | AA6: 0.96238799 | AB6: 0.96068027 | AC6: 0.95899111 | AD6: 0.95730195 | AE6: 0.96470424 | AF6: 0.97210653 | AG6: 0.96852158 | AH6: 0.96493662 | AI6: 0.96296299 | AJ6: 0.96098935 | AK6: 0.9633961 | AL6: 0.96580284 | AM6: 0.96589318 | AN6: 0.96598352 | AO6: 0.9659902 | AP6: 0.96599688 | AQ6: 0.95450842 | AR6: 0.94301997 | AS6: 0.94256722 | AT6: 0.94211447 | AU6: 0.9413933 | AV6: 0.94067212 | AW6: 0.93991918 | AX6: 0.93916624 | AY6: 0.93134169 | AZ6: 0.92351714 | BA6: 0.93081594 | BB6: 0.93811473 | BC6: 0.94496932 | BD6: 0.95182391 | BE6: 0.94745003 | BF6: 0.94307615 | BG6: 0.94247541 | BH6: 0.94187468 | BI6: 0.94120756 | BJ6: 0.94054044 | BK6: 0.93598952 | BL6: 0.93143859 | BM6: 0.9313595 | BN6: 0.93128042 | BO6: 0.9285911 | BP6: 0.92590178 | BQ6: 0.92365659 | BR6: 0.92141141 | BS6: 0.91575535 | BT6: 0.91009928 | BU6: 0.90498131 | BV6: 0.89986333 | BW6: 0.89186653 | BX6: 0.88386974 | BY6: 0.88712193 | BZ6: 0.89037412 | CA6: 0.89156143 | CB6: 0.89274874 | CC6: 0.8957618 | CD6: 0.89877487 | CE6: 0.8965864 | CF6: 0.89439794 | CG6: 0.88908461 | CH6: 0.88377129 | CI6: 0.88451562 | CJ6: 0.88525996 | CK6: 0.88207779 | CL6: 0.87889561 | CM6: 0.87403661 | CN6: 0.86917762 | CO6: 0.86597138 | CP6: 0.86276515 | CQ6: 0.86769773 | CR6: 0.87263032 | CS6: 0.87470056 | CT6: 0.87677081 | CU6: 0.87977265 | CV6: 0.88277449 | CW6: 0.88305075 | CX6: 0.88332701 | CY6: 0.88235355 | CZ6: 0.88138008 | DA6: 0.87560689 | DB6: 0.86983369 | DC6: 0.86544158 | DD6: 0.86104947 | DE6: 0.863524 | DF6: 0.86599852 | DG6: 0.86536323 | DH6: 0.86472794 | DI6: 0.86038497 | DJ6: 0.85604199 | DK6: 0.86263329 | DL6: 0.86922458 | DM6: 0.8684899 | DN6: 0.86775522 | DO6: 0.87193789 | DP6: 0.87612057 | DQ6: 0.87027975 | DR6: 0.86443893
A7: ZC_1 | B7: 1.0016623 | C7: 1.0063764 | D7: 1.0110314 | E7: 1.0153367 | F7: 1.019642 | G7: 1.0134961 | H7: 1.0073503 | I7: 1.0094386 | J7: 1.0115269 | K7: 1.0165503 | L7: 1.0215736 | M7: 1.013195 | N7: 1.0048165 | O7: 1.0052068 | P7: 1.0055972 | Q7: 1.0132857 | R7: 1.0209741 | S7: 1.0219551 | T7: 1.022936 | U7: 1.0272451 | V7: 1.0315542 | W7: 1.0252727 | X7: 1.0189912 | Y7: 1.0257022 | Z7: 1.0324133 | AA7: 1.0301803 | AB7: 1.0279473 | AC7: 1.0243865 | AD7: 1.0208257 | AE7: 1.0199845 | AF7: 1.0191433 | AG7: 1.0253146 | AH7: 1.031486 | AI7: 1.0380313 | AJ7: 1.0445767 | AK7: 1.0431767 | AL7: 1.0417768 | AM7: 1.0436998 | AN7: 1.0456229 | AO7: 1.0446652 | AP7: 1.0437075 | AQ7: 1.0468672 | AR7: 1.0500269 | AS7: 1.0525276 | AT7: 1.0550282 | AU7: 1.0517385 | AV7: 1.0484488 | AW7: 1.0423717 | AX7: 1.0362946 | AY7: 1.0307246 | AZ7: 1.0251546 | BA7: 1.0310687 | BB7: 1.0369828 | BC7: 1.0276329 | BD7: 1.018283 | BE7: 1.0148938 | BF7: 1.0115046 | BG7: 1.0129931 | BH7: 1.0144816 | BI7: 1.0104558 | BJ7: 1.0064299 | BK7: 1.0019361 | BL7: 0.99744228 | BM7: 0.99929345 | BN7: 1.0011446 | BO7: 1.0025761 | BP7: 1.0040076 | BQ7: 1.0041798 | BR7: 1.0043519 | BS7: 1.0117652 | BT7: 1.0191786 | BU7: 1.0172742 | BV7: 1.0153698 | BW7: 1.0106517 | BX7: 1.0059336 | BY7: 1.0032798 | BZ7: 1.000626 | CA7: 1.0006142 | CB7: 1.0006024 | CC7: 1.0030549 | CD7: 1.0055074 | CE7: 1.0037417 | CF7: 1.001976 | CG7: 1.0021665 | CH7: 1.0023571 | CI7: 0.9936844 | CJ7: 0.9850117 | CK7: 0.9818075 | CL7: 0.9786033 | CM7: 0.97887535 | CN7: 0.9791474 | CO7: 0.9781307 | CP7: 0.97711401 | CQ7: 0.97794011 | CR7: 0.97876622 | CS7: 0.97586995 | CT7: 0.97297369 | CU7: 0.97276238 | CV7: 0.97255108 | CW7: 0.96734917 | CX7: 0.96214727 | CY7: 0.96563657 | CZ7: 0.96912588 | DA7: 0.96969311 | DB7: 0.97026033 | DC7: 0.96073072 | DD7: 0.95120111 | DE7: 0.9455794 | DF7: 0.9399577 | DG7: 0.94529255 | DH7: 0.9506274 | DI7: 0.94874354 | DJ7: 0.94685968 | DK7: 0.94291036 | DL7: 0.93896104 | DM7: 0.93865811 | DN7: 0.93835518 | DO7: 0.93890977 | DP7: 0.93946436 | DQ7: 0.93679471 | DR7: 0.93412506
A8: ZC_1 | B8: 1.0016623 | C8: 1.0007558 | D8: 0.99979007 | E8: 0.99630247 | F8: 0.99281486 | G8: 0.98869595 | H8: 0.98457705 | I8: 0.98062304 | J8: 0.97666903 | K8: 0.9772975 | L8: 0.97792596 | M8: 0.9712023 | N8: 0.96447863 | O8: 0.96139022 | P8: 0.95830181 | Q8: 0.96016485 | R8: 0.9620279 | S8: 0.96914117 | T8: 0.97625444 | U8: 0.97540674 | V8: 0.97455904 | W8: 0.97153776 | X8: 0.96851649 | Y8: 0.97280728 | Z8: 0.97709806 | AA8: 0.98239217 | AB8: 0.98768628 | AC8: 0.98996697 | AD8: 0.99224767 | AE8: 0.99637817 | AF8: 1.0005087 | AG8: 0.99932866 | AH8: 0.99814865 | AI8: 0.99633616 | AJ8: 0.99452367 | AK8: 0.99456783 | AL8: 0.99461198 | AM8: 0.99368295 | AN8: 0.99275391 | AO8: 0.98753131 | AP8: 0.98230872 | AQ8: 0.98654695 | AR8: 0.99078517 | AS8: 0.99060033 | AT8: 0.99041548 | AU8: 0.9841762 | AV8: 0.97793693 | AW8: 0.97236009 | AX8: 0.96678325 | AY8: 0.96365941 | AZ8: 0.96053558 | BA8: 0.95525498 | BB8: 0.94997439 | BC8: 0.94410189 | BD8: 0.93822939 | BE8: 0.93929484 | BF8: 0.94036028 | BG8: 0.9427995 | BH8: 0.94523871 | BI8: 0.94506953 | BJ8: 0.94490035 | BK8: 0.94145533 | BL8: 0.93801031 | BM8: 0.93420206 | BN8: 0.93039381 | BO8: 0.93311858 | BP8: 0.93584335 | BQ8: 0.93608962 | BR8: 0.93633588 | BS8: 0.92892776 | BT8: 0.92151963 | BU8: 0.91514963 | BV8: 0.90877964 | BW8: 0.91085745 | BX8: 0.91293527 | BY8: 0.91952446 | BZ8: 0.92611366 | CA8: 0.92392246 | CB8: 0.92173127 | CC8: 0.92136755 | CD8: 0.92100384 | CE8: 0.92975681 | CF8: 0.93850977 | CG8: 0.93072705 | CH8: 0.92294433 | CI8: 0.91844643 | CJ8: 0.91394853 | CK8: 0.91415918 | CL8: 0.91436982 | CM8: 0.9137073 | CN8: 0.91304479 | CO8: 0.91367938 | CP8: 0.91431397 | CQ8: 0.91580511 | CR8: 0.91729625 | CS8: 0.92076575 | CT8: 0.92423525 | CU8: 0.9266329 | CV8: 0.92903055 | CW8: 0.92801566 | CX8: 0.92700077 | CY8: 0.92612928 | CZ8: 0.92525779 | DA8: 0.92687641 | DB8: 0.92849504 | DC8: 0.92899124 | DD8: 0.92948744 | DE8: 0.92796595 | DF8: 0.92644447 | DG8: 0.91834208 | DH8: 0.91023969 | DI8: 0.9095127 | DJ8: 0.90878571 | DK8: 0.91394248 | DL8: 0.91909925 | DM8: 0.92336524 | DN8: 0.92763122 | DO8: 0.93000159 | DP8: 0.93237196 | DQ8: 0.92861912 | DR8: 0.92486628
A9: ZC_1 | B9: 1.0016623 | C9: 1.0043271 | D9: 1.0069326 | E9: 1.0025273 | F9: 0.99812187 | G9: 0.99928631 | H9: 1.0004507 | I9: 0.99860177 | J9: 0.9967528 | K9: 0.9902527 | L9: 0.9837526 | M9: 0.98529997 | N9: 0.98684734 | O9: 0.98804276 | P9: 0.98923818 | Q9: 0.98866023 | R9: 0.98808227 | S9: 0.98587252 | T9: 0.98366277 | U9: 0.98252014 | V9: 0.98137752 | W9: 0.97702511 | X9: 0.97267271 | Y9: 0.97283379 | Z9: 0.97299487 | AA9: 0.9788558 | AB9: 0.98471674 | AC9: 0.98750719 | AD9: 0.99029765 | AE9: 0.98581693 | AF9: 0.98133621 | AG9: 0.99138829 | AH9: 1.0014404 | AI9: 1.0002358 | AJ9: 0.99903121 | AK9: 1.0003803 | AL9: 1.0017294 | AM9: 1.0020446 | AN9: 1.0023597 | AO9: 0.99944762 | AP9: 0.99653552 | AQ9: 1.0007722 | AR9: 1.0050088 | AS9: 1.0048288 | AT9: 1.0046487 | AU9: 1.0106823 | AV9: 1.0167159 | AW9: 1.0165198 | AX9: 1.0163238 | AY9: 1.0161866 | AZ9: 1.0160494 | BA9: 1.0075708 | BB9: 0.99909218 | BC9: 0.99222513 | BD9: 0.98535808 | BE9: 0.98444514 | BF9: 0.9835322 | BG9: 0.98161801 | BH9: 0.97970383 | BI9: 0.97936427 | BJ9: 0.97902471 | BK9: 0.98205944 | BL9: 0.98509416 | BM9: 0.9832913 | BN9: 0.98148844 | BO9: 0.98589724 | BP9: 0.99030604 | BQ9: 0.99010055 | BR9: 0.98989507 | BS9: 0.98931556 | BT9: 0.98873606 | BU9: 0.98429936 | BV9: 0.97986267 | BW9: 0.97328736 | BX9: 0.96671206 | BY9: 0.95613735 | BZ9: 0.94556264 | CA9: 0.94330628 | CB9: 0.94104992 | CC9: 0.93901639 | CD9: 0.93698286 | CE9: 0.93187898 | CF9: 0.92677509 | CG9: 0.92310694 | CH9: 0.91943879 | CI9: 0.91203889 | CJ9: 0.90463898 | CK9: 0.90524831 | CL9: 0.90585763 | CM9: 0.90748963 | CN9: 0.90912164 | CO9: 0.90447731 | CP9: 0.89983297 | CQ9: 0.9012328 | CR9: 0.90263264 | CS9: 0.90340251 | CT9: 0.90417239 | CU9: 0.9006981 | CV9: 0.8972238 | CW9: 0.89727718 | CX9: 0.89733057 | CY9: 0.8965225 | CZ9: 0.89571444 | DA9: 0.89694522 | DB9: 0.898176 | DC9: 0.89550265 | DD9: 0.8928293 | DE9: 0.89164366 | DF9: 0.89045802 | DG9: 0.89034243 | DH9: 0.89022684 | DI9: 0.8845275 | DJ9: 0.87882817 | DK9: 0.87786936 | DL9: 0.87691055 | DM9: 0.87930892 | DN9: 0.88170729 | DO9: 0.88356789 | DP9: 0.8854285 | DQ9: 0.88780578 | DR9: 0.89018306
A10: ZC_1 | B10: 1.0016623 | C10: 1.0046574 | D10: 1.0075934 | E10: 1.0019039 | F10: 0.99621444 | G10: 0.98515098 | H10: 0.97408751 | I10: 0.97896616 | J10: 0.98384481 | K10: 0.98340877 | L10: 0.98297273 | M10: 0.98663402 | N10: 0.99029532 | O10: 0.99182766 | P10: 0.99336001 | Q10: 0.99967676 | R10: 1.0059935 | S10: 1.0097051 | T10: 1.0134166 | U10: 1.0149253 | V10: 1.0164339 | W10: 1.0173103 | X10: 1.0181868 | Y10: 1.0199319 | Z10: 1.021677 | AA10: 1.0215382 | AB10: 1.0213993 | AC10: 1.0219482 | AD10: 1.0224971 | AE10: 1.0180567 | AF10: 1.0136163 | AG10: 1.0097586 | AH10: 1.005901 | AI10: 1.0079482 | AJ10: 1.0099954 | AK10: 1.0077395 | AL10: 1.0054836 | AM10: 1.0033902 | AN10: 1.0012969 | AO10: 1.0028829 | AP10: 1.004469 | AQ10: 1.0006927 | AR10: 0.99691644 | AS10: 0.99745437 | AT10: 0.9979923 | AU10: 1.0005322 | AV10: 1.003072 | AW10: 1.0085005 | AX10: 1.013929 | AY10: 1.0148334 | AZ10: 1.0157378 | BA10: 1.0166567 | BB10: 1.0175757 | BC10: 1.0134826 | BD10: 1.0093895 | BE10: 1.0125183 | BF10: 1.0156471 | BG10: 1.0111843 | BH10: 1.0067215 | BI10: 1.009503 | BJ10: 1.0122845 | BK10: 1.0118175 | BL10: 1.0113505 | BM10: 1.0151621 | BN10: 1.0189736 | BO10: 1.0189961 | BP10: 1.0190186 | BQ10: 1.0234697 | BR10: 1.0279208 | BS10: 1.0193904 | BT10: 1.0108599 | BU10: 1.0106371 | BV10: 1.0104143 | BW10: 1.0114022 | BX10: 1.0123901 | BY10: 1.0137291 | BZ10: 1.015068 | CA10: 1.0159935 | CB10: 1.0169191 | CC10: 1.0141185 | CD10: 1.011318 | CE10: 1.0098716 | CF10: 1.0084252 | CG10: 1.0038399 | CH10: 0.99925463 | CI10: 0.99660742 | CJ10: 0.99396022 | CK10: 0.9960734 | CL10: 0.99818659 | CM10: 0.9968128 | CN10: 0.99543901 | CO10: 0.99981435 | CP10: 1.0041897 | CQ10: 1.0122468 | CR10: 1.0203039 | CS10: 1.0233147 | CT10: 1.0263254 | CU10: 1.0248276 | CV10: 1.0233299 | CW10: 1.0209337 | CX10: 1.0185375 | CY10: 1.0170479 | CZ10: 1.0155582 | DA10: 1.0133568 | DB10: 1.0111555 | DC10: 1.0130816 | DD10: 1.0150077 | DE10: 1.0176413 | DF10: 1.0202749 | DG10: 1.0198252 | DH10: 1.0193755 | DI10: 1.018355 | DJ10: 1.0173346 | DK10: 1.019898 | DL10: 1.0224614 | DM10: 1.0211187 | DN10: 1.019776 | DO10: 1.0123561 | DP10: 1.0049361 | DQ10: 1.0025765 | DR10: 1.0002169
B11: =AVERAGE(B1:B10) -> 1.0016623 | C11: =AVERAGE(C1:C10) -> 1.0012893 | D11: =AVERAGE(D1:D10) -> 1.0008572 | E11: =AVERAGE(E1:E10) -> 1.0002122 | F11: =AVERAGE(F1:F10) -> 0.99956723 | G11: =AVERAGE(G1:G10) -> 0.99834627 | H11: =AVERAGE(H1:H10) -> 0.99712531 | I11: =AVERAGE(I1:I10) -> 0.99580147 | ... DR11: =AVERAGE(DR1:DR10) -> 0.90529359

Sheet ZC_5
A1: ZC_5 | B1: 0.99445428 | C1: 0.99034668 | D1: 0.98597933 | E1: 0.96997465 | F1: 0.95396997 | G1: 0.90104653 | H1: 0.84812309 | I1: 0.83878987 | J1: 0.82945664 | K1: 0.82001548 | L1: 0.81057432 | M1: 0.80915228 | N1: 0.80773025 | O1: 0.83107145 | P1: 0.85441265 | Q1: 0.86584529 | R1: 0.87727794 | S1: 0.90709037 | T1: 0.9369028 | U1: 0.93786637 | V1: 0.93882993 | W1: 0.92293179 | X1: 0.90703365 | Y1: 0.92613228 | Z1: 0.9452309 | AA1: 0.95230618 | AB1: 0.95938145 | AC1: 0.96758922 | AD1: 0.975797 | AE1: 0.93920134 | AF1: 0.90260569 | AG1: 0.91415884 | AH1: 0.925712 | AI1: 0.9248988 | AJ1: 0.9240856 | AK1: 0.90111409 | AL1: 0.87814258 | AM1: 0.86366558 | AN1: 0.84918857 | AO1: 0.83465593 | AP1: 0.82012328 | AQ1: 0.85733591 | AR1: 0.89454854 | AS1: 0.88319111 | AT1: 0.87183368 | AU1: 0.86461322 | AV1: 0.85739275 | AW1: 0.8494495 | AX1: 0.84150626 | AY1: 0.8680097 | AZ1: 0.89451315 | BA1: 0.852787 | BB1: 0.81106084 | BC1: 0.77593108 | BD1: 0.74080132 | BE1: 0.75035046 | BF1: 0.7598996 | BG1: 0.75576727 | BH1: 0.75163493 | BI1: 0.74783695 | BJ1: 0.74403896 | BK1: 0.75502946 | BL1: 0.76601997 | BM1: 0.76028249 | BN1: 0.75454501 | BO1: 0.76001101 | BP1: 0.765477 | BQ1: 0.76789031 | BR1: 0.77030361 | BS1: 0.78827519 | BT1: 0.80624676 | BU1: 0.82279704 | BV1: 0.83934732 | BW1: 0.87126059 | BX1: 0.90317386 | BY1: 0.88052404 | BZ1: 0.85787421 | CA1: 0.84747168 | CB1: 0.83706915 | CC1: 0.8166011 | CD1: 0.79613305 | CE1: 0.80139816 | CF1: 0.80666327 | CG1: 0.82459916 | CH1: 0.84253505 | CI1: 0.83294485 | CJ1: 0.82335465 | CK1: 0.83305955 | CL1: 0.84276445 | CM1: 0.85996711 | CN1: 0.87716977 | CO1: 0.88805991 | CP1: 0.89895005 | CQ1: 0.86768483 | CR1: 0.83641961 | CS1: 0.82250915 | CT1: 0.8085987 | CU1: 0.790229 | CV1: 0.7718593 | CW1: 0.76548483 | CX1: 0.75911036 | CY1: 0.75739931 | CZ1: 0.75568826 | DA1: 0.77676431 | DB1: 0.79784035 | DC1: 0.81273701 | DD1: 0.82763367 | DE1: 0.81021455 | DF1: 0.79279542 | DG1: 0.79188583 | DH1: 0.79097624 | DI1: 0.80460158 | DJ1: 0.81822691 | DK1: 0.78427913 | DL1: 0.75033135 | DM1: 0.74916299 | DN1: 0.74799462 | DO1: 0.72551641 | DP1: 0.70303819 | DQ1: 0.72269902 | DR1: 0.74235985
A2: ZC_5 | B2: 0.99445428 | C2: 0.96575403 | D2: 0.93679403 | E2: 0.90920423 | F2: 0.88161443 | G2: 0.89586457 | H2: 0.91011471 | I2: 0.88887019 | J2: 0.86762568 | K2: 0.8349781 | L2: 0.80233053 | M2: 0.82402825 | N2: 0.84572598 | O2: 0.83346958 | P2: 0.82121318 | Q2: 0.78419565 | R2: 0.74717812 | S2: 0.73785148 | T2: 0.72852483 | U2: 0.7096697 | V2: 0.69081458 | W2: 0.70904579 | X2: 0.727277 | Y2: 0.70232674 | Z2: 0.67737649 | AA2: 0.68376469 | AB2: 0.69015289 | AC2: 0.70196439 | AD2: 0.71377589 | AE2: 0.71547444 | AF2: 0.71717299 | AG2: 0.69315131 | AH2: 0.66912964 | AI2: 0.64245576 | AJ2: 0.61578189 | AK2: 0.61161794 | AL2: 0.607454 | AM2: 0.59248157 | AN2: 0.57750914 | AO2: 0.57014448 | AP2: 0.56277983 | AQ2: 0.54647933 | AR2: 0.53017882 | AS2: 0.5163637 | AT2: 0.50254858 | AU2: 0.50413321 | AV2: 0.50571784 | AW2: 0.5134833 | AX2: 0.52124875 | AY2: 0.52969915 | AZ2: 0.53814955 | BA2: 0.51809822 | BB2: 0.49804688 | BC2: 0.51571893 | BD2: 0.53339097 | BE2: 0.53688699 | BF2: 0.54038301 | BG2: 0.53201966 | BH2: 0.52365631 | BI2: 0.52940663 | BJ2: 0.53515695 | BK2: 0.54205287 | BL2: 0.54894878 | BM2: 0.53978643 | BN2: 0.53062407 | BO2: 0.52337483 | BP2: 0.51612558 | BQ2: 0.51125773 | BR2: 0.50638987 | BS2: 0.4855633 | BT2: 0.46473672 | BU2: 0.4655302 | BV2: 0.46632367 | BW2: 0.47377392 | BX2: 0.48122416 | BY2: 0.48363582 | BZ2: 0.48604749 | CA2: 0.48327505 | CB2: 0.48050262 | CC2: 0.47080581 | CD2: 0.46110901 | CE2: 0.46261344 | CF2: 0.46411788 | CG2: 0.4603174 | CH2: 0.45651692 | CI2: 0.47309659 | CJ2: 0.48967625 | CK2: 0.49461028 | CL2: 0.4995443 | CM2: 0.49538204 | CN2: 0.49121977 | CO2: 0.49087752 | CP2: 0.49053527 | CQ2: 0.48448292 | CR2: 0.47843057 | CS2: 0.48279944 | CT2: 0.4871683 | CU2: 0.48446162 | CV2: 0.48175494 | CW2: 0.49126795 | CX2: 0.50078096 | CY2: 0.48846698 | CZ2: 0.47615301 | DA2: 0.47246954 | DB2: 0.46878607 | DC2: 0.48927878 | DD2: 0.5097715 | DE2: 0.52090609 | DF2: 0.53204068 | DG2: 0.5154548 | DH2: 0.49886892 | DI2: 0.49988523 | DJ2: 0.50090153 | DK2: 0.50814715 | DL2: 0.51539276 | DM2: 0.51328528 | DN2: 0.51117779 | DO2: 0.50585603 | DP2: 0.50053427 | DQ2: 0.50478292 | DR2: 0.50903157
A3: ZC_5 | B3: 0.99445428 | C3: 0.99194849 | D3: 0.98918297 | E3: 0.99647617 | F3: 1.0037694 | G3: 1.0105097 | H3: 1.0172501 | I3: 1.0231712 | J3: 1.0290923 | K3: 1.0107002 | L3: 0.99230806 | M3: 1.0123336 | N3: 1.0323591 | O3: 1.0352767 | P3: 1.0381943 | Q3: 1.0180853 | R3: 0.9979764 | S3: 0.95622411 | T3: 0.91447182 | U3: 0.91271028 | V3: 0.91094875 | W3: 0.92111274 | X3: 0.93127673 | Y3: 0.90842313 | Z3: 0.88556953 | AA3: 0.86192937 | AB3: 0.83828921 | AC3: 0.82892133 | AD3: 0.81955345 | AE3: 0.80205889 | AF3: 0.78456433 | AG3: 0.78485548 | AH3: 0.78514662 | AI3: 0.78357908 | AJ3: 0.78201154 | AK3: 0.77155328 | AL3: 0.76109501 | AM3: 0.75225013 | AN3: 0.74340525 | AO3: 0.74967161 | AP3: 0.75593797 | AQ3: 0.72964149 | AR3: 0.703345 | AS3: 0.69343659 | AT3: 0.68352819 | AU3: 0.69660508 | AV3: 0.70968197 | AW3: 0.72024241 | AX3: 0.73080285 | AY3: 0.73479317 | AZ3: 0.73878349 | BA3: 0.75087043 | BB3: 0.76295736 | BC3: 0.77874128 | BD3: 0.79452521 | BE3: 0.78258286 | BF3: 0.77064052 | BG3: 0.75467294 | BH3: 0.73870536 | BI3: 0.73309219 | BJ3: 0.72747903 | BK3: 0.73386566 | BL3: 0.7402523 | BM3: 0.74915158 | BN3: 0.75805087 | BO3: 0.74237831 | BP3: 0.72670575 | BQ3: 0.71953389 | BR3: 0.71236203 | BS3: 0.73556595 | BT3: 0.75876987 | BU3: 0.77939579 | BV3: 0.8000217 | BW3: 0.7858035 | BX3: 0.7715853 | BY3: 0.73996189 | BZ3: 0.70833847 | CA3: 0.71243362 | CB3: 0.71652877 | CC3: 0.71170462 | CD3: 0.70688048 | CE3: 0.6725253 | CF3: 0.63817012 | CG3: 0.6601901 | CH3: 0.68221008 | CI3: 0.69359506 | CJ3: 0.70498004 | CK3: 0.70005951 | CL3: 0.69513899 | CM3: 0.69270009 | CN3: 0.69026118 | CO3: 0.68401211 | CP3: 0.67776303 | CQ3: 0.66688958 | CR3: 0.65601612 | CS3: 0.64081028 | CT3: 0.62560443 | CU3: 0.61379817 | CV3: 0.60199191 | CW3: 0.60110077 | CX3: 0.60020962 | CY3: 0.59838527 | CZ3: 0.59656091 | DA3: 0.58864497 | DB3: 0.58072903 | DC3: 0.57556757 | DD3: 0.57040611 | DE3: 0.57064774 | DF3: 0.57088937 | DG3: 0.59356369 | DH3: 0.61623801 | DI3: 0.61394153 | DJ3: 0.61164505 | DK3: 0.59177751 | DL3: 0.57190997 | DM3: 0.55624919 | DN3: 0.54058841 | DO3: 0.5299638 | DP3: 0.51933919 | DQ3: 0.52682812 | DR3: 0.53431704
A4: ZC_5 | B4: 0.99445428 | C4: 0.97510659 | D4: 0.95549916 | E4: 0.96677985 | F4: 0.97806054 | G4: 0.95956609 | H4: 0.94107164 | I4: 0.93655232 | J4: 0.93203299 | K4: 0.94803143 | L4: 0.96402986 | M4: 0.94369373 | N4: 0.92335761 | O4: 0.90640562 | P4: 0.88945363 | Q4: 0.88286238 | R4: 0.87627114 | S4: 0.87885426 | T4: 0.88143739 | U4: 0.88099712 | V4: 0.88055685 | W4: 0.89631309 | X4: 0.91206933 | Y4: 0.90798145 | Z4: 0.90389358 | AA4: 0.87727898 | AB4: 0.85066439 | AC4: 0.83905094 | AD4: 0.8274375 | AE4: 0.8447361 | AF4: 0.86203469 | AG4: 0.81735036 | AH4: 0.77266603 | AI4: 0.76882738 | AJ4: 0.76498873 | AK4: 0.75006223 | AL4: 0.73513573 | AM4: 0.72225261 | AN4: 0.70936949 | AO4: 0.70710742 | AP4: 0.70484534 | AQ4: 0.68052613 | AR4: 0.65620693 | AS4: 0.64693958 | AT4: 0.63767222 | AU4: 0.61249211 | AV4: 0.587312 | AW4: 0.58016975 | AX4: 0.5730275 | AY4: 0.56752894 | AZ4: 0.56203038 | BA4: 0.5794967 | BB4: 0.59696301 | BC4: 0.61144008 | BD4: 0.62591714 | BE4: 0.62266219 | BF4: 0.61940725 | BG4: 0.61997798 | BH4: 0.62054871 | BI4: 0.61633255 | BJ4: 0.61211639 | BK4: 0.59768775 | BL4: 0.58325911 | BM4: 0.58382158 | BN4: 0.58438404 | BO4: 0.56810277 | BP4: 0.5518215 | BQ4: 0.54761737 | BR4: 0.54341324 | BS4: 0.54102922 | BT4: 0.5386452 | BU4: 0.54658694 | BV4: 0.55452868 | BW4: 0.56926128 | BX4: 0.58399388 | BY4: 0.61209475 | BZ4: 0.64019563 | CA4: 0.64396095 | CB4: 0.64772628 | CC4: 0.64892029 | CD4: 0.65011431 | CE4: 0.66429245 | CF4: 0.67847059 | CG4: 0.68671663 | CH4: 0.69496267 | CI4: 0.71798023 | CJ4: 0.74099779 | CK4: 0.73425511 | CL4: 0.72751243 | CM4: 0.71619594 | CN4: 0.70487945 | CO4: 0.71870172 | CP4: 0.73252398 | CQ4: 0.72103085 | CR4: 0.70953771 | CS4: 0.70283119 | CT4: 0.69612466 | CU4: 0.70467111 | CV4: 0.71321755 | CW4: 0.70819336 | CX4: 0.70316917 | CY4: 0.70089694 | CZ4: 0.69862472 | DA4: 0.69059504 | DB4: 0.68256536 | DC4: 0.68818129 | DD4: 0.69379722 | DE4: 0.69304552 | DF4: 0.69229381 | DG4: 0.68947409 | DH4: 0.68665437 | DI4: 0.70334047 | DJ4: 0.72002658 | DK4: 0.71944447 | DL4: 0.71886236 | DM4: 0.70549401 | DN4: 0.69212566 | DO4: 0.67995943 | DP4: 0.6677932 | DQ4: 0.65567482 | DR4: 0.64355644
A5: ZC_5 | B5: 0.99445428 | C5: 0.97358379 | D5: 0.95245357 | E5: 0.96983095 | F5: 0.98720833 | G5: 1.0294464 | H5: 1.0716845 | I5: 1.0323795 | J5: 0.9930744 | K5: 0.98041616 | L5: 0.96775791 | M5: 0.93778701 | N5: 0.90781611 | O5: 0.88972566 | P5: 0.87163522 | Q5: 0.83727285 | R5: 0.80291048 | S5: 0.7826754 | T5: 0.76244032 | U5: 0.75236384 | V5: 0.74228736 | W5: 0.73618245 | X5: 0.73007753 | Y5: 0.72140405 | Z5: 0.71273057 | AA5: 0.71234255 | AB5: 0.71195454 | AC5: 0.71003493 | AD5: 0.70811532 | AE5: 0.72226089 | AF5: 0.73640645 | AG5: 0.74626975 | AH5: 0.75613305 | AI5: 0.74077234 | AJ5: 0.72541162 | AK5: 0.72364259 | AL5: 0.72187357 | AM5: 0.71745756 | AN5: 0.71304155 | AO5: 0.69560198 | AP5: 0.67816241 | AQ5: 0.68035182 | AR5: 0.68254123 | AS5: 0.67059078 | AT5: 0.65864032 | AU5: 0.64293392 | AV5: 0.62722751 | AW5: 0.60343603 | AX5: 0.57964455 | AY5: 0.57125724 | AZ5: 0.56286993 | BA5: 0.55444068 | BB5: 0.54601142 | BC5: 0.55133367 | BD5: 0.55665592 | BE5: 0.54319829 | BF5: 0.52974066 | BG5: 0.53666842 | BH5: 0.54359618 | BI5: 0.53192867 | BJ5: 0.52026116 | BK5: 0.51671661 | BL5: 0.51317206 | BM5: 0.50005707 | BN5: 0.48694208 | BO5: 0.48355222 | BP5: 0.48016236 | BQ5: 0.46624736 | BR5: 0.45233236 | BS5: 0.46799028 | BT5: 0.48364819 | BU5: 0.48060431 | BV5: 0.47756043 | BW5: 0.47201565 | BX5: 0.46647087 | BY5: 0.45988803 | BZ5: 0.45330519 | CA5: 0.44871604 | CB5: 0.44412689 | CC5: 0.4462422 | CD5: 0.44835751 | CE5: 0.44910361 | CF5: 0.4498497 | CG5: 0.45665316 | CH5: 0.46345661 | CI5: 0.46602384 | CJ5: 0.46859107 | CK5: 0.4611068 | CL5: 0.45362254 | CM5: 0.4534673 | CN5: 0.45331205 | CO5: 0.44137399 | CP5: 0.42943592 | CQ5: 0.41012476 | CR5: 0.39081359 | CS5: 0.38325904 | CT5: 0.37570449 | CU5: 0.37588064 | CV5: 0.37605679 | CW5: 0.37780136 | CX5: 0.37954592 | CY5: 0.37935617 | CZ5: 0.37916642 | DA5: 0.38131054 | DB5: 0.38345466 | DC5: 0.3775572 | DD5: 0.37165974 | DE5: 0.36431916 | DF5: 0.35697858 | DG5: 0.3560616 | DH5: 0.35514462 | DI5: 0.3541693 | DJ5: 0.35319399 | DK5: 0.34682797 | DL5: 0.34046194 | DM5: 0.34070828 | DN5: 0.34095462 | DO5: 0.3507829 | DP5: 0.36061119 | DQ5: 0.36278858 | DR5: 0.36496598
A6: ZC_5 | B6: 0.99445428 | C6: 0.98851895 | D6: 0.98232388 | E6: 0.98575521 | F6: 0.98918654 | G6: 1.0346467 | H6: 1.0801068 | I6: 1.0762246 | J6: 1.0723423 | K6: 1.0696832 | L6: 1.0670241 | M6: 1.0558462 | N6: 1.0446684 | O6: 1.00592 | P6: 0.96717172 | Q6: 0.94643803 | R6: 0.92570434 | S6: 0.89055768 | T6: 0.85541101 | U6: 0.85094837 | V6: 0.84648574 | W6: 0.85964134 | X6: 0.87279694 | Y6: 0.85465002 | Z6: 0.83650309 | AA6: 0.82973842 | AB6: 0.82297374 | AC6: 0.81400357 | AD6: 0.80503339 | AE6: 0.83217371 | AF6: 0.85931403 | AG6: 0.83959485 | AH6: 0.81987568 | AI6: 0.80911721 | AJ6: 0.79835875 | AK6: 0.8059354 | AL6: 0.81351205 | AM6: 0.81378795 | AN6: 0.81406385 | AO6: 0.81512004 | AP6: 0.81617624 | AQ6: 0.77162283 | AR6: 0.72706941 | AS6: 0.72662694 | AT6: 0.72618448 | AU6: 0.72348096 | AV6: 0.72077745 | AW6: 0.71907487 | AX6: 0.7173723 | AY6: 0.68914003 | AZ6: 0.66090777 | BA6: 0.6876295 | BB6: 0.71435123 | BC6: 0.74068151 | BD6: 0.76701178 | BE6: 0.75049131 | BF6: 0.73397085 | BG6: 0.7317721 | BH6: 0.72957336 | BI6: 0.72701492 | BJ6: 0.72445647 | BK6: 0.70820148 | BL6: 0.6919465 | BM6: 0.69175383 | BN6: 0.69156115 | BO6: 0.68148948 | BP6: 0.67141781 | BQ6: 0.66395387 | BR6: 0.65648994 | BS6: 0.6374286 | BT6: 0.61836725 | BU6: 0.60165805 | BV6: 0.58494885 | BW6: 0.56047349 | BX6: 0.53599814 | BY6: 0.54610832 | BZ6: 0.55621849 | CA6: 0.55915008 | CB6: 0.56208167 | CC6: 0.57228992 | CD6: 0.58249817 | CE6: 0.57492474 | CF6: 0.5673513 | CG6: 0.55158945 | CH6: 0.53582761 | CI6: 0.53818628 | CJ6: 0.54054495 | CK6: 0.53093301 | CL6: 0.52132107 | CM6: 0.50773802 | CN6: 0.49415498 | CO6: 0.48501322 | CP6: 0.47587145 | CQ6: 0.48988721 | CR6: 0.50390296 | CS6: 0.50933113 | CT6: 0.51475929 | CU6: 0.52347863 | CV6: 0.53219796 | CW6: 0.53289282 | CX6: 0.53358768 | CY6: 0.53143622 | CZ6: 0.52928476 | DA6: 0.5122359 | DB6: 0.49518704 | DC6: 0.48314688 | DD6: 0.47110672 | DE6: 0.47830606 | DF6: 0.48550541 | DG6: 0.48301792 | DH6: 0.48053044 | DI6: 0.46939447 | DJ6: 0.45825851 | DK6: 0.47568271 | DL6: 0.49310691 | DM6: 0.49096652 | DN6: 0.48882613 | DO6: 0.50080181 | DP6: 0.51277749 | DQ6: 0.49644767 | DR6: 0.48011784
A7: ZC_5 | B7: 0.99445428 | C7: 1.0143068 | D7: 1.0338997 | E7: 1.0521352 | F7: 1.0703707 | G7: 1.0384535 | H7: 1.0065364 | I7: 1.0158518 | J7: 1.0251673 | K7: 1.0515774 | L7: 1.0779875 | M7: 1.0378612 | N7: 0.9977348 | O7: 1.0020034 | P7: 1.0062719 | Q7: 1.0465807 | R7: 1.0868894 | S7: 1.0934857 | T7: 1.1000819 | U7: 1.1252359 | V7: 1.15039 | W7: 1.1194554 | X7: 1.0885209 | Y7: 1.1279008 | Z7: 1.1672808 | AA7: 1.1556483 | AB7: 1.1440157 | AC7: 1.122285 | AD7: 1.1005544 | AE7: 1.0910266 | AF7: 1.0814988 | AG7: 1.1078807 | AH7: 1.1342627 | AI7: 1.166168 | AJ7: 1.1980733 | AK7: 1.1870479 | AL7: 1.1760225 | AM7: 1.1865245 | AN7: 1.1970265 | AO7: 1.1932086 | AP7: 1.1893908 | AQ7: 1.2080723 | AR7: 1.2267538 | AS7: 1.2432783 | AT7: 1.2598028 | AU7: 1.2409035 | AV7: 1.2220043 | AW7: 1.1900666 | AX7: 1.158129 | AY7: 1.1283455 | AZ7: 1.0985621 | BA7: 1.1309354 | BB7: 1.1633088 | BC7: 1.1142875 | BD7: 1.0652661 | BE7: 1.0486968 | BF7: 1.0321275 | BG7: 1.0396637 | BH7: 1.0471999 | BI7: 1.0272128 | BJ7: 1.0072257 | BK7: 0.98639454 | BL7: 0.96556337 | BM7: 0.97448009 | BN7: 0.9833968 | BO7: 0.98959553 | BP7: 0.99579426 | BQ7: 0.99721258 | BR7: 0.99863089 | BS7: 1.0357015 | BT7: 1.0727721 | BU7: 1.0628179 | BV7: 1.0528637 | BW7: 1.0294194 | BX7: 1.0059751 | BY7: 0.99385058 | BZ7: 0.98172609 | CA7: 0.98045583 | CB7: 0.97918557 | CC7: 0.99245223 | CD7: 1.0057189 | CE7: 0.99590387 | CF7: 0.98608884 | CG7: 0.98749875 | CH7: 0.98890867 | CI7: 0.94889765 | CJ7: 0.90888663 | CK7: 0.89419497 | CL7: 0.87950331 | CM7: 0.88095723 | CN7: 0.88241116 | CO7: 0.87724422 | CP7: 0.87207728 | CQ7: 0.87651458 | CR7: 0.88095189 | CS7: 0.86767297 | CT7: 0.85439405 | CU7: 0.85353613 | CV7: 0.85267821 | CW7: 0.83075937 | CX7: 0.80884052 | CY7: 0.8244263 | CZ7: 0.84001209 | DA7: 0.8413925 | DB7: 0.84277292 | DC7: 0.80381642 | DD7: 0.76485992 | DE7: 0.74415649 | DF7: 0.72345307 | DG7: 0.74267647 | DH7: 0.76189986 | DI7: 0.75523451 | DJ7: 0.74856916 | DK7: 0.7332279 | DL7: 0.71788663 | DM7: 0.7165873 | DN7: 0.71528796 | DO7: 0.71776134 | DP7: 0.72023472 | DQ7: 0.71021373 | DR7: 0.70019273
A8: ZC_5 | B8: 0.99445428 | C8: 0.98692824 | D8: 0.97914246 | E8: 0.95962654 | F8: 0.94011062 | G8: 0.92031997 | H8: 0.90052931 | I8: 0.8824229 | J8: 0.86431649 | K8: 0.86796157 | L8: 0.87160665 | M8: 0.84448393 | N8: 0.81736121 | O8: 0.80666187 | P8: 0.79596254 | Q8: 0.80485462 | R8: 0.8137467 | S8: 0.84507 | T8: 0.8763933 | U8: 0.87439361 | V8: 0.87239392 | W8: 0.86123507 | X8: 0.85007622 | Y8: 0.87146753 | Z8: 0.89285883 | AA8: 0.91735623 | AB8: 0.94185363 | AC8: 0.9501812 | AD8: 0.95850877 | AE8: 0.9735553 | AF8: 0.98860182 | AG8: 0.97763023 | AH8: 0.96665863 | AI8: 0.95503068 | AJ8: 0.94340273 | AK8: 0.94101174 | AL8: 0.93862075 | AM8: 0.93426116 | AN8: 0.92990157 | AO8: 0.90768892 | AP8: 0.88547627 | AQ8: 0.90509934 | AR8: 0.92472241 | AS8: 0.92548189 | AT8: 0.92624137 | AU8: 0.89851949 | AV8: 0.87079761 | AW8: 0.84841941 | AX8: 0.82604122 | AY8: 0.81313153 | AZ8: 0.80022185 | BA8: 0.779806 | BB8: 0.75939016 | BC8: 0.73726922 | BD8: 0.71514828 | BE8: 0.71944465 | BF8: 0.72374102 | BG8: 0.73304206 | BH8: 0.7423431 | BI8: 0.74164535 | BJ8: 0.7409476 | BK8: 0.72849014 | BL8: 0.71603268 | BM8: 0.70219774 | BN8: 0.6883628 | BO8: 0.69780106 | BP8: 0.70723933 | BQ8: 0.70856319 | BR8: 0.70988704 | BS8: 0.68347304 | BT8: 0.65705903 | BU8: 0.63538072 | BV8: 0.61370241 | BW8: 0.62055567 | BX8: 0.62740893 | BY8: 0.65052473 | BZ8: 0.67364053 | CA8: 0.66514011 | CB8: 0.65663969 | CC8: 0.6563428 | CD8: 0.65604591 | CE8: 0.6865962 | CF8: 0.71714649 | CG8: 0.68944899 | CH8: 0.66175149 | CI8: 0.64653022 | CJ8: 0.63130894 | CK8: 0.63167103 | CL8: 0.63203312 | CM8: 0.62999757 | CN8: 0.62796202 | CO8: 0.62956673 | CP8: 0.63117143 | CQ8: 0.63682349 | CR8: 0.64247555 | CS8: 0.65390301 | CT8: 0.66533048 | CU8: 0.67385084 | CV8: 0.6823712 | CW8: 0.67861099 | CX8: 0.67485078 | CY8: 0.67265879 | CZ8: 0.67046679 | DA8: 0.67539222 | DB8: 0.68031764 | DC8: 0.68193618 | DD8: 0.68355471 | DE8: 0.67888861 | DF8: 0.67422251 | DG8: 0.64550522 | DH8: 0.61678792 | DI8: 0.61491115 | DJ8: 0.61303437 | DK8: 0.62998905 | DL8: 0.64694373 | DM8: 0.66165829 | DN8: 0.67637284 | DO8: 0.68526417 | DP8: 0.69415551 | DQ8: 0.68060652 | DR8: 0.66705754
A9: ZC_5 | B9: 0.99445428 | C9: 1.0041869 | D9: 1.0136598 | E9: 0.98924084 | F9: 0.96482192 | G9: 0.96912392 | H9: 0.97342593 | I9: 0.96387497 | J9: 0.95432401 | K9: 0.92574889 | L9: 0.89717377 | M9: 0.90551183 | N9: 0.91384988 | O9: 0.92145942 | P9: 0.92906896 | Q9: 0.92791845 | R9: 0.92676794 | S9: 0.91800331 | T9: 0.90923869 | U9: 0.90587138 | V9: 0.90250408 | W9: 0.88524109 | X9: 0.8679781 | Y9: 0.87136829 | Z9: 0.87475848 | AA9: 0.90145518 | AB9: 0.92815187 | AC9: 0.93876385 | AD9: 0.94937583 | AE9: 0.92456641 | AF9: 0.89975698 | AG9: 0.94101485 | AH9: 0.98227271 | AI9: 0.97333419 | AJ9: 0.96439568 | AK9: 0.96808061 | AL9: 0.97176555 | AM9: 0.97314204 | AN9: 0.97451852 | AO9: 0.96209048 | AP9: 0.94966243 | AQ9: 0.97040574 | AR9: 0.99114906 | AS9: 0.99199892 | AT9: 0.99284878 | AU9: 1.0225411 | AV9: 1.0522335 | AW9: 1.052857 | AX9: 1.0534805 | AY9: 1.0526822 | AZ9: 1.0518839 | BA9: 1.0112168 | BB9: 0.97054977 | BC9: 0.93917149 | BD9: 0.90779322 | BE9: 0.90412072 | BF9: 0.90044822 | BG9: 0.89206922 | BH9: 0.88369022 | BI9: 0.88214032 | BJ9: 0.88059043 | BK9: 0.89467718 | BL9: 0.90876393 | BM9: 0.90084694 | BN9: 0.89292995 | BO9: 0.91215441 | BP9: 0.93137887 | BQ9: 0.93098595 | BR9: 0.93059302 | BS9: 0.92808407 | BT9: 0.92557512 | BU9: 0.90548355 | BV9: 0.88539198 | BW9: 0.85716909 | BX9: 0.8289462 | BY9: 0.78714474 | BZ9: 0.74534327 | CA9: 0.73586612 | CB9: 0.72638898 | CC9: 0.71985949 | CD9: 0.71333001 | CE9: 0.69393936 | CF9: 0.67454871 | CG9: 0.66207852 | CH9: 0.64960834 | CI9: 0.62511559 | CJ9: 0.60062285 | CK9: 0.60226562 | CL9: 0.60390839 | CM9: 0.60942366 | CN9: 0.61493892 | CO9: 0.59946309 | CP9: 0.58398725 | CQ9: 0.58899991 | CR9: 0.59401257 | CS9: 0.59597119 | CT9: 0.59792982 | CU9: 0.58694292 | CV9: 0.57595602 | CW9: 0.57599685 | CX9: 0.57603768 | CY9: 0.57427716 | CZ9: 0.57251664 | DA9: 0.57566665 | DB9: 0.57881667 | DC9: 0.57040094 | DD9: 0.56198522 | DE9: 0.55898619 | DF9: 0.55598716 | DG9: 0.55476176 | DH9: 0.55353636 | DI9: 0.53714707 | DJ9: 0.52075778 | DK9: 0.51772549 | DL9: 0.5146932 | DM9: 0.5214889 | DN9: 0.52828459 | DO9: 0.5340628 | DP9: 0.53984102 | DQ9: 0.546835 | DR9: 0.55382898
A10: ZC_5 | B10: 0.99445428 | C10: 1.0058075 | D10: 1.0169011 | E10: 0.98639132 | F10: 0.95588157 | G10: 0.905335 | H10: 0.85478842 | I10: 0.87522644 | J10: 0.89566447 | K10: 0.89469105 | L10: 0.89371763 | M10: 0.91160616 | N10: 0.92949468 | O10: 0.93877807 | P10: 0.94806146 | Q10: 0.97975336 | R10: 1.0114453 | S10: 1.0312962 | T10: 1.0511472 | U10: 1.0608825 | V10: 1.0706179 | W10: 1.0774816 | X10: 1.0843454 | Y10: 1.0968624 | Z10: 1.1093794 | AA10: 1.1091814 | AB10: 1.1089834 | AC10: 1.1091677 | AD10: 1.109352 | AE10: 1.0813021 | AF10: 1.0532522 | AG10: 1.0285012 | AH10: 1.0037503 | AI10: 1.0103808 | AJ10: 1.0170113 | AK10: 1.003315 | AL10: 0.98961868 | AM10: 0.97955929 | AN10: 0.96949991 | AO10: 0.97826384 | AP10: 0.98702778 | AQ10: 0.9699678 | AR10: 0.95290783 | AS10: 0.95707442 | AT10: 0.961241 | AU10: 0.97325623 | AV10: 0.98527146 | AW10: 1.0133629 | AX10: 1.0414542 | AY10: 1.0458846 | AZ10: 1.0503149 | BA10: 1.0557162 | BB10: 1.0611176 | BC10: 1.0409309 | BD10: 1.0207443 | BE10: 1.0368035 | BF10: 1.0528627 | BG10: 1.0308249 | BH10: 1.0087871 | BI10: 1.0224255 | BJ10: 1.036064 | BK10: 1.0344717 | BL10: 1.0328794 | BM10: 1.0522468 | BN10: 1.0716141 | BO10: 1.0709957 | BP10: 1.0703773 | BQ10: 1.0941765 | BR10: 1.1179757 | BS10: 1.0744003 | BT10: 1.0308249 | BU10: 1.0294576 | BV10: 1.0280903 | BW10: 1.0329409 | BX10: 1.0377915 | BY10: 1.0452139 | BZ10: 1.0526363 | CA10: 1.0560105 | CB10: 1.0593847 | CC10: 1.0468534 | CD10: 1.034322 | CE10: 1.0258436 | CF10: 1.0173653 | CG10: 0.99573312 | CH10: 0.97410099 | CI10: 0.96194239 | CJ10: 0.94978379 | CK10: 0.95916111 | CL10: 0.96853843 | CM10: 0.96237013 | CN10: 0.95620182 | CO10: 0.97617832 | CP10: 0.99615482 | CQ10: 1.0373042 | CR10: 1.0784536 | CS10: 1.0931644 | CT10: 1.1078752 | CU10: 1.1001077 | CV10: 1.0923402 | CW10: 1.0797708 | CX10: 1.0672014 | CY10: 1.0610396 | CZ10: 1.0548779 | DA10: 1.0425979 | DB10: 1.0303179 | DC10: 1.039703 | DD10: 1.049088 | DE10: 1.063661 | DF10: 1.0782341 | DG10: 1.0742345 | DH10: 1.0702349 | DI10: 1.0659298 | DJ10: 1.0616246 | DK10: 1.0741823 | DL10: 1.0867399 | DM10: 1.0795693 | DN10: 1.0723988 | DO10: 1.0360482 | DP10: 0.99969766 | DQ10: 0.9881412 | DR10: 0.97658474
B11: =AVERAGE(B1:B10) -> 0.99445428 | C11: =AVERAGE(C1:C10) -> 0.9896488 | D11: =AVERAGE(D1:D10) -> 0.98458359 | E11: =AVERAGE(E1:E10) -> 0.9785415 | F11: =AVERAGE(F1:F10) -> 0.9724994 | G11: =AVERAGE(G1:G10) -> 0.96643125 | H11: =AVERAGE(H1:H10) -> 0.96036309 | I11: =AVERAGE(I1:I10) -> 0.95333638 | ... DR11: =AVERAGE(DR1:DR10) -> 0.61720127
A19: D(t+i)/Dt | B19: =Deflator!N1/Deflator!D1 -> 0.90764464 | C19: =Deflator!O1/Deflator!E1 -> 0.89200643 | D19: =Deflator!P1/Deflator!F1 -> 0.8779114 | E19: =Deflator!Q1/Deflator!G1 -> 0.86518278 | F19: =Deflator!R1/Deflator!H1 -> 0.85734022 | G19: =Deflator!S1/Deflator!I1 -> 0.85376993 | H19: =Deflator!T1/Deflator!J1 -> 0.8557653 | I19: =Deflator!U1/Deflator!K1 -> 0.86114253 | ... DG19: =Deflator!DS1/Deflator!DI1 -> 0.76945434
B20: =Deflator!N2/Deflator!D2 -> 0.91290803 | C20: =Deflator!O2/Deflator!E2 -> 0.9040549 | D20: =Deflator!P2/Deflator!F2 -> 0.89567676 | E20: =Deflator!Q2/Deflator!G2 -> 0.88728563 | F20: =Deflator!R2/Deflator!H2 -> 0.87869018 | G20: =Deflator!S2/Deflator!I2 -> 0.86222266 | H20: =Deflator!T2/Deflator!J2 -> 0.84250512 | I20: =Deflator!U2/Deflator!K2 -> 0.82582401 | ... DG20: =Deflator!DS2/Deflator!DI2 -> 0.50768407
B21: =Deflator!N3/Deflator!D3 -> 1.0353492 | C21: =Deflator!O3/Deflator!E3 -> 1.0404562 | D21: =Deflator!P3/Deflator!F3 -> 1.0465356 | E21: =Deflator!Q3/Deflator!G3 -> 1.0544254 | F21: =Deflator!R3/Deflator!H3 -> 1.0582495 | G21: =Deflator!S3/Deflator!I3 -> 1.0585742 | H21: =Deflator!T3/Deflator!J3 -> 1.0531501 | I21: =Deflator!U3/Deflator!K3 -> 1.0431581 | ... DG21: =Deflator!DS3/Deflator!DI3 -> 0.56667597
B22: =Deflator!N4/Deflator!D4 -> 0.98946343 | C22: =Deflator!O4/Deflator!E4 -> 0.98861433 | D22: =Deflator!P4/Deflator!F4 -> 0.98282467 | E22: =Deflator!Q4/Deflator!G4 -> 0.97480994 | F22: =Deflator!R4/Deflator!H4 -> 0.96359091 | G22: =Deflator!S4/Deflator!I4 -> 0.9547071 | H22: =Deflator!T4/Deflator!J4 -> 0.94681455 | I22: =Deflator!U4/Deflator!K4 -> 0.93720674 | ... DG22: =Deflator!DS4/Deflator!DI4 -> 0.69972802
B23: =Deflator!N5/Deflator!D5 -> 1.0268407 | C23: =Deflator!O5/Deflator!E5 -> 1.0223267 | D23: =Deflator!P5/Deflator!F5 -> 1.0156726 | E23: =Deflator!Q5/Deflator!G5 -> 1.0064466 | F23: =Deflator!R5/Deflator!H5 -> 0.98828381 | G23: =Deflator!S5/Deflator!I5 -> 0.96335853 | H23: =Deflator!T5/Deflator!J5 -> 0.93304174 | I23: =Deflator!U5/Deflator!K5 -> 0.90345305 | ... DG23: =Deflator!DS5/Deflator!DI5 -> 0.34901296
B24: =Deflator!N6/Deflator!D6 -> 1.0759955 | C24: =Deflator!O6/Deflator!E6 -> 1.0826314 | D24: =Deflator!P6/Deflator!F6 -> 1.0863049 | E24: =Deflator!Q6/Deflator!G6 -> 1.0873062 | F24: =Deflator!R6/Deflator!H6 -> 1.0814539 | G24: =Deflator!S6/Deflator!I6 -> 1.069891 | H24: =Deflator!T6/Deflator!J6 -> 1.051563 | I24: =Deflator!U6/Deflator!K6 -> 1.0297917 | ... DG24: =Deflator!DS6/Deflator!DI6 -> 0.492552
B25: =Deflator!N7/Deflator!D7 -> 1.0697918 | C25: =Deflator!O7/Deflator!E7 -> 1.068203 | D25: =Deflator!P7/Deflator!F7 -> 1.0647585 | E25: =Deflator!Q7/Deflator!G7 -> 1.0602208 | F25: =Deflator!R7/Deflator!H7 -> 1.0551773 | G25: =Deflator!S7/Deflator!I7 -> 1.0594024 | H25: =Deflator!T7/Deflator!J7 -> 1.0681135 | I25: =Deflator!U7/Deflator!K7 -> 1.0738334 | ... DG25: =Deflator!DS7/Deflator!DI7 -> 0.74651991
B26: =Deflator!N8/Deflator!D8 -> 0.94327742 | C26: =Deflator!O8/Deflator!E8 -> 0.9281642 | D26: =Deflator!P8/Deflator!F8 -> 0.91127279 | E26: =Deflator!Q8/Deflator!G8 -> 0.89216235 | F26: =Deflator!R8/Deflator!H8 -> 0.87613926 | G26: =Deflator!S8/Deflator!I8 -> 0.86289725 | H26: =Deflator!T8/Deflator!J8 -> 0.85447562 | I26: =Deflator!U8/Deflator!K8 -> 0.85010832 | ... DG26: =Deflator!DS8/Deflator!DI8 -> 0.66880597
B27: =Deflator!N9/Deflator!D9 -> 0.98702138 | C27: =Deflator!O9/Deflator!E9 -> 0.9768361 | D27: =Deflator!P9/Deflator!F9 -> 0.97034543 | E27: =Deflator!Q9/Deflator!G9 -> 0.96502775 | F27: =Deflator!R9/Deflator!H9 -> 0.96220702 | G27: =Deflator!S9/Deflator!I9 -> 0.95677593 | H27: =Deflator!T9/Deflator!J9 -> 0.95044071 | I27: =Deflator!U9/Deflator!K9 -> 0.9462132 | ... DG27: =Deflator!DS9/Deflator!DI9 -> 0.54163369
B28: =Deflator!N10/Deflator!D10 -> 0.95109352 | C28: =Deflator!O10/Deflator!E10 -> 0.94462382 | D28: =Deflator!P10/Deflator!F10 -> 0.93896339 | E28: =Deflator!Q10/Deflator!G10 -> 0.93469306 | F28: =Deflator!R10/Deflator!H10 -> 0.93816566 | G28: =Deflator!S10/Deflator!I10 -> 0.94818361 | H28: =Deflator!T10/Deflator!J10 -> 0.96447035 | I28: =Deflator!U10/Deflator!K10 -> 0.98156444 | ... DG28: =Deflator!DS10/Deflator!DI10 -> 1.0859089
A29: E(D(t+i)/Dt) | B29: =AVERAGE(B19:B28) -> 0.98993857 | C29: =AVERAGE(C19:C28) -> 0.98479171 | D29: =AVERAGE(D19:D28) -> 0.97902661 | E29: =AVERAGE(E19:E28) -> 0.97275605 | F29: =AVERAGE(F19:F28) -> 0.96592978 | G29: =AVERAGE(G19:G28) -> 0.95897827 | H29: =AVERAGE(H19:H28) -> 0.952034 | I29: =AVERAGE(I19:I28) -> 0.94522954 | ... DG29: =AVERAGE(DG19:DG28) -> 0.64279758
A30: E(Dt+i)/E(Dt) | B30: =Deflator!N11/Deflator!D11 -> 0.9899476 | C30: =Deflator!O11/Deflator!E11 -> 0.98487165 | D30: =Deflator!P11/Deflator!F11 -> 0.97921855 | E30: =Deflator!Q11/Deflator!G11 -> 0.97314612 | F30: =Deflator!R11/Deflator!H11 -> 0.9666666 | G30: =Deflator!S11/Deflator!I11 -> 0.9601989 | H30: =Deflator!T11/Deflator!J11 -> 0.95367717 | I30: =Deflator!U11/Deflator!K11 -> 0.94728582 | ... DG30: =Deflator!DS11/Deflator!DI11 -> 0.88345053
A31: Err | B31: =B30/B11 -> 0.99546819 | C31: =C30/C11 -> 0.99517288 | D31: =D30/D11 -> 0.99455096 | E31: =E30/E11 -> 0.99448631 | F31: =F30/F11 -> 0.99400226 | G31: =G30/G11 -> 0.99355117 | H31: =H30/H11 -> 0.99303813 | I31: =I30/I11 -> 0.99365328 | ... DG31: =DG30/DG11 -> 1.3704055
A32: Err2 | B32: =B11/B29 -> 1.0045616 | C32: =C11/C29 -> 1.0049321 | D32: =D11/D29 -> 1.005676 | E32: =E11/E29 -> 1.0059475 | F32: =F11/F29 -> 1.0068013 | G32: =G11/G29 -> 1.0077718 | H32: =H11/H29 -> 1.0087487 | I32: =I11/I29 -> 1.0085766 | ... DG32: =DG11/DG29 -> 1.0029029
A33: Err3 | B33: =B1/B19 -> 1.0956428 | C33: =C1/C19 -> 1.1102461 | D33: =D1/D19 -> 1.1230966 | E33: =E1/E19 -> 1.1211211 | F33: =F1/F19 -> 1.1127088 | G33: =G1/G19 -> 1.0553739 | H33: =H1/H19 -> 0.99106973 | I33: =I1/I19 -> 0.97404302 | ... DG33: =DG1/DG19 -> 1.0291525
B34: =B2/B20 -> 1.0893258 | C34: =C2/C20 -> 1.0682471 | D34: =D2/D20 -> 1.0459064 | E34: =E2/E20 -> 1.024703 | F34: =F2/F20 -> 1.003328 | G34: =G2/G20 -> 1.0390177 | H34: =H2/H20 -> 1.0802483 | I34: =I2/I20 -> 1.0763434 | ... DG34: =DG2/DG20 -> 1.0153062
B35: =B3/B21 -> 0.96050129 | C35: =C3/C21 -> 0.95337845 | D35: =D3/D21 -> 0.94519761 | E35: =E3/E21 -> 0.94504189 | F35: =F3/F21 -> 0.94851865 | G35: =G3/G21 -> 0.95459509 | H35: =H3/H21 -> 0.96591178 | I35: =I3/I21 -> 0.98084 | ... DG35: =DG3/DG21 -> 1.0474481
B36: =B4/B22 -> 1.005044 | C36: =C4/C22 -> 0.98633669 | D36: =D4/D22 -> 0.97219696 | E36: =E4/E22 -> 0.99176241 | F36: =F4/F22 -> 1.0150164 | G36: =G4/G22 -> 1.0050895 | H36: =H4/H22 -> 0.99393449 | I36: =I4/I22 -> 0.99930173 | ... DG36: =DG4/DG22 -> 0.98534584
B37: =B5/B23 -> 0.9684601 | C37: =C5/C23 -> 0.95232159 | D37: =D5/D23 -> 0.93775645 | E37: =E5/E23 -> 0.9636189 | F37: =F5/F23 -> 0.99891177 | G37: =G5/G23 -> 1.0686016 | H37: =H5/H23 -> 1.1485923 | I37: =I5/I23 -> 1.1427041 | ... DG37: =DG5/DG23 -> 1.0201959
B38: =B6/B24 -> 0.92421787 | C38: =C6/C24 -> 0.91307065 | D38: =D6/D24 -> 0.90428011 | E38: =E6/E24 -> 0.9066031 | F38: =F6/F24 -> 0.91468211 | G38: =G6/G24 -> 0.96705802 | H38: =H6/H24 -> 1.0271442 | I38: =I6/I24 -> 1.0450896 | ... DG38: =DG6/DG24 -> 0.98064352
B39: =B7/B25 -> 0.92957737 | C39: =C7/C25 -> 0.94954503 | D39: =D7/D25 -> 0.97101802 | E39: =E7/E25 -> 0.9923737 | F39: =F7/F25 -> 1.0143989 | G39: =G7/G25 -> 0.98022574 | H39: =H7/H25 -> 0.94234962 | I39: =I7/I25 -> 0.94600506 | ... DG39: =DG7/DG25 -> 0.99485152
B40: =B8/B26 -> 1.0542543 | C40: =C8/C26 -> 1.0633121 | D40: =D8/D26 -> 1.0744779 | E40: =E8/E26 -> 1.0756187 | F40: =F8/F26 -> 1.0730151 | G40: =G8/G26 -> 1.0665464 | H40: =H8/H26 -> 1.053897 | I40: =I8/I26 -> 1.0380123 | ... DG40: =DG8/DG26 -> 0.96516067
B41: =B9/B27 -> 1.0075306 | C41: =C9/C27 -> 1.0279994 | D41: =D9/D27 -> 1.0446381 | E41: =E9/E27 -> 1.0250906 | F41: =F9/F27 -> 1.0027176 | G41: =G9/G27 -> 1.0129058 | H41: =H9/H27 -> 1.0241838 | I41: =I9/I27 -> 1.0186657 | ... DG41: =DG9/DG27 -> 1.0242379
B42: =B10/B28 -> 1.0455904 | C42: =C10/C28 -> 1.0647705 | D42: =D10/D28 -> 1.083004 | E42: =E10/E28 -> 1.0553104 | F42: =F10/F28 -> 1.0188836 | G42: =G10/G28 -> 0.95480979 | H42: =H10/H28 -> 0.88627755 | I42: =I10/I28 -> 0.89166478 | ... DG42: =DG10/DG28 -> 0.9892492
B43: =B11/B29 -> 1.0045616 | C43: =C11/C29 -> 1.0049321 | D43: =D11/D29 -> 1.005676 | E43: =E11/E29 -> 1.0059475 | F43: =F11/F29 -> 1.0068013 | G43: =G11/G29 -> 1.0077718 | H43: =H11/H29 -> 1.0087487 | I43: =I11/I29 -> 1.0085766 | ... DG43: =DG11/DG29 -> 1.0029029

Sheet ZC_10
A1: ZC_10 | B1: 0.93039436 | C1: 0.92334566 | D1: 0.91439073 | E1: 0.88684219 | F1: 0.85929365 | G1: 0.77362745 | H1: 0.68796125 | I1: 0.67582524 | J1: 0.66368924 | K1: 0.65205072 | L1: 0.6404122 | M1: 0.64131057 | N1: 0.64220893 | O1: 0.68236603 | P1: 0.72252312 | Q1: 0.7442798 | R1: 0.76603648 | S1: 0.81956479 | T1: 0.87309311 | U1: 0.8737737 | V1: 0.87445429 | W1: 0.84259072 | X1: 0.81072715 | Y1: 0.83848609 | Z1: 0.86624502 | AA1: 0.87207953 | AB1: 0.87791403 | AC1: 0.8862603 | AD1: 0.89460658 | AE1: 0.82810092 | AF1: 0.76159527 | AG1: 0.77897337 | AH1: 0.79635148 | AI1: 0.79488831 | AJ1: 0.79342515 | AK1: 0.75720729 | AL1: 0.72098943 | AM1: 0.69956716 | AN1: 0.67814488 | AO1: 0.65751067 | AP1: 0.63687646 | AQ1: 0.69640096 | AR1: 0.75592546 | AS1: 0.73860911 | AT1: 0.72129276 | AU1: 0.71053079 | AV1: 0.69976882 | AW1: 0.6881707 | AX1: 0.67657257 | AY1: 0.71944961 | AZ1: 0.76232665 | BA1: 0.69687666 | BB1: 0.63142666 | BC1: 0.5810025 | BD1: 0.53057835 | BE1: 0.54427034 | BF1: 0.55796233 | BG1: 0.55208081 | BH1: 0.54619928 | BI1: 0.54113244 | BJ1: 0.53606559 | BK1: 0.55163785 | BL1: 0.5672101 | BM1: 0.55913055 | BN1: 0.55105099 | BO1: 0.5587905 | BP1: 0.56653001 | BQ1: 0.57014048 | BR1: 0.57375095 | BS1: 0.60003164 | BT1: 0.62631233 | BU1: 0.65184067 | BV1: 0.677369 | BW1: 0.72885964 | BX1: 0.78035028 | BY1: 0.74325199 | BZ1: 0.70615369 | CA1: 0.68981303 | CB1: 0.67347237 | CC1: 0.64234329 | CD1: 0.61121421 | CE1: 0.61895922 | CF1: 0.62670424 | CG1: 0.65386069 | CH1: 0.68101715 | CI1: 0.66630516 | CJ1: 0.65159317 | CK1: 0.66642628 | CL1: 0.68125939 | CM1: 0.70841559 | CN1: 0.73557179 | CO1: 0.75338333 | CP1: 0.77119486 | CQ1: 0.72124566 | CR1: 0.67129645 | CS1: 0.64981511 | CT1: 0.62833377 | CU1: 0.60123272 | CV1: 0.57413168 | CW1: 0.56508592 | CX1: 0.55604015 | CY1: 0.55338222 | CZ1: 0.55072429 | DA1: 0.58093574 | DB1: 0.61114719 | DC1: 0.63367452 | DD1: 0.65620186 | DE1: 0.62969687 | DF1: 0.60319188 | DG1: 0.60192287 | DH1: 0.60065387 | DI1: 0.62102433 | DJ1: 0.64139479 | DK1: 0.59195239 | DL1: 0.54250998 | DM1: 0.54058664 | DN1: 0.5386633 | DO1: 0.50839447 | DP1: 0.47812565 | DQ1: 0.50437137 | DR1: 0.53061708
A2: ZC_10 | B2: 0.93039436 | C2: 0.88025894 | D2: 0.82821729 | E2: 0.78295869 | F2: 0.7377001 | G2: 0.76312203 | H2: 0.78854396 | I2: 0.75628876 | J2: 0.72403356 | K2: 0.67595355 | L2: 0.62787354 | M2: 0.66489999 | N2: 0.70192645 | O2: 0.68556549 | P2: 0.66920452 | Q2: 0.61538653 | R2: 0.56156854 | S2: 0.5491375 | T2: 0.53670646 | U2: 0.50990365 | V2: 0.48310085 | W2: 0.50597318 | X2: 0.52884551 | Y2: 0.49177592 | Z2: 0.45470633 | AA2: 0.45948069 | AB2: 0.46425505 | AC2: 0.47642974 | AD2: 0.48860443 | AE2: 0.48836788 | AF2: 0.48813132 | AG2: 0.45658749 | AH2: 0.42504366 | AI2: 0.39344139 | AJ2: 0.36183912 | AK2: 0.3576492 | AL2: 0.35345928 | AM2: 0.33757235 | AN2: 0.32168542 | AO2: 0.31454733 | AP2: 0.30740924 | AQ2: 0.2911118 | AR2: 0.27481436 | AS2: 0.2616545 | AT2: 0.24849465 | AU2: 0.25026816 | AV2: 0.25204166 | AW2: 0.25996507 | AX2: 0.26788848 | AY2: 0.2765839 | AZ2: 0.28527931 | BA2: 0.26556417 | BB2: 0.24584903 | BC2: 0.26345754 | BD2: 0.28106606 | BE2: 0.28480816 | BF2: 0.28855027 | BG2: 0.280016 | BH2: 0.27148173 | BI2: 0.27743768 | BJ2: 0.28339363 | BK2: 0.29056548 | BL2: 0.29773733 | BM2: 0.28831569 | BN2: 0.27889405 | BO2: 0.27160213 | BP2: 0.26431022 | BQ2: 0.2595954 | BR2: 0.25488058 | BS2: 0.23532403 | BT2: 0.21576747 | BU2: 0.21653992 | BV2: 0.21731236 | BW2: 0.22410059 | BX2: 0.23088881 | BY2: 0.23309335 | BZ2: 0.2352979 | CA2: 0.23272745 | CB2: 0.23015699 | CC2: 0.22134094 | CD2: 0.21252489 | CE2: 0.2138283 | CF2: 0.21513171 | CG2: 0.21164122 | CH2: 0.20815074 | CI2: 0.22331358 | CJ2: 0.23847643 | CK2: 0.2431003 | CL2: 0.24772417 | CM2: 0.24367969 | CN2: 0.23963522 | CO2: 0.23929458 | CP2: 0.23895394 | CQ2: 0.23339973 | CR2: 0.22784552 | CS2: 0.2318211 | CT2: 0.23579667 | CU2: 0.23324501 | CV2: 0.23069335 | CW2: 0.23969195 | CX2: 0.24869055 | CY2: 0.23703623 | CZ2: 0.22538192 | DA2: 0.2219365 | DB2: 0.21849108 | DC2: 0.23774683 | DD2: 0.25700259 | DE2: 0.26793618 | DF2: 0.27886978 | DG2: 0.26257226 | DH2: 0.24627475 | DI2: 0.24726045 | DJ2: 0.24824616 | DK2: 0.25530173 | DL2: 0.2623573 | DM2: 0.26015042 | DN2: 0.25794354 | DO2: 0.25288397 | DP2: 0.2478244 | DQ2: 0.25178444 | DR2: 0.25574449
A3: ZC_10 | B3: 0.93039436 | C3: 0.92622346 | D3: 0.92014634 | E3: 0.93416054 | F3: 0.94817475 | G3: 0.96305966 | H3: 0.97794457 | I3: 0.99259292 | J3: 1.0072413 | K3: 0.97717067 | L3: 0.94710006 | M3: 0.98969892 | N3: 1.0322978 | O3: 1.0427546 | P3: 1.0532115 | Q3: 1.0180883 | R3: 0.98296501 | S3: 0.90803858 | T3: 0.83311216 | U3: 0.82901549 | V3: 0.82491883 | W3: 0.83904181 | X3: 0.85316478 | Y3: 0.80838622 | Z3: 0.76360766 | AA3: 0.71992812 | AB3: 0.67624858 | AC3: 0.6572897 | AD3: 0.63833083 | AE3: 0.60953675 | AF3: 0.58074266 | AG3: 0.57992096 | AH3: 0.57909926 | AI3: 0.5767866 | AJ3: 0.57447394 | AK3: 0.56059236 | AL3: 0.54671078 | AM3: 0.53549395 | AN3: 0.52427713 | AO3: 0.53413562 | AP3: 0.54399411 | AQ3: 0.50937388 | AR3: 0.47475365 | AS3: 0.46262904 | AT3: 0.45050443 | AU3: 0.46796168 | AV3: 0.48541893 | AW3: 0.50021948 | AX3: 0.51502004 | AY3: 0.52079667 | AZ3: 0.5265733 | BA3: 0.54378535 | BB3: 0.56099741 | BC3: 0.58426112 | BD3: 0.60752483 | BE3: 0.5904215 | BF3: 0.57331817 | BG3: 0.5507447 | BH3: 0.52817122 | BI3: 0.52069921 | BJ3: 0.5132272 | BK3: 0.5220555 | BL3: 0.5308838 | BM3: 0.54344904 | BN3: 0.55601427 | BO3: 0.53417738 | BP3: 0.51234048 | BQ3: 0.5027753 | BR3: 0.49321012 | BS3: 0.5250739 | BT3: 0.55693767 | BU3: 0.58713172 | BV3: 0.61732577 | BW3: 0.59638757 | BX3: 0.57544937 | BY3: 0.53148777 | BZ3: 0.48752617 | CA3: 0.49303322 | CB3: 0.49854028 | CC3: 0.49208559 | CD3: 0.48563089 | CE3: 0.44197692 | CF3: 0.39832294 | CG3: 0.42552692 | CH3: 0.4527309 | CI3: 0.46766384 | CJ3: 0.48259679 | CK3: 0.47599528 | CL3: 0.46939376 | CM3: 0.46605834 | CN3: 0.46272292 | CO3: 0.45465499 | CP3: 0.44658705 | CQ3: 0.43308889 | CR3: 0.41959072 | CS3: 0.40105088 | CT3: 0.38251104 | CU3: 0.36874704 | CV3: 0.35498303 | CW3: 0.3540029 | CX3: 0.35302277 | CY3: 0.35080201 | CZ3: 0.34858125 | DA3: 0.33959803 | DB3: 0.33061481 | DC3: 0.32501241 | DD3: 0.31941001 | DE3: 0.31950439 | DF3: 0.31959877 | DG3: 0.34510396 | DH3: 0.37060914 | DI3: 0.36796663 | DJ3: 0.36532412 | DK3: 0.34308756 | DL3: 0.32085099 | DM3: 0.30413591 | DN3: 0.28742084 | DO3: 0.27678541 | DP3: 0.26614999 | DQ3: 0.27351856 | DR3: 0.28088713
A4: ZC_10 | B4: 0.93039436 | C4: 0.89640205 | D4: 0.86050352 | E4: 0.88113303 | F4: 0.90176253 | G4: 0.87150597 | H4: 0.84124941 | I4: 0.83642386 | J4: 0.8315983 | K4: 0.86359349 | L4: 0.89558868 | M4: 0.8637401 | N4: 0.83189153 | O4: 0.8064146 | P4: 0.78093767 | Q4: 0.77263727 | R4: 0.76433687 | S4: 0.77010919 | T4: 0.77588151 | U4: 0.77419759 | V4: 0.77251366 | W4: 0.79598486 | X4: 0.81945606 | Y4: 0.80696098 | Z4: 0.79446591 | AA4: 0.74507898 | AB4: 0.69569204 | AC4: 0.67297713 | AD4: 0.65026222 | AE4: 0.67351626 | AF4: 0.6967703 | AG4: 0.62909797 | AH4: 0.56142564 | AI4: 0.55597843 | AJ4: 0.55053122 | AK4: 0.53087392 | AL4: 0.51121663 | AM4: 0.49502901 | AN4: 0.47884138 | AO4: 0.47698216 | AP4: 0.47512295 | AQ4: 0.44513034 | AR4: 0.41513773 | AS4: 0.40450814 | AT4: 0.39387856 | AU4: 0.365244 | AV4: 0.33660943 | AW4: 0.32917768 | AX4: 0.32174593 | AY4: 0.3160099 | AZ4: 0.31027387 | BA4: 0.32964866 | BB4: 0.34902345 | BC4: 0.36600663 | BD4: 0.38298982 | BE4: 0.37936037 | BF4: 0.37573093 | BG4: 0.376372 | BH4: 0.37701307 | BI4: 0.37225875 | BJ4: 0.36750443 | BK4: 0.3511436 | BL4: 0.33478277 | BM4: 0.33545701 | BN4: 0.33613125 | BO4: 0.31847074 | BP4: 0.30081022 | BQ4: 0.29648287 | BR4: 0.29215551 | BS4: 0.28960593 | BT4: 0.28705634 | BU4: 0.29543779 | BV4: 0.30381923 | BW4: 0.31977946 | BX4: 0.33573969 | BY4: 0.36831581 | BZ4: 0.40089192 | CA4: 0.4054989 | CB4: 0.41010588 | CC4: 0.41156815 | CD4: 0.41303041 | CE4: 0.43072132 | CF4: 0.44841223 | CG4: 0.45882796 | CH4: 0.4692437 | CI4: 0.50033502 | CJ4: 0.53142635 | CK4: 0.52201179 | CL4: 0.51259723 | CM4: 0.49723142 | CN4: 0.48186562 | CO4: 0.50043883 | CP4: 0.51901203 | CQ4: 0.50366931 | CR4: 0.48832658 | CS4: 0.47931125 | CT4: 0.47029593 | CU4: 0.48152686 | CV4: 0.49275778 | CW4: 0.48613508 | CX4: 0.47951238 | CY4: 0.47631914 | CZ4: 0.47312589 | DA4: 0.46251913 | DB4: 0.45191236 | DC4: 0.45920985 | DD4: 0.46650734 | DE4: 0.4652875 | DF4: 0.46406767 | DG4: 0.46047733 | DH4: 0.45688698 | DI4: 0.47887699 | DJ4: 0.50086699 | DK4: 0.50011441 | DL4: 0.49936183 | DM4: 0.48146039 | DN4: 0.46355895 | DO4: 0.44820352 | DP4: 0.43284809 | DQ4: 0.41768992 | DR4: 0.40253176
A5: ZC_10 | B5: 0.93039436 | C5: 0.8937533 | D5: 0.85520601 | E5: 0.88667705 | F5: 0.9181481 | G5: 0.99992242 | H5: 1.0816967 | I5: 1.0109317 | J5: 0.94016658 | K5: 0.92123331 | L5: 0.90230004 | M5: 0.85366021 | N5: 0.80502037 | O5: 0.77799002 | P5: 0.75095966 | Q5: 0.69818534 | R5: 0.64541102 | S5: 0.61574874 | T5: 0.58608646 | U5: 0.5706172 | V5: 0.55514794 | W5: 0.54396981 | X5: 0.53279168 | Y5: 0.51726085 | Z5: 0.50173003 | AA5: 0.49738565 | AB5: 0.49304128 | AC5: 0.48708916 | AD5: 0.48113704 | AE5: 0.49745366 | AF5: 0.51377028 | AG5: 0.52609572 | AH5: 0.53842116 | AI5: 0.51759617 | AJ5: 0.49677117 | AK5: 0.49514945 | AL5: 0.49352774 | AM5: 0.48858767 | AN5: 0.4836476 | AO5: 0.46229747 | AP5: 0.44094735 | AQ5: 0.44445708 | AR5: 0.44796682 | AS5: 0.43364119 | AT5: 0.41931556 | AU5: 0.40078955 | AV5: 0.38226353 | AW5: 0.35561745 | AX5: 0.32897137 | AY5: 0.32007119 | AZ5: 0.31117102 | BA5: 0.30243702 | BB5: 0.29370302 | BC5: 0.29948252 | BD5: 0.30526202 | BE5: 0.29146065 | BF5: 0.27765928 | BG5: 0.2847462 | BH5: 0.29183312 | BI5: 0.28008362 | BJ5: 0.26833412 | BK5: 0.2648408 | BL5: 0.26134748 | BM5: 0.24877127 | BN5: 0.23619506 | BO5: 0.23302132 | BP5: 0.22984758 | BQ5: 0.21736451 | BR5: 0.20488145 | BS5: 0.21897756 | BT5: 0.23307368 | BU5: 0.23031447 | BV5: 0.22755526 | BW5: 0.22247409 | BX5: 0.21739293 | BY5: 0.21149848 | BZ5: 0.20560404 | CA5: 0.20162607 | CB5: 0.1976481 | CC5: 0.19947584 | CD5: 0.20130359 | CE5: 0.2019131 | CF5: 0.20252261 | CG5: 0.20841865 | CH5: 0.21431469 | CI5: 0.21666414 | CJ5: 0.21901358 | CK5: 0.21229201 | CL5: 0.20557044 | CM5: 0.20536332 | CN5: 0.20515621 | CO5: 0.19494907 | CP5: 0.18474194 | CQ5: 0.16940502 | CR5: 0.15406811 | CS5: 0.14836112 | CT5: 0.14265413 | CU5: 0.14276453 | CV5: 0.14287493 | CW5: 0.14417696 | CX5: 0.14547899 | CY5: 0.14527549 | CZ5: 0.14507199 | DA5: 0.14660125 | DB5: 0.1481305 | DC5: 0.14380206 | DD5: 0.13947362 | DE5: 0.13417603 | DF5: 0.12887845 | DG5: 0.12825412 | DH5: 0.12762979 | DI5: 0.12696036 | DJ5: 0.12629093 | DK5: 0.12196917 | DL5: 0.11764742 | DM5: 0.11774837 | DN5: 0.11784932 | DO5: 0.12464181 | DP5: 0.13143429 | DQ5: 0.13290384 | DR5: 0.13437339
A6: ZC_10 | B6: 0.93039436 | C6: 0.92007264 | D6: 0.9078447 | E6: 0.91477746 | F6: 0.92171022 | G6: 1.0099554 | H6: 1.0982006 | I6: 1.0944653 | J6: 1.09073 | K6: 1.0903069 | L6: 1.0898838 | M6: 1.0730614 | N6: 1.056239 | O6: 0.98727218 | P6: 0.91830536 | Q6: 0.8841212 | R6: 0.84993705 | S6: 0.79105797 | T6: 0.73217888 | U6: 0.72396039 | V6: 0.7157419 | W6: 0.7341604 | X6: 0.7525789 | Y6: 0.71823442 | Z6: 0.68388994 | AA6: 0.66822208 | AB6: 0.65255422 | AC6: 0.63459521 | AD6: 0.61663621 | AE6: 0.65457955 | AF6: 0.69252289 | AG6: 0.66109623 | AH6: 0.62966956 | AI6: 0.61379951 | AJ6: 0.59792947 | AK6: 0.60990558 | AL6: 0.62188169 | AM6: 0.62340937 | AN6: 0.62493704 | AO6: 0.62794897 | AP6: 0.6309609 | AQ6: 0.56858901 | AR6: 0.50621712 | AS6: 0.5063432 | AT6: 0.50646928 | AU6: 0.50333768 | AV6: 0.50020608 | AW6: 0.49853762 | AX6: 0.49686915 | AY6: 0.46068767 | AZ6: 0.42450618 | BA6: 0.45921609 | BB6: 0.493926 | BC6: 0.53070797 | BD6: 0.56748994 | BE6: 0.54460678 | BF6: 0.52172362 | BG6: 0.51866901 | BH6: 0.51561441 | BI6: 0.51236247 | BJ6: 0.50911053 | BK6: 0.48751463 | BL6: 0.46591873 | BM6: 0.46573597 | BN6: 0.46555321 | BO6: 0.45259026 | BP6: 0.43962731 | BQ6: 0.43037896 | BR6: 0.42113061 | BS6: 0.39801591 | BT6: 0.3749012 | BU6: 0.35589222 | BV6: 0.33688324 | BW6: 0.31065134 | BX6: 0.28441944 | BY6: 0.2949221 | BZ6: 0.30542476 | CA6: 0.30856991 | CB6: 0.31171506 | CC6: 0.3228492 | CD6: 0.33398333 | CE6: 0.32562419 | CF6: 0.31726505 | CG6: 0.30051032 | CH6: 0.2837556 | CI6: 0.28623599 | CJ6: 0.28871638 | CK6: 0.27887718 | CL6: 0.26903798 | CM6: 0.25572534 | CN6: 0.2424127 | CO6: 0.23387131 | CP6: 0.22532992 | CQ6: 0.23861161 | CR6: 0.25189329 | CS6: 0.25710211 | CT6: 0.26231092 | CU6: 0.2710041 | CV6: 0.27969728 | CW6: 0.28043234 | CX6: 0.28116739 | CY6: 0.27886288 | CZ6: 0.27655837 | DA6: 0.25973821 | DB6: 0.24291806 | DC6: 0.23177675 | DD6: 0.22063545 | DE6: 0.22712802 | DF6: 0.2336206 | DG6: 0.23134241 | DH6: 0.22906423 | DI6: 0.21902994 | DJ6: 0.20899566 | DK6: 0.22492646 | DL6: 0.24085727 | DM6: 0.23871511 | DN6: 0.23657294 | DO6: 0.24812839 | DP6: 0.25968383 | DQ6: 0.2440379 | DR6: 0.22839198
A7: ZC_10 | B7: 0.93039436 | C7: 0.96730186 | D7: 1.0023031 | E7: 1.0379684 | F7: 1.0736338 | G7: 1.0158767 | H7: 0.95811964 | I7: 0.97897157 | J7: 0.9998235 | K7: 1.0557362 | L7: 1.1116488 | M7: 1.0390133 | N7: 0.96637778 | O7: 0.97892437 | P7: 0.99147096 | Q7: 1.0754357 | R7: 1.1594004 | S7: 1.1752402 | T7: 1.19108 | U7: 1.2433174 | V7: 1.2955547 | W7: 1.224634 | X7: 1.1537134 | Y7: 1.228284 | Z7: 1.3028547 | AA7: 1.2684228 | AB7: 1.2339909 | AC7: 1.1815081 | AD7: 1.1290254 | AE7: 1.1047589 | AF7: 1.0804924 | AG7: 1.130113 | AH7: 1.1797336 | AI7: 1.2454237 | AJ7: 1.3111138 | AK7: 1.2898169 | AL7: 1.2685199 | AM7: 1.2929747 | AN7: 1.3174295 | AO7: 1.3123128 | AP7: 1.307196 | AQ7: 1.3498178 | AR7: 1.3924397 | AS7: 1.4312711 | AT7: 1.4701026 | AU7: 1.4294377 | AV7: 1.3887729 | AW7: 1.3218267 | AX7: 1.2548805 | AY7: 1.1946254 | AZ7: 1.1343703 | BA7: 1.2014729 | BB7: 1.2685754 | BC7: 1.1699231 | BD7: 1.0712709 | BE7: 1.0400573 | BF7: 1.0088437 | BG7: 1.0231091 | BH7: 1.0373745 | BI7: 1.0002024 | BJ7: 0.96303024 | BK7: 0.92531875 | BL7: 0.88760725 | BM7: 0.90373377 | BN7: 0.91986029 | BO7: 0.93108496 | BP7: 0.94230962 | BQ7: 0.9451495 | BR7: 0.94798939 | BS7: 1.0181111 | BT7: 1.0882328 | BU7: 1.0691539 | BV7: 1.0500749 | BW7: 1.0056731 | BX7: 0.96127133 | BY7: 0.93894155 | BZ7: 0.91661178 | CA7: 0.91436738 | CB7: 0.91212298 | CC7: 0.93632373 | CD7: 0.96052447 | CE7: 0.94237764 | CF7: 0.9242308 | CG7: 0.92630408 | CH7: 0.92837735 | CI7: 0.85862098 | CJ7: 0.78886462 | CK7: 0.76436927 | CL7: 0.73987392 | CM7: 0.74198565 | CN7: 0.74409739 | CO7: 0.73566118 | CP7: 0.72722497 | CQ7: 0.73468644 | CR7: 0.7421479 | CS7: 0.72056745 | CT7: 0.69898701 | CU7: 0.69753793 | CV7: 0.69608885 | CW7: 0.66237153 | CX7: 0.62865422 | CY7: 0.6522145 | CZ7: 0.67577477 | DA7: 0.67762366 | DB7: 0.67947254 | DC7: 0.62140929 | DD7: 0.56334604 | DE7: 0.53433225 | DF7: 0.50531846 | DG7: 0.5319983 | DH7: 0.55867813 | DI7: 0.54933061 | DJ7: 0.53998308 | DK7: 0.51901734 | DL7: 0.49805159 | DM7: 0.49604335 | DN7: 0.4940351 | DO7: 0.49752053 | DP7: 0.50100596 | DQ7: 0.48743611 | DR7: 0.47386626
A8: ZC_10 | B8: 0.93039436 | C8: 0.91723331 | D8: 0.90216603 | E8: 0.86873796 | F8: 0.83530988 | G8: 0.80393422 | H8: 0.77255856 | I8: 0.74563001 | J8: 0.71870145 | K8: 0.72783074 | L8: 0.73696004 | M8: 0.69703159 | N8: 0.65710315 | O8: 0.64353904 | P8: 0.62997493 | Q8: 0.64617056 | R8: 0.66236619 | S8: 0.71484112 | T8: 0.76731606 | U8: 0.76301873 | V8: 0.7587214 | W8: 0.73693298 | X8: 0.71514455 | Y8: 0.74547845 | Z8: 0.77581235 | AA8: 0.81148304 | AB8: 0.84715373 | AC8: 0.85567789 | AD8: 0.86420205 | AE8: 0.88619385 | AF8: 0.90818566 | AG8: 0.88703958 | AH8: 0.8658935 | AI8: 0.84585693 | AJ8: 0.82582037 | AK8: 0.82297173 | AL8: 0.82012308 | AM8: 0.81423505 | AN8: 0.80834702 | AO8: 0.77351955 | AP8: 0.73869208 | AQ8: 0.77235759 | AR8: 0.80602311 | AS8: 0.80845998 | AT8: 0.81089686 | AU8: 0.76599125 | AV8: 0.72108564 | AW8: 0.68690686 | AX8: 0.65272808 | AY8: 0.63364546 | AZ8: 0.61456283 | BA8: 0.58524887 | BB8: 0.55593491 | BC8: 0.52577451 | BD8: 0.4956141 | BE8: 0.5016819 | BF8: 0.50774969 | BG8: 0.52048178 | BH8: 0.53321387 | BI8: 0.5324898 | BJ8: 0.53176573 | BK8: 0.51478273 | BL8: 0.49779972 | BM8: 0.47959858 | BN8: 0.46139743 | BO8: 0.47376175 | BP8: 0.48612607 | BQ8: 0.48801349 | BR8: 0.48990091 | BS8: 0.45575074 | BT8: 0.42160058 | BU8: 0.39562512 | BV8: 0.36964967 | BW8: 0.37767133 | BX8: 0.385693 | BY8: 0.41404163 | BZ8: 0.44239025 | CA8: 0.43174129 | CB8: 0.42109232 | CC8: 0.42072158 | CD8: 0.42035085 | CE8: 0.45976104 | CF8: 0.49917123 | CG8: 0.46300426 | CH8: 0.42683729 | CI8: 0.40832837 | CJ8: 0.38981946 | CK8: 0.39014522 | CL8: 0.39047099 | CM8: 0.38791229 | CN8: 0.38535359 | CO8: 0.3872338 | CP8: 0.389114 | CQ8: 0.39605702 | CR8: 0.40300003 | CS8: 0.41694322 | CT8: 0.43088641 | CU8: 0.44162735 | CV8: 0.45236829 | CW8: 0.44761514 | CX8: 0.44286198 | CY8: 0.43989858 | CZ8: 0.43693519 | DA8: 0.4429867 | DB8: 0.44903822 | DC8: 0.45115789 | DD8: 0.45327757 | DE8: 0.44709965 | DF8: 0.44092174 | DG8: 0.40608543 | DH8: 0.37124911 | DI8: 0.36909003 | DJ8: 0.36693095 | DK8: 0.38709189 | DL8: 0.40725283 | DM8: 0.42531034 | DN8: 0.44336786 | DO8: 0.45493868 | DP8: 0.46650951 | DQ8: 0.44897964 | DR8: 0.43144976
A9: ZC_10 | B9: 0.93039436 | C9: 0.94849856 | D9: 0.96469654 | E9: 0.92149922 | F9: 0.87830189 | G9: 0.888197 | H9: 0.8980921 | I9: 0.88429572 | J9: 0.87049933 | K9: 0.82492347 | L9: 0.7793476 | M9: 0.79737486 | N9: 0.81540213 | O9: 0.83250888 | P9: 0.84961563 | Q9: 0.85072132 | R9: 0.851827 | S9: 0.83787095 | T9: 0.8239149 | U9: 0.81705292 | V9: 0.81019094 | W9: 0.77737666 | X9: 0.74456237 | Y9: 0.7451205 | Z9: 0.74567863 | AA9: 0.78457789 | AB9: 0.82347716 | AC9: 0.83591116 | AD9: 0.84834516 | AE9: 0.80264893 | AF9: 0.75695269 | AG9: 0.82505221 | AH9: 0.89315173 | AI9: 0.8774436 | AJ9: 0.86173548 | AK9: 0.86940015 | AL9: 0.87706483 | AM9: 0.88105667 | AN9: 0.88504852 | AO9: 0.86540864 | AP9: 0.84576876 | AQ9: 0.88377047 | AR9: 0.92177218 | AS9: 0.92462373 | AT9: 0.92747528 | AU9: 0.98367052 | AV9: 1.0398658 | AW9: 1.0423451 | AX9: 1.0448245 | AY9: 1.043907 | AZ9: 1.0429895 | BA9: 0.96828139 | BB9: 0.89357333 | BC9: 0.83987528 | BD9: 0.78617723 | BE9: 0.78046972 | BF9: 0.77476221 | BG9: 0.76088039 | BH9: 0.74699857 | BI9: 0.74480996 | BJ9: 0.74262135 | BK9: 0.76600514 | BL9: 0.78938892 | BM9: 0.77630664 | BN9: 0.76322436 | BO9: 0.79559756 | BP9: 0.82797076 | BQ9: 0.82750502 | BR9: 0.82703929 | BS9: 0.82250773 | BT9: 0.81797617 | BU9: 0.78453091 | BV9: 0.75108565 | BW9: 0.70607686 | BX9: 0.66106808 | BY9: 0.59953026 | BZ9: 0.53799244 | CA9: 0.52494412 | CB9: 0.51189581 | CC9: 0.50306695 | CD9: 0.49423809 | CE9: 0.46882503 | CF9: 0.44341197 | CG9: 0.42761438 | CH9: 0.41181678 | CI9: 0.38290904 | CJ9: 0.3540013 | CK9: 0.35578102 | CL9: 0.35756075 | CM9: 0.36380285 | CN9: 0.37004495 | CO9: 0.35243023 | CP9: 0.3348155 | CQ9: 0.34054503 | CR9: 0.34627456 | CS9: 0.34836611 | CT9: 0.35045766 | CU9: 0.33817204 | CV9: 0.32588642 | CW9: 0.32596336 | CX9: 0.32604031 | CY9: 0.32397881 | CZ9: 0.32191731 | DA9: 0.32521471 | DB9: 0.32851212 | DC9: 0.31943196 | DD9: 0.3103518 | DE9: 0.3070051 | DF9: 0.3036584 | DG9: 0.3024007 | DH9: 0.301143 | DI9: 0.28438819 | DJ9: 0.26763338 | DK9: 0.26465115 | DL9: 0.26166892 | DM9: 0.26828533 | DN9: 0.27490174 | DO9: 0.28087474 | DP9: 0.28684775 | DQ9: 0.29395695 | DR9: 0.30106615
A10: ZC_10 | B10: 0.93039436 | C10: 0.95148644 | D10: 0.97067229 | E10: 0.91664986 | F10: 0.86262743 | G10: 0.78054258 | H10: 0.69845773 | I10: 0.7342169 | J10: 0.76997607 | K10: 0.77176342 | L10: 0.77355077 | M10: 0.80808529 | N10: 0.84261982 | O10: 0.86307588 | P10: 0.88353195 | Q10: 0.94615989 | R10: 1.0087878 | S10: 1.0497574 | T10: 1.090727 | U10: 1.1090723 | V10: 1.1274176 | W10: 1.136293 | X10: 1.1451683 | Y10: 1.1629577 | Z10: 1.1807471 | AA10: 1.1713457 | AB10: 1.1619443 | AC10: 1.1542463 | AD10: 1.1465482 | AE10: 1.0865601 | AF10: 1.026572 | AG10: 0.97894216 | AH10: 0.93131236 | AI10: 0.94315197 | AJ10: 0.95499157 | AK10: 0.93174597 | AL10: 0.90850036 | AM10: 0.89237689 | AN10: 0.87625341 | AO10: 0.89378671 | AP10: 0.91132001 | AQ10: 0.88277022 | AR10: 0.85422044 | AS10: 0.86271607 | AT10: 0.87121171 | AU10: 0.89344265 | AV10: 0.91567359 | AW10: 0.96877494 | AX10: 1.0218763 | AY10: 1.0309293 | AZ10: 1.0399824 | BA10: 1.0509323 | BB10: 1.0618823 | BC10: 1.0241205 | BD10: 0.98635876 | BE10: 1.0173868 | BF10: 1.0484149 | BG10: 1.0067233 | BH10: 0.96503173 | BI10: 0.99105468 | BJ10: 1.0170776 | BK10: 1.0141374 | BL10: 1.0111971 | BM10: 1.0486742 | BN10: 1.0861512 | BO10: 1.0848739 | BP10: 1.0835967 | BQ10: 1.1314664 | BR10: 1.1793361 | BS10: 1.0933827 | BT10: 1.0074293 | BU10: 1.0051187 | BV10: 1.0028081 | BW10: 1.0118779 | BX10: 1.0209476 | BY10: 1.0349694 | BZ10: 1.0489912 | CA10: 1.0555695 | CB10: 1.0621477 | CC10: 1.0381074 | CD10: 1.0140671 | CE10: 0.99792037 | CF10: 0.98177359 | CG10: 0.94172484 | CH10: 0.90167608 | CI10: 0.88032195 | CJ10: 0.85896782 | CK10: 0.87527916 | CL10: 0.8915905 | CM10: 0.88037127 | CN10: 0.86915205 | CO10: 0.90488959 | CP10: 0.94062712 | CQ10: 1.0190808 | CR10: 1.0975345 | CS10: 1.1264541 | CT10: 1.1553736 | CU10: 1.1396576 | CV10: 1.1239416 | CW10: 1.0993005 | CX10: 1.0746594 | CY10: 1.062267 | CZ10: 1.0498747 | DA10: 1.0260451 | DB10: 1.0022155 | DC10: 1.0201356 | DD10: 1.0380557 | DE10: 1.065737 | DF10: 1.0934182 | DG10: 1.0857225 | DH10: 1.0780267 | DI10: 1.0697274 | DJ10: 1.061428 | DK10: 1.086049 | DL10: 1.1106701 | DM10: 1.0959965 | DN10: 1.0813228 | DO10: 1.0129944 | DP10: 0.94466595 | DQ10: 0.923273 | DR10: 0.90188005
B11: =AVERAGE(B1:B10) -> 0.93039436 | C11: =AVERAGE(C1:C10) -> 0.92245762 | D11: =AVERAGE(D1:D10) -> 0.91261466 | E11: =AVERAGE(E1:E10) -> 0.90314044 | F11: =AVERAGE(F1:F10) -> 0.89366623 | G11: =AVERAGE(G1:G10) -> 0.88697434 | H11: =AVERAGE(H1:H10) -> 0.88028246 | I11: =AVERAGE(I1:I10) -> 0.87096419 | ... DR11: =AVERAGE(DR1:DR10) -> 0.39408081

Sheet Deflator
A1: 1 | B1: DEFLATOR | C1: =B1&A1 -> DEFLATOR1 | D1: 1.0010941 | E1: 0.99962838 | F1: 0.99948463 | G1: 0.99975926 | H1: 0.9956829 | I1: 0.98608358 | J1: 0.9733013 | K1: 0.95884773 | L1: 0.94329196 | M1: 0.92618496 | N1: 0.90863767 | O1: 0.89167494 | P1: 0.87745895 | Q1: 0.8649745 | R1: 0.85363899 | S1: 0.84188851 | T1: 0.83291749 | U1: 0.82570456 | V1: 0.81980234 | W1: 0.81328231 | X1: 0.80827287 | Y1: 0.80284504 | Z1: 0.79744191 | AA1: 0.79329389 | AB1: 0.78839799 | AC1: 0.78358581 | AD1: 0.78015327 | AE1: 0.77804277 | AF1: 0.77561966 | AG1: 0.76908826 | AH1: 0.76240139 | AI1: 0.75666174 | AJ1: 0.75274204 | AK1: 0.74956594 | AL1: 0.74654038 | AM1: 0.74254647 | AN1: 0.73587517 | AO1: 0.72815735 | AP1: 0.71991219 | AQ1: 0.71033531 | AR1: 0.69975291 | AS1: 0.69248607 | AT1: 0.68691743 | AU1: 0.67871461 | AV1: 0.67096399 | AW1: 0.66397374 | AX1: 0.65395371 | AY1: 0.64484537 | AZ1: 0.63652376 | BA1: 0.63144291 | BB1: 0.62439294 | BC1: 0.61512494 | BD1: 0.60345875 | BE1: 0.58856447 | BF1: 0.57297194 | BG1: 0.55806314 | BH1: 0.54348902 | BI1: 0.53039868 | BJ1: 0.51650248 | BK1: 0.50217187 | BL1: 0.48889989 | BM1: 0.47668372 | BN1: 0.46379107 | BO1: 0.45197246 | BP1: 0.4410039 | BQ1: 0.43027652 | BR1: 0.41958486 | BS1: 0.40986575 | BT1: 0.40103722 | BU1: 0.39304507 | BV1: 0.3861654 | BW1: 0.38014393 | BX1: 0.37528953 | BY1: 0.37250085 | BZ1: 0.36891815 | CA1: 0.36424715 | CB1: 0.35955972 | CC1: 0.35464168 | CD1: 0.34801374 | CE1: 0.34119156 | CF1: 0.33516337 | CG1: 0.32924351 | CH1: 0.32320591 | CI1: 0.31803475 | CJ1: 0.3123978 | CK1: 0.30652875 | CL1: 0.30191245 | CM1: 0.29761866 | CN1: 0.29309235 | CO1: 0.28872496 | CP1: 0.28634888 | CQ1: 0.28441273 | CR1: 0.28161143 | CS1: 0.27803702 | CT1: 0.27386079 | CU1: 0.26929402 | CV1: 0.26382515 | CW1: 0.25814313 | CX1: 0.2516882 | CY1: 0.24495265 | CZ1: 0.23870148 | DA1: 0.23248277 | DB1: 0.22655829 | DC1: 0.22166726 | DD1: 0.2169402 | DE1: 0.21314569 | DF1: 0.20945607 | DG1: 0.20503343 | DH1: 0.20102327 | DI1: 0.19713292 | DJ1: 0.19310838 | DK1: 0.18936232 | DL1: 0.18537238 | DM1: 0.18068072 | DN1: 0.17588822 | DO1: 0.17117757 | DP1: 0.16642862 | DQ1: 0.16147831 | DR1: 0.15617376 | DS1: 0.15168478
A2: 2 | B2: DEFLATOR | C2: =B2&A2 -> DEFLATOR2 | D2: 0.99990356 | E2: 0.99724423 | F2: 0.99152107 | G2: 0.98210637 | H2: 0.97375129 | I2: 0.96756241 | J2: 0.96288422 | K2: 0.95340909 | L2: 0.94125669 | M2: 0.92592069 | N2: 0.91281998 | O2: 0.90156354 | P2: 0.88808238 | Q2: 0.87140887 | R2: 0.85562569 | S2: 0.83425423 | T2: 0.81123488 | U2: 0.78734811 | V2: 0.7614806 | W2: 0.73388681 | X2: 0.70798307 | Y2: 0.68487349 | Z2: 0.66131691 | AA2: 0.63653673 | AB2: 0.61204348 | AC2: 0.58816893 | AD2: 0.56640345 | AE2: 0.54543609 | AF2: 0.52802113 | AG2: 0.51226161 | AH2: 0.49393867 | AI2: 0.47546971 | AJ2: 0.45683599 | AK2: 0.43765125 | AL2: 0.41771296 | AM2: 0.39870939 | AN2: 0.38097074 | AO2: 0.36323558 | AP2: 0.34426672 | AQ2: 0.32569311 | AR2: 0.3080026 | AS2: 0.29027829 | AT2: 0.27287439 | AU2: 0.25558749 | AV2: 0.23929004 | AW2: 0.22470711 | AX2: 0.20994492 | AY2: 0.19659774 | AZ2: 0.18431672 | BA2: 0.17320093 | BB2: 0.16304794 | BC2: 0.15292528 | BD2: 0.14299907 | BE2: 0.13398913 | BF2: 0.12588879 | BG2: 0.1183627 | BH2: 0.11146389 | BI2: 0.10489494 | BJ2: 0.098482303 | BK2: 0.09253197 | BL2: 0.08701934 | BM2: 0.081841052 | BN2: 0.076960831 | BO2: 0.072236417 | BP2: 0.067887536 | BQ2: 0.063764971 | BR2: 0.059773672 | BS2: 0.056016841 | BT2: 0.05225653 | BU2: 0.048514966 | BV2: 0.044905362 | BW2: 0.041586894 | BX2: 0.038544866 | BY2: 0.035848243 | BZ2: 0.033317455 | CA2: 0.030967916 | CB2: 0.028775607 | CC2: 0.026692402 | CD2: 0.024827583 | CE2: 0.023008609 | CF2: 0.021257897 | CG2: 0.019659641 | CH2: 0.018205022 | CI2: 0.016839001 | CJ2: 0.01563202 | CK2: 0.014517432 | CL2: 0.013509484 | CM2: 0.012583181 | CN2: 0.011723155 | CO2: 0.010921706 | CP2: 0.010199275 | CQ2: 0.0095392424 | CR2: 0.0088709408 | CS2: 0.0082339559 | CT2: 0.0076557155 | CU2: 0.0071147257 | CV2: 0.0066127153 | CW2: 0.0061435067 | CX2: 0.0057078176 | CY2: 0.0053213683 | CZ2: 0.0049375447 | DA2: 0.0045743195 | DB2: 0.0042542949 | DC2: 0.0039528728 | DD2: 0.0036744031 | DE2: 0.0034250071 | DF2: 0.0032051425 | DG2: 0.0030036922 | DH2: 0.0028169203 | DI2: 0.0026336892 | DJ2: 0.0024625633 | DK2: 0.0022975442 | DL2: 0.0021462795 | DM2: 0.0020083468 | DN2: 0.0018757778 | DO2: 0.001753304 | DP2: 0.0016378434 | DQ2: 0.0015306688 | DR2: 0.0014314469 | DS2: 0.0013370821
A3: 3 | B3: DEFLATOR | C3: =B3&A3 -> DEFLATOR3 | D3: 1.0001158 | E3: 1.0004584 | F3: 1.0015981 | G3: 1.0024821 | H3: 1.005725 | I3: 1.0106712 | J3: 1.0153694 | K3: 1.0205769 | L3: 1.0290113 | M3: 1.0332291 | N3: 1.0354692 | O3: 1.0409331 | P3: 1.0482081 | Q3: 1.0570425 | R3: 1.0643079 | S3: 1.0698705 | T3: 1.0693364 | U3: 1.0646231 | V3: 1.0563426 | W3: 1.0471259 | X3: 1.0402225 | Y3: 1.0342541 | Z3: 1.0257059 | AA3: 1.0129958 | AB3: 0.99867878 | AC3: 0.98095801 | AD3: 0.96302902 | AE3: 0.94332844 | AF3: 0.9222407 | AG3: 0.90001118 | AH3: 0.88015182 | AI3: 0.86029126 | AJ3: 0.84399999 | AK3: 0.82740602 | AL3: 0.80905386 | AM3: 0.7916046 | AN3: 0.77111935 | AO3: 0.75215159 | AP3: 0.7325185 | AQ3: 0.71355236 | AR3: 0.69568581 | AS3: 0.67504312 | AT3: 0.65346859 | AU3: 0.63166627 | AV3: 0.61011236 | AW3: 0.59065291 | AX3: 0.57326686 | AY3: 0.55566763 | AZ3: 0.54057269 | BA3: 0.52438929 | BB3: 0.51037238 | BC3: 0.49777326 | BD3: 0.48633594 | BE3: 0.47605005 | BF3: 0.46547801 | BG3: 0.45511537 | BH3: 0.44390935 | BI3: 0.43209068 | BJ3: 0.4182544 | BK3: 0.40502794 | BL3: 0.39337503 | BM3: 0.38210581 | BN3: 0.37194403 | BO3: 0.36261164 | BP3: 0.35248224 | BQ3: 0.34194072 | BR3: 0.33237707 | BS3: 0.32259159 | BT3: 0.31248008 | BU3: 0.30422942 | BV3: 0.2971451 | BW3: 0.29076706 | BX3: 0.28476146 | BY3: 0.27808511 | BZ3: 0.27076616 | CA3: 0.26247828 | CB3: 0.25403627 | CC3: 0.24573747 | CD3: 0.23792801 | CE3: 0.23004639 | CF3: 0.2221771 | CG3: 0.21303545 | CH3: 0.20392912 | CI3: 0.19601269 | CJ3: 0.18925873 | CK3: 0.18297825 | CL3: 0.17693326 | CM3: 0.17094093 | CN3: 0.16541606 | CO3: 0.15974796 | CP3: 0.15463978 | CQ3: 0.14932831 | CR3: 0.14379812 | CS3: 0.13803231 | CT3: 0.13252784 | CU3: 0.12691989 | CV3: 0.12110809 | CW3: 0.11557338 | CX3: 0.11011161 | CY3: 0.10484942 | CZ3: 0.099696865 | DA3: 0.094686676 | DB3: 0.090078607 | DC3: 0.085562842 | DD3: 0.080942371 | DE3: 0.076500914 | DF3: 0.072298635 | DG3: 0.068349138 | DH3: 0.064885527 | DI3: 0.061843922 | DJ3: 0.058831398 | DK3: 0.056019694 | DL3: 0.053259177 | DM3: 0.050390226 | DN3: 0.047671563 | DO3: 0.04495766 | DP3: 0.04232588 | DQ3: 0.039765573 | DR3: 0.037283284 | DS3: 0.035045465
A4: 4 | B4: DEFLATOR | C4: =B4&A4 -> DEFLATOR4 | D4: 0.99898208 | E4: 0.9966073 | F4: 0.99621175 | G4: 0.99663358 | H4: 0.99724186 | I4: 0.99510796 | J4: 0.99321624 | K4: 0.99176295 | L4: 0.99080844 | M4: 0.98980809 | N4: 0.98845623 | O4: 0.98526026 | P4: 0.97910149 | Q4: 0.97152831 | R4: 0.96093319 | S4: 0.95003664 | T4: 0.94039159 | U4: 0.92948693 | V4: 0.9177644 | W4: 0.90578024 | X4: 0.89658394 | Y4: 0.88887331 | Z4: 0.88217281 | AA4: 0.87265796 | AB4: 0.86374591 | AC4: 0.85310963 | AD4: 0.83825118 | AE4: 0.82151322 | AF4: 0.80654105 | AG4: 0.79278872 | AH4: 0.78113688 | AI4: 0.76566889 | AJ4: 0.74822069 | AK4: 0.73143296 | AL4: 0.71582071 | AM4: 0.69885708 | AN4: 0.67925385 | AO4: 0.65927093 | AP4: 0.63895473 | AQ4: 0.61917272 | AR4: 0.59754826 | AS4: 0.57403586 | AT4: 0.55165473 | AU4: 0.52962592 | AV4: 0.50768038 | AW4: 0.48373849 | AX4: 0.45983102 | AY4: 0.43557231 | AZ4: 0.41316618 | BA4: 0.39076167 | BB4: 0.3698563 | BC4: 0.35135451 | BD4: 0.33476786 | BE4: 0.31969433 | BF4: 0.30547796 | BG4: 0.29143084 | BH4: 0.27829574 | BI4: 0.26575976 | BJ4: 0.2535631 | BK4: 0.24189773 | BL4: 0.22990695 | BM4: 0.21816467 | BN4: 0.20670704 | BO4: 0.19603667 | BP4: 0.18557019 | BQ4: 0.1752165 | BR4: 0.16525173 | BS4: 0.15578077 | BT4: 0.14695303 | BU4: 0.13868905 | BV4: 0.13042167 | BW4: 0.12294407 | BX4: 0.11616035 | BY4: 0.10983319 | BZ4: 0.10458387 | CA4: 0.099976422 | CB4: 0.095862986 | CC4: 0.091709911 | CD4: 0.087714865 | CE4: 0.083922519 | CF4: 0.08053034 | CG4: 0.077473943 | CH4: 0.074664398 | CI4: 0.072010586 | CJ4: 0.070015179 | CK4: 0.068294204 | CL4: 0.066314106 | CM4: 0.064229856 | CN4: 0.062209653 | CO4: 0.060116558 | CP4: 0.058260125 | CQ4: 0.056570285 | CR4: 0.055070997 | CS4: 0.053431875 | CT4: 0.051737436 | CU4: 0.049950846 | CV4: 0.048349675 | CW4: 0.046795162 | CX4: 0.045416589 | CY4: 0.043912897 | CZ4: 0.042528613 | DA4: 0.041115332 | DB4: 0.039671407 | DC4: 0.038297881 | DD4: 0.03699168 | DE4: 0.035760599 | DF4: 0.034566428 | DG4: 0.033421905 | DH4: 0.032285463 | DI4: 0.031159933 | DJ4: 0.030110236 | DK4: 0.029162022 | DL4: 0.028269781 | DM4: 0.027377918 | DN4: 0.026516013 | DO4: 0.02561574 | DP4: 0.024663757 | DQ4: 0.023703324 | DR4: 0.022766768 | DS4: 0.021803478
A5: 5 | B5: DEFLATOR | C5: =B5&A5 -> DEFLATOR5 | D5: 1.0013843 | E5: 1.0001407 | F5: 0.99827331 | G5: 0.99964283 | H5: 1.0050668 | I5: 1.0126289 | J5: 1.021222 | K5: 1.0265621 | L5: 1.0270704 | M5: 1.0281822 | N5: 1.0282622 | O5: 1.0224706 | P5: 1.0139189 | Q5: 1.0060871 | R5: 0.99329122 | S5: 0.9755247 | T5: 0.95284279 | U5: 0.92745065 | V5: 0.90400945 | W5: 0.88025975 | X5: 0.85448826 | Y5: 0.82889395 | Z5: 0.80020312 | AA5: 0.77249741 | AB5: 0.74754657 | AC5: 0.72328709 | AD5: 0.69836001 | AE5: 0.67405658 | AF5: 0.65166452 | AG5: 0.63273565 | AH5: 0.61322167 | AI5: 0.5964938 | AJ5: 0.58133479 | AK5: 0.56607834 | AL5: 0.55040967 | AM5: 0.53601923 | AN5: 0.52041235 | AO5: 0.5042553 | AP5: 0.48766285 | AQ5: 0.47069645 | AR5: 0.45498828 | AS5: 0.43940402 | AT5: 0.4233149 | AU5: 0.40783366 | AV5: 0.39093766 | AW5: 0.37349104 | AX5: 0.35560418 | AY5: 0.33707627 | AZ5: 0.32019043 | BA5: 0.30294436 | BB5: 0.28622179 | BC5: 0.27037528 | BD5: 0.25522497 | BE5: 0.24116392 | BF5: 0.22717416 | BG5: 0.21341995 | BH5: 0.20087679 | BI5: 0.18912189 | BJ5: 0.17851129 | BK5: 0.16795688 | BL5: 0.15742405 | BM5: 0.14730583 | BN5: 0.13751726 | BO5: 0.12780532 | BP5: 0.11880392 | BQ5: 0.11044632 | BR5: 0.10238461 | BS5: 0.094660621 | BT5: 0.08765624 | BU5: 0.081448309 | BV5: 0.075641669 | BW5: 0.070313445 | BX5: 0.06526154 | BY5: 0.060498196 | BZ5: 0.055984174 | CA5: 0.051853397 | CB5: 0.047881568 | CC5: 0.044239256 | CD5: 0.040823405 | CE5: 0.037669387 | CF5: 0.034746969 | CG5: 0.032039352 | CH5: 0.029611277 | CI5: 0.027432841 | CJ5: 0.025414384 | CK5: 0.023573097 | CL5: 0.021802681 | CM5: 0.020205872 | CN5: 0.018659623 | CO5: 0.017245165 | CP5: 0.015937853 | CQ5: 0.01464326 | CR5: 0.01344068 | CS5: 0.012264756 | CT5: 0.011141158 | CU5: 0.01007438 | CV5: 0.0091207448 | CW5: 0.0082761586 | CX5: 0.0075244633 | CY5: 0.0068350148 | CZ5: 0.0062102476 | DA5: 0.0056348433 | DB5: 0.005115008 | DC5: 0.0046557207 | DD5: 0.0042193224 | DE5: 0.0038213819 | DF5: 0.0034598893 | DG5: 0.0031279071 | DH5: 0.0028176804 | DI5: 0.0025389793 | DJ5: 0.0022862161 | DK5: 0.0020595181 | DL5: 0.0018544357 | DM5: 0.001667102 | DN5: 0.0014946678 | DO5: 0.0013410067 | DP5: 0.0012058185 | DQ5: 0.0010857048 | DR5: 0.0009795046 | DS5: 0.0008861367
A6: 6 | B6: DEFLATOR | C6: =B6&A6 -> DEFLATOR6 | D6: 1.0007942 | E6: 1.0036897 | F6: 1.0049216 | G6: 1.0052895 | H6: 1.00933 | I6: 1.0180452 | J6: 1.0290437 | K6: 1.0407687 | L6: 1.0526122 | M6: 1.0650751 | N6: 1.07685 | O6: 1.0866259 | P6: 1.0916512 | Q6: 1.0930575 | R6: 1.0915438 | S6: 1.0891975 | T6: 1.0821042 | U6: 1.0717749 | V6: 1.058908 | W6: 1.0460945 | X6: 1.0307516 | Y6: 1.0154926 | Z6: 0.9997824 | AA6: 0.98210843 | AB6: 0.96504321 | AC6: 0.94772463 | AD6: 0.928922 | AE6: 0.90906403 | AF6: 0.89023249 | AG6: 0.87674597 | AH6: 0.86401895 | AI6: 0.85071143 | AJ6: 0.83561007 | AK6: 0.81965112 | AL6: 0.80326276 | AM6: 0.78747695 | AN6: 0.77395799 | AO6: 0.76081105 | AP6: 0.74726051 | AQ6: 0.73400114 | AR6: 0.72078713 | AS6: 0.70335689 | AT6: 0.6835395 | AU6: 0.6657471 | AV6: 0.6470335 | AW6: 0.62729464 | AX6: 0.61020087 | AY6: 0.59206512 | AZ6: 0.57308105 | BA6: 0.55121493 | BB6: 0.53126932 | BC6: 0.51342565 | BD6: 0.4977228 | BE6: 0.48475995 | BF6: 0.47248509 | BG6: 0.45982364 | BH6: 0.44709175 | BI6: 0.43337785 | BJ6: 0.42061899 | BK6: 0.40854791 | BL6: 0.39594376 | BM6: 0.38279429 | BN6: 0.37048544 | BO6: 0.35764346 | BP6: 0.34454092 | BQ6: 0.33172426 | BR6: 0.31933876 | BS6: 0.30663902 | BT6: 0.2936919 | BU6: 0.28057196 | BV6: 0.26715497 | BW6: 0.25370441 | BX6: 0.24008531 | BY6: 0.22582097 | BZ6: 0.21269903 | CA6: 0.20077945 | CB6: 0.18942837 | CC6: 0.17876062 | CD6: 0.1694458 | CE6: 0.16064009 | CF6: 0.15186058 | CG6: 0.14344501 | CH6: 0.13551345 | CI6: 0.12765954 | CJ6: 0.12038542 | CK6: 0.11353903 | CL6: 0.10659056 | CM6: 0.099924202 | CN6: 0.093711799 | CO6: 0.087797604 | CP6: 0.081651158 | CQ6: 0.075778651 | CR6: 0.070502024 | CS6: 0.065731852 | CT6: 0.061379171 | CU6: 0.057366899 | CV6: 0.053783234 | CW6: 0.050462535 | CX6: 0.047489184 | CY6: 0.044740459 | CZ6: 0.042063275 | DA6: 0.039534172 | DB6: 0.037104616 | DC6: 0.034661775 | DD6: 0.032357439 | DE6: 0.030078602 | DF6: 0.02793689 | DG6: 0.026023811 | DH6: 0.024183668 | DI6: 0.02245692 | DJ6: 0.020866952 | DK6: 0.019359202 | DL6: 0.017977256 | DM6: 0.016751949 | DN6: 0.015619938 | DO6: 0.014562321 | DP6: 0.013581814 | DQ6: 0.012683292 | DR6: 0.011873434 | DS6: 0.011061201
A7: 7 | B7: DEFLATOR | C7: =B7&A7 -> DEFLATOR7 | D7: 1.0019857 | E7: 1.0060892 | F7: 1.0129928 | G7: 1.0233591 | H7: 1.0320629 | I7: 1.0375328 | J7: 1.0401766 | K7: 1.0467057 | L7: 1.0548882 | M7: 1.0653791 | N7: 1.0719162 | O7: 1.0747075 | P7: 1.0785927 | Q7: 1.0849865 | R7: 1.0890094 | S7: 1.0991647 | T7: 1.1110266 | U7: 1.1239875 | V7: 1.1400097 | W7: 1.1592662 | X7: 1.1767634 | Y7: 1.1904143 | Z7: 1.2055769 | AA7: 1.223968 | AB7: 1.2431112 | AC7: 1.2626025 | AD7: 1.2794794 | AE7: 1.2967435 | AF7: 1.3076784 | AG7: 1.3163099 | AH7: 1.3336256 | AI7: 1.3538208 | AJ7: 1.3768592 | AK7: 1.4038177 | AL7: 1.4355985 | AM7: 1.4665775 | AN7: 1.4949612 | AO7: 1.5251539 | AP7: 1.5626313 | AQ7: 1.6008534 | AR7: 1.6375605 | AS7: 1.6779238 | AT7: 1.7207009 | AU7: 1.7678967 | AV7: 1.8142676 | AW7: 1.8535558 | AX7: 1.9007039 | AY7: 1.941988 | AZ7: 1.9790918 | BA7: 2.0095778 | BB7: 2.0344986 | BC7: 2.0651976 | BD7: 2.1003996 | BE7: 2.1293704 | BF7: 2.1504751 | BG7: 2.1680025 | BH7: 2.1799836 | BI7: 2.1913643 | BJ7: 2.2059877 | BK7: 2.2171933 | BL7: 2.2245268 | BM7: 2.2295878 | BN7: 2.2326661 | BO7: 2.2377216 | BP7: 2.2381706 | BQ7: 2.2384259 | BR7: 2.2416175 | BS7: 2.2436258 | BT7: 2.2539075 | BU7: 2.27306 | BV7: 2.2974095 | BW7: 2.3191007 | BX7: 2.3375747 | BY7: 2.3465167 | BZ7: 2.3551779 | CA7: 2.3615842 | CB7: 2.3669636 | CC7: 2.3750567 | CD7: 2.3751593 | CE7: 2.3821102 | CF7: 2.3943152 | CG7: 2.4022991 | CH7: 2.4058606 | CI7: 2.4110794 | CJ7: 2.40584 | CK7: 2.3973231 | CL7: 2.3821055 | CM7: 2.3634172 | CN7: 2.3429027 | CO7: 2.3210073 | CP7: 2.2923902 | CQ7: 2.2593422 | CR7: 2.2381139 | CS7: 2.2195757 | CT7: 2.1956599 | CU7: 2.1713504 | CV7: 2.1457706 | CW7: 2.120378 | CX7: 2.0940521 | CY7: 2.059488 | CZ7: 2.0335139 | DA7: 2.0092637 | DB7: 1.9759698 | DC7: 1.943746 | DD7: 1.9104135 | DE7: 1.8718572 | DF7: 1.8256758 | DG7: 1.7763975 | DH7: 1.7258138 | DI7: 1.6809114 | DJ7: 1.636337 | DK7: 1.5955747 | DL7: 1.5526806 | DM7: 1.5070875 | DN7: 1.4646528 | DO7: 1.4217401 | DP7: 1.3801091 | DQ7: 1.3380271 | DR7: 1.2954158 | DS7: 1.2548338
A8: 8 | B8: DEFLATOR | C8: =B8&A8 -> DEFLATOR8 | D8: 1.0017731 | E8: 1.002857 | F8: 1.0028011 | G8: 1.002559 | H8: 0.99925189 | I8: 0.99327818 | J8: 0.9864091 | K8: 0.97781822 | L8: 0.96492686 | M8: 0.95473169 | N8: 0.94494991 | O8: 0.93081594 | P8: 0.91382534 | Q8: 0.89444543 | R8: 0.87548382 | S8: 0.85709701 | T8: 0.84286252 | U8: 0.8312514 | V8: 0.82179333 | W8: 0.81248122 | X8: 0.80091381 | Y8: 0.78828133 | Z8: 0.7772875 | AA8: 0.76910551 | AB8: 0.76184469 | AC8: 0.75703911 | AD8: 0.75252305 | AE8: 0.74978201 | AF8: 0.74870022 | AG8: 0.74920739 | AH8: 0.74842684 | AI8: 0.74823588 | AJ8: 0.74525927 | AK8: 0.7425406 | AL8: 0.74119674 | AM8: 0.73867462 | AN8: 0.73858407 | AO8: 0.73654056 | AP8: 0.7344005 | AQ8: 0.7306919 | AR8: 0.72500097 | AS8: 0.72153146 | AT8: 0.71852757 | AU8: 0.71533388 | AV8: 0.71156759 | AW8: 0.70516399 | AX8: 0.69608615 | AY8: 0.68708421 | AZ8: 0.67480231 | BA8: 0.66374499 | BB8: 0.64995839 | BC8: 0.63446743 | BD8: 0.61758787 | BE8: 0.59933295 | BF8: 0.58159718 | BG8: 0.56383644 | BH8: 0.5473853 | BI8: 0.53197869 | BJ8: 0.51942252 | BK8: 0.50653608 | BL8: 0.49209239 | BM8: 0.47754261 | BN8: 0.46197231 | BO8: 0.44577992 | BP8: 0.43106821 | BQ8: 0.41742079 | BR8: 0.40312561 | BS8: 0.38959735 | BT8: 0.37692445 | BU8: 0.36248114 | BV8: 0.34719067 | BW8: 0.33168886 | BX8: 0.31641046 | BY8: 0.30249193 | BZ8: 0.28980185 | CA8: 0.27862626 | CB8: 0.26811452 | CC8: 0.25798251 | CD8: 0.24784583 | CE8: 0.23825214 | CF8: 0.229088 | CG8: 0.2216924 | CH8: 0.21477436 | CI8: 0.2071303 | CJ8: 0.19871284 | CK8: 0.19020281 | CL8: 0.18188223 | CM8: 0.17397417 | CN8: 0.1660432 | CO8: 0.15868346 | CP8: 0.15119472 | CQ8: 0.14432905 | CR8: 0.13806979 | CS8: 0.13240297 | CT8: 0.12683635 | CU8: 0.121719 | CV8: 0.11716286 | CW8: 0.11271243 | CX8: 0.10854866 | CY8: 0.10452412 | CZ8: 0.10071095 | DA8: 0.097067657 | DB8: 0.093322471 | DC8: 0.089798099 | DD8: 0.086723791 | DE8: 0.083804546 | DF8: 0.080935845 | DG8: 0.078066109 | DH8: 0.074923951 | DI8: 0.071583399 | DJ8: 0.068493756 | DK8: 0.065439547 | DL8: 0.062571124 | DM8: 0.060066298 | DN8: 0.057631068 | DO8: 0.055446451 | DP8: 0.053404739 | DQ8: 0.051503758 | DR8: 0.049735932 | DS8: 0.047875404
A9: 9 | B9: DEFLATOR | C9: =B9&A9 -> DEFLATOR9 | D9: 1.00291 | E9: 1.0067322 | F9: 1.0082231 | G9: 1.0084423 | H9: 1.0077521 | I9: 1.0088128 | J9: 1.0084104 | K9: 1.006227 | L9: 1.0021318 | M9: 0.99661392 | N9: 0.9898936 | O9: 0.98341237 | P9: 0.97832465 | Q9: 0.9731748 | R9: 0.96966615 | S9: 0.96520785 | T9: 0.95843429 | U9: 0.95210531 | V9: 0.94588033 | W9: 0.93926773 | X9: 0.9292254 | Y9: 0.91720966 | Z9: 0.90375535 | AA9: 0.89279037 | AB9: 0.88085873 | AC9: 0.8704902 | AD9: 0.86453983 | AE9: 0.86096082 | AF9: 0.85610251 | AG9: 0.85053561 | AH9: 0.84329554 | AI9: 0.84070386 | AJ9: 0.84065949 | AK9: 0.83997112 | AL9: 0.83773504 | AM9: 0.83670645 | AN9: 0.83847367 | AO9: 0.84030728 | AP9: 0.84194063 | AQ9: 0.84207026 | AR9: 0.84407055 | AS9: 0.84849202 | AT9: 0.85113961 | AU9: 0.85315364 | AV9: 0.85513681 | AW9: 0.86101721 | AX9: 0.86780384 | AY9: 0.87652601 | AZ9: 0.88288859 | BA9: 0.89072391 | BB9: 0.89689107 | BC9: 0.89886685 | BD9: 0.89720434 | BE9: 0.89245401 | BF9: 0.88622006 | BG9: 0.8805198 | BH9: 0.87313395 | BI9: 0.86492793 | BJ9: 0.85679168 | BK9: 0.84813225 | BL9: 0.84197916 | BM9: 0.83639486 | BN9: 0.83126265 | BO9: 0.82456506 | BP9: 0.81879468 | BQ9: 0.81461028 | BR9: 0.81082184 | BS9: 0.80678011 | BT9: 0.80148998 | BU9: 0.79514154 | BV9: 0.7910189 | BW9: 0.78445583 | BX9: 0.77566488 | BY9: 0.76587505 | BZ9: 0.7502929 | CA9: 0.73150589 | CB9: 0.71050169 | CC9: 0.69126627 | CD9: 0.67228587 | CE9: 0.65309102 | CF9: 0.6320364 | CG9: 0.60960288 | CH9: 0.58660819 | CI9: 0.56380833 | CJ9: 0.53714266 | CK9: 0.50960367 | CL9: 0.4852816 | CM9: 0.46301376 | CN9: 0.44151045 | CO9: 0.42167017 | CP9: 0.40131596 | CQ9: 0.38098471 | CR9: 0.36051964 | CS9: 0.34204093 | CT9: 0.3248972 | CU9: 0.3092753 | CV9: 0.29347394 | CW9: 0.278374 | CX9: 0.26317405 | CY9: 0.24956892 | CZ9: 0.23608966 | DA9: 0.22354225 | DB9: 0.21189968 | DC9: 0.20062156 | DD9: 0.18976238 | DE9: 0.179279 | DF9: 0.16928423 | DG9: 0.15964833 | DH9: 0.15057799 | DI9: 0.14207342 | DJ9: 0.13382769 | DK9: 0.12570813 | DL9: 0.11788159 | DM9: 0.11055458 | DN9: 0.10361147 | DO9: 0.097312931 | DP9: 0.091648751 | DQ9: 0.086404609 | DR9: 0.081448491 | DS9: 0.076951751
A10: 10 | B10: DEFLATOR | C10: =B10&A10 -> DEFLATOR10 | D10: 1.0005041 | E10: 1.0031755 | F10: 1.006141 | G10: 1.0054066 | H10: 0.99990629 | I10: 0.99135792 | J10: 0.98075593 | K10: 0.97211725 | L10: 0.96675033 | M10: 0.95941802 | N10: 0.95157292 | O10: 0.94762345 | P10: 0.94472954 | Q10: 0.93974653 | R10: 0.93807774 | S10: 0.93998934 | T10: 0.94591002 | U10: 0.95419572 | V10: 0.96027236 | W10: 0.96649898 | X10: 0.97500295 | Y10: 0.98357961 | Z10: 0.99633252 | AA10: 1.0085479 | AB10: 1.0177802 | AC10: 1.0267342 | AD10: 1.0377191 | AE10: 1.0493046 | AF10: 1.0595664 | AG10: 1.0656821 | AH10: 1.0742106 | AI10: 1.0791408 | AJ10: 1.0819907 | AK10: 1.0853313 | AL10: 1.0894941 | AM10: 1.0908904 | AN10: 1.0943946 | AO10: 1.0986303 | AP10: 1.1031432 | AQ10: 1.1076925 | AR10: 1.1085404 | AS10: 1.108467 | AT10: 1.1091866 | AU10: 1.1079328 | AV10: 1.1104998 | AW10: 1.1151731 | AX10: 1.1221553 | AY10: 1.132653 | AZ10: 1.1392586 | BA10: 1.1489264 | BB10: 1.1589642 | BC10: 1.1680836 | BD10: 1.1768252 | BE10: 1.1830646 | BF10: 1.1916879 | BG10: 1.2023741 | BH10: 1.2096443 | BI10: 1.2154227 | BJ10: 1.2170141 | BK10: 1.2215115 | BL10: 1.2296524 | BM10: 1.2387277 | BN10: 1.2495002 | BO10: 1.2647751 | BP10: 1.2789468 | BQ10: 1.2923306 | BR10: 1.30869 | BS10: 1.3276992 | BT10: 1.3436737 | BU10: 1.353956 | BV10: 1.363878 | BW10: 1.3716323 | BX10: 1.3806218 | BY10: 1.3904299 | BZ10: 1.4016199 | CA10: 1.4103867 | CB10: 1.422485 | CC10: 1.4330252 | CD10: 1.4445014 | CE10: 1.4550022 | CF10: 1.4648215 | CG10: 1.4740729 | CH10: 1.4791239 | CI10: 1.4799841 | CJ10: 1.4797974 | CK10: 1.4763854 | CL10: 1.4760118 | CM10: 1.471815 | CN10: 1.4719596 | CO10: 1.4699401 | CP10: 1.466993 | CQ10: 1.4718316 | CR10: 1.4771705 | CS10: 1.4901143 | CT10: 1.5087613 | CU10: 1.5334504 | CV10: 1.5557249 | CW10: 1.5739859 | CX10: 1.5884811 | CY10: 1.6034046 | CZ10: 1.6167739 | DA10: 1.6311037 | DB10: 1.6434692 | DC10: 1.6503096 | DD10: 1.6636864 | DE10: 1.6776979 | DF10: 1.6912539 | DG10: 1.7058535 | DH10: 1.7253483 | DI10: 1.7436133 | DJ10: 1.7625558 | DK10: 1.7799811 | DL10: 1.7970354 | DM10: 1.8155784 | DN10: 1.8381095 | DO10: 1.8588593 | DP10: 1.8745795 | DQ10: 1.8864027 | DR10: 1.8931191 | DS10: 1.8934051
D11: =AVERAGE(D1:D10) -> 1.0009447 | E11: =AVERAGE(E1:E10) -> 1.0016623 | F11: =AVERAGE(F1:F10) -> 1.0022168 | G11: =AVERAGE(G1:G10) -> 1.002568 | H11: =AVERAGE(H1:H10) -> 1.0025771 | I11: =AVERAGE(I1:I10) -> 1.0021081 | J11: =AVERAGE(J1:J10) -> 1.0010789 | K11: =AVERAGE(K1:K10) -> 0.99947957 | ... DS11: =AVERAGE(DS1:DS10) -> 0.34948842
D21: =M1/D1 -> 0.92517276 | E21: =N1/E1 -> 0.90897546 | F21: =O1/F1 -> 0.89213472 | G21: =P1/G1 -> 0.87767024 | H21: =Q1/H1 -> 0.86872488 | I21: =R1/I1 -> 0.86568624 | J21: =S1/J1 -> 0.86498241 | K21: =T1/K1 -> 0.86866503 | ... P21: =Y1/P1 -> 0.91496592
D22: =M2/D2 -> 0.92601 | E22: =N2/E2 -> 0.91534245 | F22: =O2/F2 -> 0.90927321 | G22: =P2/G2 -> 0.90426292 | H22: =Q2/H2 -> 0.89489881 | I22: =R2/I2 -> 0.8843106 | J22: =S2/J2 -> 0.86641178 | K22: =T2/K2 -> 0.85087807 | ... P22: =Y2/P2 -> 0.77118239
D23: =M3/D3 -> 1.0331094 | E23: =N3/E3 -> 1.0349947 | F23: =O3/F3 -> 1.0392722 | G23: =P3/G3 -> 1.0456128 | H23: =Q3/H3 -> 1.0510254 | I23: =R3/I3 -> 1.0530704 | J23: =S3/J3 -> 1.0536762 | K23: =T3/K3 -> 1.0477764 | ... P23: =Y3/P3 -> 0.98668775
D24: =M4/D4 -> 0.99081666 | E24: =N4/E4 -> 0.99182118 | F24: =O4/F4 -> 0.98900686 | G24: =P4/G4 -> 0.98240869 | H24: =Q4/H4 -> 0.97421533 | I24: =R4/I4 -> 0.96565722 | J24: =S4/J4 -> 0.95652548 | K24: =T4/K4 -> 0.94820197 | ... P24: =Y4/P4 -> 0.90784594
D25: =M5/D5 -> 1.0267608 | E25: =N5/E5 -> 1.0281175 | F25: =O5/F5 -> 1.0242391 | G25: =P5/G5 -> 1.0142812 | H25: =Q5/H5 -> 1.0010152 | I25: =R5/I5 -> 0.98090348 | J25: =S5/J5 -> 0.9552523 | K25: =T5/K5 -> 0.92818818 | ... P25: =Y5/P5 -> 0.81751505
D26: =M6/D6 -> 1.0642299 | E26: =N6/E6 -> 1.0728914 | F26: =O6/F6 -> 1.0813042 | G26: =P6/G6 -> 1.0859073 | H26: =Q6/H6 -> 1.0829536 | I26: =R6/I6 -> 1.0721958 | J26: =S6/J6 -> 1.058456 | K26: =T6/K6 -> 1.0397164 | ... P26: =Y6/P6 -> 0.9302354
D27: =M7/D7 -> 1.0632677 | E27: =N7/E7 -> 1.0654285 | F27: =O7/F7 -> 1.0609232 | G27: =P7/G7 -> 1.0539728 | H27: =Q7/H7 -> 1.0512794 | I27: =R7/I7 -> 1.0496144 | J27: =S7/J7 -> 1.0567098 | K27: =T7/K7 -> 1.0614508 | ... P27: =Y7/P7 -> 1.1036737
D28: =M8/D8 -> 0.95304189 | E28: =N8/E8 -> 0.9422579 | F28: =O8/F8 -> 0.92821593 | G28: =P8/G8 -> 0.9114928 | H28: =Q8/H8 -> 0.89511507 | I28: =R8/I8 -> 0.88140848 | J28: =S8/J8 -> 0.86890623 | K28: =T8/K8 -> 0.86198283 | ... P28: =Y8/P8 -> 0.86261706
D29: =M9/D9 -> 0.99372221 | E29: =N9/E9 -> 0.98327399 | F29: =O9/F9 -> 0.97539165 | G29: =P9/G9 -> 0.97013449 | H29: =Q9/H9 -> 0.96568867 | I29: =R9/I9 -> 0.96119528 | J29: =S9/J9 -> 0.95715777 | K29: =T9/K9 -> 0.95250301 | ... P29: =Y9/P9 -> 0.93753097
D30: =M10/D10 -> 0.95893466 | E30: =N10/E10 -> 0.94856078 | F30: =O10/F10 -> 0.94183964 | G30: =P10/G10 -> 0.93964928 | H30: =Q10/H10 -> 0.93983461 | I30: =R10/I10 -> 0.94625535 | J30: =S10/J10 -> 0.95843349 | K30: =T10/K10 -> 0.97304108 | ... P30: =Y10/P10 -> 1.041123
D31: =M11/D11 -> 0.99351572 | E31: =N11/E11 -> 0.98923842 | F31: =O11/F11 -> 0.98432668 | G31: =P11/G11 -> 0.97887552 | H31: =Q11/H11 -> 0.97313734 | I31: =R11/I11 -> 0.96711901 | J31: =S11/J11 -> 0.96118609 | K31: =T11/K11 -> 0.9552032 | ... P31: =Y11/P11 -> 0.93079445

Sheet Equity
A1: 1 | B1: EQUITY_TOTAL_RETURN | C1: =B1&A1 -> EQUITY_TOTAL_RETURN1 | D1: 0 | E1: 0.097470561 | F1: 0 | G1: -0.02372003 | H1: 0 | I1: 0.16418952 | J1: 0 | K1: -0.16536528 | L1: 0 | M1: 0.015408088 | N1: 0 | O1: 0.11625707 | P1: 0 | Q1: 0.01594496 | R1: 0 | S1: 0.14632101 | T1: 0 | U1: -0.052905635 | V1: 0 | W1: -0.19923664 | X1: 0 | Y1: 0.048497484 | Z1: 0 | AA1: 0.1552705 | AB1: 0 | AC1: 0.047737946 | AD1: 0 | AE1: 0.065332343 | AF1: 0 | AG1: -0.02110904 | AH1: 0 | AI1: -0.0076742549 | AJ1: 0 | AK1: -0.050856179 | AL1: 0 | AM1: -0.065785363 | AN1: 0 | AO1: 0.13182064 | AP1: 0 | AQ1: 0.079979174 | AR1: 0 | AS1: -0.046153584 | AT1: 0 | AU1: 0.18522277 | AV1: 0 | AW1: -0.015439381 | AX1: 0 | AY1: -5.4508926e-05 | AZ1: 0 | BA1: 0.0077239515 | BB1: 0 | BC1: 0.18321327 | BD1: 0 | BE1: 0.092388678 | BF1: 0 | BG1: -0.085057584 | BH1: 0 | BI1: -0.11745406 | BJ1: 0 | BK1: -0.13237931 | BL1: 0 | BM1: 0.014661388 | BN1: 0 | BO1: -0.12933206 | BP1: 0 | BQ1: -0.034855946 | BR1: 0 | BS1: -0.17566877 | BT1: 0 | BU1: 0.24955966 | BV1: 0 | BW1: 0.19057741 | BX1: 0 | BY1: 0.068714596 | BZ1: 0 | CA1: 0.045790505 | CB1: 0 | CC1: 0.0067043084 | CD1: 0 | CE1: -0.089630241 | CF1: 0 | CG1: 0.020079335 | CH1: 0 | CI1: -0.012342303 | CJ1: 0 | CK1: 0.14587745 | CL1: 0 | CM1: 0.26574011 | CN1: 0 | CO1: 0.13509218 | CP1: 0 | CQ1: 0.063862256 | CR1: 0 | CS1: 0.080130479 | CT1: 0 | CU1: -0.12808379 | CV1: 0 | CW1: 0.042629246 | CX1: 0 | CY1: 0.18137347 | CZ1: 0 | DA1: 0.053973943 | DB1: 0 | DC1: 0.017053958 | DD1: 0 | DE1: 0.14682533 | DF1: 0 | DG1: 0.081978027 | DH1: 0 | DI1: -0.094582869 | DJ1: 0 | DK1: 0.18298138 | DL1: 0 | DM1: 0.13718464 | DN1: 0 | DO1: 0.039815084 | DP1: 0 | DQ1: 0.084854718 | DR1: 0 | DS1: 0.11093984
A2: 2 | B2: EQUITY_TOTAL_RETURN | C2: =B2&A2 -> EQUITY_TOTAL_RETURN2 | D2: 0 | E2: -0.077478072 | F2: 0 | G2: -0.093310993 | H2: 0 | I2: 0.03618161 | J2: 0 | K2: -0.21740995 | L2: 0 | M2: 0.26438606 | N2: 0 | O2: 0.038116992 | P2: 0 | Q2: 0.10074123 | R2: 0 | S2: -0.014564744 | T2: 0 | U2: -0.097570443 | V2: 0 | W2: -0.017710005 | X2: 0 | Y2: 0.012863587 | Z2: 0 | AA2: 0.23567908 | AB2: 0 | AC2: 0.34514497 | AD2: 0 | AE2: -0.023447399 | AF2: 0 | AG2: 0.39009195 | AH2: 0 | AI2: -0.032904888 | AJ2: 0 | AK2: 0.078659419 | AL2: 0 | AM2: 0.031646378 | AN2: 0 | AO2: 0.05747705 | AP2: 0 | AQ2: 0.015377291 | AR2: 0 | AS2: 0.16810686 | AT2: 0 | AU2: -0.14325305 | AV2: 0 | AW2: -0.098859287 | AX2: 0 | AY2: 0.16474842 | AZ2: 0 | BA2: 0.083398696 | BB2: 0 | BC2: 0.1475373 | BD2: 0 | BE2: -0.043346934 | BF2: 0 | BG2: 0.10899999 | BH2: 0 | BI2: -0.044595794 | BJ2: 0 | BK2: -0.032446176 | BL2: 0 | BM2: -0.092065666 | BN2: 0 | BO2: 0.3910028 | BP2: 0 | BQ2: 0.29615946 | BR2: 0 | BS2: 0.040230336 | BT2: 0 | BU2: 0.026577086 | BV2: 0 | BW2: 0.38404627 | BX2: 0 | BY2: 0.24679483 | BZ2: 0 | CA2: 0.16608356 | CB2: 0 | CC2: 0.21658135 | CD2: 0 | CE2: 0.18730197 | CF2: 0 | CG2: 0.22263449 | CH2: 0 | CI2: 0.3903592 | CJ2: 0 | CK2: 0.033983468 | CL2: 0 | CM2: 0.14253503 | CN2: 0 | CO2: 0.15850695 | CP2: 0 | CQ2: 0.27711802 | CR2: 0 | CS2: 0.21091464 | CT2: 0 | CU2: 0.15077497 | CV2: 0 | CW2: 0.30983108 | CX2: 0 | CY2: 0.08399683 | CZ2: 0 | DA2: 0.39434461 | DB2: 0 | DC2: 0.02606057 | DD2: 0 | DE2: 0.12118296 | DF2: 0 | DG2: 0.17513187 | DH2: 0 | DI2: 0.14440346 | DJ2: 0 | DK2: 0.16956532 | DL2: 0 | DM2: 0.17763583 | DN2: 0 | DO2: 0.027609764 | DP2: 0 | DQ2: 0.19518546 | DR2: 0 | DS2: 0.23832237
A3: 3 | B3: EQUITY_TOTAL_RETURN | C3: =B3&A3 -> EQUITY_TOTAL_RETURN3 | D3: 0 | E3: -0.088145823 | F3: 0 | G3: 0.064219104 | H3: 0 | I3: 0.076338476 | J3: 0 | K3: 0.24067549 | L3: 0 | M3: -0.15084164 | N3: 0 | O3: 0.03215087 | P3: 0 | Q3: 0.11937723 | R3: 0 | S3: -0.13086565 | T3: 0 | U3: -0.059209398 | V3: 0 | W3: 0.10941713 | X3: 0 | Y3: -0.0012472491 | Z3: 0 | AA3: 0.014546398 | AB3: 0 | AC3: 0.16447239 | AD3: 0 | AE3: -0.012345599 | AF3: 0 | AG3: 0.095290362 | AH3: 0 | AI3: -0.051027104 | AJ3: 0 | AK3: 0.021649377 | AL3: 0 | AM3: -0.086930637 | AN3: 0 | AO3: -0.08558167 | AP3: 0 | AQ3: -0.015314691 | AR3: 0 | AS3: 0.36627777 | AT3: 0 | AU3: -0.32640286 | AV3: 0 | AW3: 0.24913621 | AX3: 0 | AY3: -0.082211276 | AZ3: 0 | BA3: -0.15079475 | BB3: 0 | BC3: 0.26336881 | BD3: 0 | BE3: -0.054941725 | BF3: 0 | BG3: 0.044050206 | BH3: 0 | BI3: -0.10905538 | BJ3: 0 | BK3: -0.042015818 | BL3: 0 | BM3: -0.058701955 | BN3: 0 | BO3: 0.19981499 | BP3: 0 | BQ3: -0.1241562 | BR3: 0 | BS3: -0.20886697 | BT3: 0 | BU3: -0.00055502382 | BV3: 0 | BW3: 0.012007398 | BX3: 0 | BY3: 0.038599939 | BZ3: 0 | CA3: 0.094147368 | CB3: 0 | CC3: -0.046614722 | CD3: 0 | CE3: 0.032532766 | CF3: 0 | CG3: 0.067794067 | CH3: 0 | CI3: 0.15397943 | CJ3: 0 | CK3: 0.067709005 | CL3: 0 | CM3: 0.096935528 | CN3: 0 | CO3: 0.055435247 | CP3: 0 | CQ3: 0.20736065 | CR3: 0 | CS3: 0.16170544 | CT3: 0 | CU3: 0.039542485 | CV3: 0 | CW3: 0.063339463 | CX3: 0 | CY3: -0.02611513 | CZ3: 0 | DA3: -0.088837612 | DB3: 0 | DC3: -0.0099461269 | DD3: 0 | DE3: 0.37905106 | DF3: 0 | DG3: 0.1925357 | DH3: 0 | DI3: 0.21954441 | DJ3: 0 | DK3: -0.0098963497 | DL3: 0 | DM3: 0.14628894 | DN3: 0 | DO3: 0.18220448 | DP3: 0 | DQ3: -0.16660827 | DR3: 0 | DS3: -0.027799844
A4: 4 | B4: EQUITY_TOTAL_RETURN | C4: =B4&A4 -> EQUITY_TOTAL_RETURN4 | D4: 0 | E4: 0.020197603 | F4: 0 | G4: 0.06886834 | H4: 0 | I4: -0.052008561 | J4: 0 | K4: 0.03697366 | L4: 0 | M4: 0.23607045 | N4: 0 | O4: -0.09163767 | P4: 0 | Q4: -0.0857962 | R4: 0 | S4: -0.002667475 | T4: 0 | U4: 0.073093903 | V4: 0 | W4: 0.15240952 | X4: 0 | Y4: -0.062497537 | Z4: 0 | AA4: -0.042622778 | AB4: 0 | AC4: -0.16580893 | AD4: 0 | AE4: 0.2031781 | AF4: 0 | AG4: -0.042481779 | AH4: 0 | AI4: 0.019760666 | AJ4: 0 | AK4: 0.14769583 | AL4: 0 | AM4: 0.26143704 | AN4: 0 | AO4: 0.13582179 | AP4: 0 | AQ4: 0.040702602 | AR4: 0 | AS4: -0.14238974 | AT4: 0 | AU4: 0.33845677 | AV4: 0 | AW4: 0.04891692 | AX4: 0 | AY4: 0.15528685 | AZ4: 0 | BA4: 0.37535529 | BB4: 0 | BC4: 0.13036969 | BD4: 0 | BE4: 0.18048554 | BF4: 0 | BG4: 0.14551231 | BH4: 0 | BI4: 0.16122615 | BJ4: 0 | BK4: 0.078692963 | BL4: 0 | BM4: 0.080249742 | BN4: 0 | BO4: 0.19352388 | BP4: 0 | BQ4: 0.14807047 | BR4: 0 | BS4: 0.14031542 | BT4: 0 | BU4: 0.12902149 | BV4: 0 | BW4: 0.16511595 | BX4: 0 | BY4: 0.14339708 | BZ4: 0 | CA4: 0.11581078 | CB4: 0 | CC4: 0.40579847 | CD4: 0 | CE4: -0.078959147 | CF4: 0 | CG4: 0.26118832 | CH4: 0 | CI4: -0.12991124 | CJ4: 0 | CK4: 0.0040152206 | CL4: 0 | CM4: -0.045264304 | CN4: 0 | CO4: 0.06300243 | CP4: 0 | CQ4: 0.33404678 | CR4: 0 | CS4: 0.044822665 | CT4: 0 | CU4: 0.34054475 | CV4: 0 | CW4: 0.076108625 | CX4: 0 | CY4: 0.063569908 | CZ4: 0 | DA4: 0.015313078 | DB4: 0 | DC4: 0.13482988 | DD4: 0 | DE4: 0.27860462 | DF4: 0 | DG4: 0.0094094042 | DH4: 0 | DI4: 0.050626124 | DJ4: 0 | DK4: -0.043236281 | DL4: 0 | DM4: 0.05784542 | DN4: 0 | DO4: -0.0069193172 | DP4: 0 | DQ4: 0.0098128766 | DR4: 0 | DS4: -0.069992241
A5: 5 | B5: EQUITY_TOTAL_RETURN | C5: =B5&A5 -> EQUITY_TOTAL_RETURN5 | D5: 0 | E5: 0.19974498 | F5: 0 | G5: -0.081086262 | H5: 0 | I5: -0.31743812 | J5: 0 | K5: -0.012672388 | L5: 0 | M5: -0.16824228 | N5: 0 | O5: -0.1551012 | P5: 0 | Q5: 0.16604643 | R5: 0 | S5: 0.12833201 | T5: 0 | U5: -0.10297058 | V5: 0 | W5: 0.0084203739 | X5: 0 | Y5: -0.041112116 | Z5: 0 | AA5: 0.22112494 | AB5: 0 | AC5: 0.25154972 | AD5: 0 | AE5: 0.049215116 | AF5: 0 | AG5: 0.088421071 | AH5: 0 | AI5: 0.13385769 | AJ5: 0 | AK5: 0.31309144 | AL5: 0 | AM5: -0.046567697 | AN5: 0 | AO5: 0.17795313 | AP5: 0 | AQ5: 0.10397673 | AR5: 0 | AS5: -0.0067595067 | AT5: 0 | AU5: 0.039273667 | AV5: 0 | AW5: -0.041276261 | AX5: 0 | AY5: 0.10905205 | AZ5: 0 | BA5: 0.28877442 | BB5: 0 | BC5: 0.17121397 | BD5: 0 | BE5: 0.26330758 | BF5: 0 | BG5: -0.017707771 | BH5: 0 | BI5: 0.24412356 | BJ5: 0 | BK5: 0.10626541 | BL5: 0 | BM5: 0.28718697 | BN5: 0 | BO5: 0.25741546 | BP5: 0 | BQ5: 0.16058387 | BR5: 0 | BS5: 0.18197056 | BT5: 0 | BU5: 0.089619624 | BV5: 0 | BW5: 0.37414778 | BX5: 0 | BY5: 0.23045048 | BZ5: 0 | CA5: 0.0047414432 | CB5: 0 | CC5: 0.32627202 | CD5: 0 | CE5: 0.026741088 | CF5: 0 | CG5: 0.27359873 | CH5: 0 | CI5: 0.49486932 | CJ5: 0 | CK5: -0.014859044 | CL5: 0 | CM5: 0.44686921 | CN5: 0 | CO5: 0.23825788 | CP5: 0 | CQ5: 0.33473436 | CR5: 0 | CS5: 0.38504893 | CT5: 0 | CU5: 0.19676144 | CV5: 0 | CW5: 0.35127897 | CX5: 0 | CY5: 0.42478302 | CZ5: 0 | DA5: 0.33191636 | DB5: 0 | DC5: 0.31615399 | DD5: 0 | DE5: 0.0799511 | DF5: 0 | DG5: -0.059813717 | DH5: 0 | DI5: -0.071330605 | DJ5: 0 | DK5: 0.26306961 | DL5: 0 | DM5: 0.039113964 | DN5: 0 | DO5: 0.23140912 | DP5: 0 | DQ5: 0.2760549 | DR5: 0 | DS5: 0.29342653
A6: 6 | B6: EQUITY_TOTAL_RETURN | C6: =B6&A6 -> EQUITY_TOTAL_RETURN6 | D6: 0 | E6: -0.10376977 | F6: 0 | G6: 0.005912136 | H6: 0 | I6: -0.15591563 | J6: 0 | K6: 0.18827198 | L6: 0 | M6: -0.021574843 | N6: 0 | O6: -0.10135446 | P6: 0 | Q6: -0.011415629 | R6: 0 | S6: -0.11579143 | T6: 0 | U6: 0.077551302 | V6: 0 | W6: 0.27692952 | X6: 0 | Y6: -0.019048053 | Z6: 0 | AA6: -0.11052199 | AB6: 0 | AC6: -0.016433155 | AD6: 0 | AE6: -0.02818926 | AF6: 0 | AG6: 0.058437971 | AH6: 0 | AI6: 0.039400736 | AJ6: 0 | AK6: 0.086034981 | AL6: 0 | AM6: 0.10427269 | AN6: 0 | AO6: -0.080616721 | AP6: 0 | AQ6: -0.029000671 | AR6: 0 | AS6: 0.10798992 | AT6: 0 | AU6: -0.10296651 | AV6: 0 | AW6: 0.086903911 | AX6: 0 | AY6: 0.075271916 | AZ6: 0 | BA6: 0.068597507 | BB6: 0 | BC6: -0.083101466 | BD6: 0 | BE6: 8.2150855e-06 | BF6: 0 | BG6: 0.19371913 | BH6: 0 | BI6: 0.2442799 | BJ6: 0 | BK6: 0.27093069 | BL6: 0 | BM6: 0.087667286 | BN6: 0 | BO6: 0.27518268 | BP6: 0 | BQ6: 0.1549443 | BR6: 0 | BS6: 0.35703538 | BT6: 0 | BU6: -0.10587165 | BV6: 0 | BW6: -0.054460775 | BX6: 0 | BY6: 0.057062491 | BZ6: 0 | CA6: 0.078407262 | CB6: 0 | CC6: 0.13018839 | CD6: 0 | CE6: 0.25392176 | CF6: 0 | CG6: 0.11910804 | CH6: 0 | CI6: 0.16368046 | CJ6: 0 | CK6: -0.00038950748 | CL6: 0 | CM6: -0.089556299 | CN6: 0 | CO6: 0.018478605 | CP6: 0 | CQ6: 0.089409649 | CR6: 0 | CS6: 0.074144625 | CT6: 0 | CU6: 0.33512696 | CV6: 0 | CW6: 0.11966258 | CX6: 0 | CY6: -0.014041392 | CZ6: 0 | DA6: 0.11273371 | DB6: 0 | DC6: 0.15983527 | DD6: 0 | DE6: 0.030121432 | DF6: 0 | DG6: 0.094318321 | DH6: 0 | DI6: 0.31332405 | DJ6: 0 | DK6: 0.0048668306 | DL6: 0 | DM6: 0.047958911 | DN6: 0 | DO6: 0.15015765 | DP6: 0 | DQ6: 0.10427161 | DR6: 0 | DS6: 0.07788365
A7: 7 | B7: EQUITY_TOTAL_RETURN | C7: =B7&A7 -> EQUITY_TOTAL_RETURN7 | D7: 0 | E7: 0.061728487 | F7: 0 | G7: 0.08335584 | H7: 0 | I7: -0.051476314 | J7: 0 | K7: 0.26646453 | L7: 0 | M7: -0.21022945 | N7: 0 | O7: -0.036099911 | P7: 0 | Q7: -0.089574374 | R7: 0 | S7: 0.03208963 | T7: 0 | U7: 0.13447586 | V7: 0 | W7: 0.04370606 | X7: 0 | Y7: 0.01600819 | Z7: 0 | AA7: -0.16839308 | AB7: 0 | AC7: -0.23701885 | AD7: 0 | AE7: 0.059717377 | AF7: 0 | AG7: -0.25979913 | AH7: 0 | AI7: 0.05953038 | AJ7: 0 | AK7: -0.044329599 | AL7: 0 | AM7: 0.00088039159 | AN7: 0 | AO7: -0.019775703 | AP7: 0 | AQ7: 0.029046452 | AR7: 0 | AS7: -0.10082774 | AT7: 0 | AU7: 0.23267017 | AV7: 0 | AW7: 0.17782943 | AX7: 0 | AY7: -0.07827495 | AZ7: 0 | BA7: -0.0082380305 | BB7: 0 | BC7: -0.058794707 | BD7: 0 | BE7: 0.14009974 | BF7: 0 | BG7: -0.011882017 | BH7: 0 | BI7: 0.14729808 | BJ7: 0 | BK7: 0.13860501 | BL7: 0 | BM7: 0.21618541 | BN7: 0 | BO7: -0.19964338 | BP7: 0 | BQ7: -0.140007 | BR7: 0 | BS7: 0.072087084 | BT7: 0 | BU7: 0.093729522 | BV7: 0 | BW7: -0.18740783 | BX7: 0 | BY7: -0.096863642 | BZ7: 0 | CA7: -0.028669858 | CB7: 0 | CC7: -0.068515666 | CD7: 0 | CE7: -0.03774249 | CF7: 0 | CG7: -0.063384426 | CH7: 0 | CI7: -0.17843487 | CJ7: 0 | CK7: 0.10977424 | CL7: 0 | CM7: 0.0072504695 | CN7: 0 | CO7: -0.0019200516 | CP7: 0 | CQ7: -0.094247642 | CR7: 0 | CS7: -0.042540158 | CT7: 0 | CU7: 0.011547375 | CV7: 0 | CW7: -0.11093329 | CX7: 0 | CY7: 0.074911187 | CZ7: 0 | DA7: -0.15989393 | DB7: 0 | DC7: 0.1470529 | DD7: 0 | DE7: 0.05125909 | DF7: 0 | DG7: 0.0092802667 | DH7: 0 | DI7: 0.035737869 | DJ7: 0 | DK7: 0.016133474 | DL7: 0 | DM7: 0.011153358 | DN7: 0 | DO7: 0.16454207 | DP7: 0 | DQ7: 0.0009612285 | DR7: 0 | DS7: -0.035559004
A8: 8 | B8: EQUITY_TOTAL_RETURN | C8: =B8&A8 -> EQUITY_TOTAL_RETURN8 | D8: 0 | E8: 0.076918339 | F8: 0 | G8: -0.079591734 | H8: 0 | I8: -0.083142887 | J8: 0 | K8: -0.20279636 | L8: 0 | M8: 0.17297949 | N8: 0 | O8: -0.031081338 | P8: 0 | Q8: -0.10292153 | R8: 0 | S8: 0.16902031 | T8: 0 | U8: 0.08324623 | V8: 0 | W8: -0.081614341 | X8: 0 | Y8: 0.029105901 | Z8: 0 | AA8: 0.012900376 | AB8: 0 | AC8: -0.11885363 | AD8: 0 | AE8: 0.046740768 | AF8: 0 | AG8: -0.059028102 | AH8: 0 | AI8: 0.086353807 | AJ8: 0 | AK8: 0.0075296113 | AL8: 0 | AM8: 0.12754663 | AN8: 0 | AO8: 0.13387057 | AP8: 0 | AQ8: 0.064061842 | AR8: 0 | AS8: -0.22959275 | AT8: 0 | AU8: 0.57233151 | AV8: 0 | AW8: -0.14397145 | AX8: 0 | AY8: 0.17050397 | AZ8: 0 | BA8: 0.2659869 | BB8: 0 | BC8: -0.14195937 | BD8: 0 | BE8: 0.15239321 | BF8: 0 | BG8: 0.050817946 | BH8: 0 | BI8: 0.23527064 | BJ8: 0 | BK8: 0.15350472 | BL8: 0 | BM8: 0.17404723 | BN8: 0 | BO8: -0.07620319 | BP8: 0 | BQ8: 0.27536579 | BR8: 0 | BS8: 0.4049863 | BT8: 0 | BU8: 0.12195673 | BV8: 0 | BW8: 0.11462299 | BX8: 0 | BY8: 0.086887612 | BZ8: 0 | CA8: 0.034754225 | CB8: 0 | CC8: 0.19081869 | CD8: 0 | CE8: 0.10508276 | CF8: 0 | CG8: 0.071070306 | CH8: 0 | CI8: -0.0080053263 | CJ8: 0 | CK8: 0.077955806 | CL8: 0 | CM8: 0.046885201 | CN8: 0 | CO8: 0.08943381 | CP8: 0 | CQ8: -0.039990356 | CR8: 0 | CS8: -0.00099408466 | CT8: 0 | CU8: 0.12638861 | CV8: 0 | CW8: 0.096790005 | CX8: 0 | CY8: 0.20137744 | CZ8: 0 | DA8: 0.29139514 | DB8: 0 | DC8: 0.19260033 | DD8: 0 | DE8: -0.14497172 | DF8: 0 | DG8: -0.0089954048 | DH8: 0 | DI8: -0.025718053 | DJ8: 0 | DK8: 0.19726117 | DL8: 0 | DM8: 0.041908764 | DN8: 0 | DO8: 0.013472964 | DP8: 0 | DQ8: 0.43549278 | DR8: 0 | DS8: 0.23794929
A9: 9 | B9: EQUITY_TOTAL_RETURN | C9: =B9&A9 -> EQUITY_TOTAL_RETURN9 | D9: 0 | E9: -0.03688777 | F9: 0 | G9: -0.082798974 | H9: 0 | I9: 0.040126084 | J9: 0 | K9: -0.045905526 | L9: 0 | M9: -0.19390149 | N9: 0 | O9: 0.1015734 | P9: 0 | Q9: 0.10032838 | R9: 0 | S9: 0.016536296 | T9: 0 | U9: -0.053391461 | V9: 0 | W9: -0.11345332 | X9: 0 | Y9: 0.095906006 | Z9: 0 | AA9: 0.073650621 | AB9: 0 | AC9: 0.23498075 | AD9: 0 | AE9: -0.1441501 | AF9: 0 | AG9: 0.081872231 | AH9: 0 | AI9: 0.010777409 | AJ9: 0 | AK9: -0.10395394 | AL9: 0 | AM9: -0.18301052 | AN9: 0 | AO9: -0.08525255 | AP9: 0 | AQ9: 0.0061214319 | AR9: 0 | AS9: 0.22446297 | AT9: 0 | AU9: -0.2077769 | AV9: 0 | AW9: 0.018083014 | AX9: 0 | AY9: -0.069350238 | AZ9: 0 | BA9: -0.21749331 | BB9: 0 | BC9: -0.039865628 | BD9: 0 | BE9: -0.080790462 | BF9: 0 | BG9: -0.049464578 | BH9: 0 | BI9: -0.056641714 | BJ9: 0 | BK9: 0.02325258 | BL9: 0 | BM9: 0.01952137 | BN9: 0 | BO9: -0.068591103 | BP9: 0 | BQ9: -0.028195063 | BR9: 0 | BS9: -0.021108028 | BT9: 0 | BU9: -0.0060646935 | BV9: 0 | BW9: -0.032095439 | BX9: 0 | BY9: -0.011918911 | BZ9: 0 | CA9: 0.013952528 | CB9: 0 | CC9: -0.19278111 | CD9: 0 | CE9: 0.23519599 | CF9: 0 | CG9: -0.097432949 | CH9: 0 | CI9: 0.31741009 | CJ9: 0 | CK9: 0.14203677 | CL9: 0 | CM9: 0.20358054 | CN9: 0 | CO9: 0.088448865 | CP9: 0 | CQ9: -0.13412098 | CR9: 0 | CS9: 0.10806907 | CT9: 0 | CU9: -0.13108812 | CV9: 0 | CW9: 0.083603899 | CX9: 0 | CY9: 0.097453765 | CZ9: 0 | DA9: 0.15697188 | DB9: 0 | DC9: 0.038838652 | DD9: 0 | DE9: -0.076314966 | DF9: 0 | DG9: 0.16974062 | DH9: 0 | DI9: 0.13192649 | DJ9: 0 | DK9: 0.23963833 | DL9: 0 | DM9: 0.13035255 | DN9: 0 | DO9: 0.20822251 | DP9: 0 | DQ9: 0.18191173 | DR9: 0 | DS9: 0.28957552
A10: 10 | B10: EQUITY_TOTAL_RETURN | C10: =B10&A10 -> EQUITY_TOTAL_RETURN10 | D10: 0 | E10: -0.18256564 | F10: 0 | G10: 0.070399834 | H10: 0 | I10: 0.44142503 | J10: 0 | K10: 0.0017892965 | L10: 0 | M10: 0.19718805 | N10: 0 | O10: 0.19062456 | P10: 0 | Q10: -0.13692579 | R10: 0 | S10: -0.10136496 | T10: 0 | U10: 0.13784138 | V10: 0 | W10: 0.017423594 | X10: 0 | Y10: 0.071447568 | Z10: 0 | AA10: -0.15567354 | AB10: 0 | AC10: -0.17527456 | AD10: 0 | AE10: -0.01814679 | AF10: 0 | AG10: -0.048922741 | AH10: 0 | AI10: -0.092221296 | AJ10: 0 | AK10: -0.21525938 | AL10: 0 | AM10: 0.087352092 | AN10: 0 | AO10: -0.11876179 | AP10: 0 | AQ10: -0.052757636 | AR10: 0 | AS10: 0.0629038 | AT10: 0 | AU10: 0.020867257 | AV10: 0 | AW10: 0.11516553 | AX10: 0 | AY10: -0.033149879 | AZ10: 0 | BA10: -0.16433016 | BB10: 0 | BC10: -0.076240221 | BD10: 0 | BE10: -0.14248177 | BF10: 0 | BG10: 0.11176595 | BH10: 0 | BI10: -0.11422413 | BJ10: 0 | BK10: -0.0028076489 | BL10: 0 | BM10: -0.13954493 | BN10: 0 | BO10: -0.11854748 | BP10: 0 | BQ10: -0.041218463 | BR10: 0 | BS10: -0.055593821 | BT10: 0 | BU10: 0.032182713 | BV10: 0 | BW10: -0.17965817 | BX10: 0 | BY10: -0.082674659 | BZ10: 0 | CA10: 0.12636789 | CB10: 0 | CC10: -0.1445577 | CD10: 0 | CE10: 0.11251565 | CF10: 0 | CG10: -0.10750173 | CH10: 0 | CI10: -0.23399973 | CJ10: 0 | CK10: 0.16235194 | CL10: 0 | CM10: -0.20356174 | CN10: 0 | CO10: -0.069129317 | CP10: 0 | CQ10: -0.13611795 | CR10: 0 | CS10: -0.16687548 | CT10: 0 | CU10: -0.031580594 | CV10: 0 | CW10: -0.13454032 | CX10: 0 | CY10: -0.17900507 | CZ10: 0 | DA10: -0.11935894 | DB10: 0 | DC10: -0.10630694 | DD10: 0 | DE10: 0.093209524 | DF10: 0 | DG10: 0.25409069 | DH10: 0 | DI10: 0.27190132 | DJ10: 0 | DK10: -0.060204676 | DL10: 0 | DM10: 0.14668686 | DN10: 0 | DO10: -0.030329249 | DP10: 0 | DQ10: -0.058079294 | DR10: 0 | DS10: -0.070138882
D11: =AVERAGE(D1:D10) -> 0 | E11: =AVERAGE(E1:E10) -> -0.0032787096 | F11: =AVERAGE(F1:F10) -> 0 | G11: =AVERAGE(G1:G10) -> -0.0067752739 | H11: =AVERAGE(H1:H10) -> 0 | I11: =AVERAGE(I1:I10) -> 0.0098279206 | J11: =AVERAGE(J1:J10) -> 0 | K11: =AVERAGE(K1:K10) -> 0.0090025447 | ... DS11: =AVERAGE(DS1:DS10) -> 0.10446072
B15: 0
B16: -0.0032787096
B17: -0.0067752739
B18: 0.0098279206
B19: 0.0090025447
B20: 0.014124245
B21: 0.0063448313
B22: 0.0075804706
B23: 0.012704498
B24: 0.014016116
B25: 0.01962919
B26: 0.014992378
... B75: 0.10446072

Sheet Property
A1: 1 | B1: PROP_TOTAL_RETURN | C1: =B1&A1 -> PROP_TOTAL_RETURN1 | D1: 0 | E1: 0.097470561 | F1: 0 | G1: -0.02372003 | H1: 0 | I1: 0.16418952 | J1: 0 | K1: -0.16536528 | L1: 0 | M1: 0.015408088 | N1: 0 | O1: 0.11625707 | P1: 0 | Q1: 0.01594496 | R1: 0 | S1: 0.14632101 | T1: 0 | U1: -0.052905635 | V1: 0 | W1: -0.19923664 | X1: 0 | Y1: 0.048497484 | Z1: 0 | AA1: 0.1552705 | AB1: 0 | AC1: 0.047737946 | AD1: 0 | AE1: 0.065332343 | AF1: 0 | AG1: -0.02110904 | AH1: 0 | AI1: -0.0076742549 | AJ1: 0 | AK1: -0.050856179 | AL1: 0 | AM1: -0.065785363 | AN1: 0 | AO1: 0.13182064 | AP1: 0 | AQ1: 0.079979174 | AR1: 0 | AS1: -0.046153584 | AT1: 0 | AU1: 0.18522277 | AV1: 0 | AW1: -0.015439381 | AX1: 0 | AY1: -5.4508926e-05 | AZ1: 0 | BA1: 0.0077239515 | BB1: 0 | BC1: 0.18321327 | BD1: 0 | BE1: 0.092388678 | BF1: 0 | BG1: -0.085057584 | BH1: 0 | BI1: -0.11745406 | BJ1: 0 | BK1: -0.13237931 | BL1: 0 | BM1: 0.014661388 | BN1: 0 | BO1: -0.12933206 | BP1: 0 | BQ1: -0.034855946 | BR1: 0 | BS1: -0.17566877 | BT1: 0 | BU1: 0.24955966 | BV1: 0 | BW1: 0.19057741 | BX1: 0 | BY1: 0.068714596 | BZ1: 0 | CA1: 0.045790505 | CB1: 0 | CC1: 0.0067043084 | CD1: 0 | CE1: -0.089630241 | CF1: 0 | CG1: 0.020079335 | CH1: 0 | CI1: -0.012342303 | CJ1: 0 | CK1: 0.14587745 | CL1: 0 | CM1: 0.26574011 | CN1: 0 | CO1: 0.13509218 | CP1: 0 | CQ1: 0.063862256 | CR1: 0 | CS1: 0.080130479 | CT1: 0 | CU1: -0.12808379 | CV1: 0 | CW1: 0.042629246 | CX1: 0 | CY1: 0.18137347 | CZ1: 0 | DA1: 0.053973943 | DB1: 0 | DC1: 0.017053958 | DD1: 0 | DE1: 0.14682533 | DF1: 0 | DG1: 0.081978027 | DH1: 0 | DI1: -0.094582869 | DJ1: 0 | DK1: 0.18298138 | DL1: 0 | DM1: 0.13718464 | DN1: 0 | DO1: 0.039815084 | DP1: 0 | DQ1: 0.084854718 | DR1: 0 | DS1: 0.11093984
A2: 2 | B2: PROP_TOTAL_RETURN | C2: =B2&A2 -> PROP_TOTAL_RETURN2 | D2: 0 | E2: -0.077478072 | F2: 0 | G2: -0.093310993 | H2: 0 | I2: 0.03618161 | J2: 0 | K2: -0.21740995 | L2: 0 | M2: 0.26438606 | N2: 0 | O2: 0.038116992 | P2: 0 | Q2: 0.10074123 | R2: 0 | S2: -0.014564744 | T2: 0 | U2: -0.097570443 | V2: 0 | W2: -0.017710005 | X2: 0 | Y2: 0.012863587 | Z2: 0 | AA2: 0.23567908 | AB2: 0 | AC2: 0.34514497 | AD2: 0 | AE2: -0.023447399 | AF2: 0 | AG2: 0.39009195 | AH2: 0 | AI2: -0.032904888 | AJ2: 0 | AK2: 0.078659419 | AL2: 0 | AM2: 0.031646378 | AN2: 0 | AO2: 0.05747705 | AP2: 0 | AQ2: 0.015377291 | AR2: 0 | AS2: 0.16810686 | AT2: 0 | AU2: -0.14325305 | AV2: 0 | AW2: -0.098859287 | AX2: 0 | AY2: 0.16474842 | AZ2: 0 | BA2: 0.083398696 | BB2: 0 | BC2: 0.1475373 | BD2: 0 | BE2: -0.043346934 | BF2: 0 | BG2: 0.10899999 | BH2: 0 | BI2: -0.044595794 | BJ2: 0 | BK2: -0.032446176 | BL2: 0 | BM2: -0.092065666 | BN2: 0 | BO2: 0.3910028 | BP2: 0 | BQ2: 0.29615946 | BR2: 0 | BS2: 0.040230336 | BT2: 0 | BU2: 0.026577086 | BV2: 0 | BW2: 0.38404627 | BX2: 0 | BY2: 0.24679483 | BZ2: 0 | CA2: 0.16608356 | CB2: 0 | CC2: 0.21658135 | CD2: 0 | CE2: 0.18730197 | CF2: 0 | CG2: 0.22263449 | CH2: 0 | CI2: 0.3903592 | CJ2: 0 | CK2: 0.033983468 | CL2: 0 | CM2: 0.14253503 | CN2: 0 | CO2: 0.15850695 | CP2: 0 | CQ2: 0.27711802 | CR2: 0 | CS2: 0.21091464 | CT2: 0 | CU2: 0.15077497 | CV2: 0 | CW2: 0.30983108 | CX2: 0 | CY2: 0.08399683 | CZ2: 0 | DA2: 0.39434461 | DB2: 0 | DC2: 0.02606057 | DD2: 0 | DE2: 0.12118296 | DF2: 0 | DG2: 0.17513187 | DH2: 0 | DI2: 0.14440346 | DJ2: 0 | DK2: 0.16956532 | DL2: 0 | DM2: 0.17763583 | DN2: 0 | DO2: 0.027609764 | DP2: 0 | DQ2: 0.19518546 | DR2: 0 | DS2: 0.23832237
A3: 3 | B3: PROP_TOTAL_RETURN | C3: =B3&A3 -> PROP_TOTAL_RETURN3 | D3: 0 | E3: -0.088145823 | F3: 0 | G3: 0.064219104 | H3: 0 | I3: 0.076338476 | J3: 0 | K3: 0.24067549 | L3: 0 | M3: -0.15084164 | N3: 0 | O3: 0.03215087 | P3: 0 | Q3: 0.11937723 | R3: 0 | S3: -0.13086565 | T3: 0 | U3: -0.059209398 | V3: 0 | W3: 0.10941713 | X3: 0 | Y3: -0.0012472491 | Z3: 0 | AA3: 0.014546398 | AB3: 0 | AC3: 0.16447239 | AD3: 0 | AE3: -0.012345599 | AF3: 0 | AG3: 0.095290362 | AH3: 0 | AI3: -0.051027104 | AJ3: 0 | AK3: 0.021649377 | AL3: 0 | AM3: -0.086930637 | AN3: 0 | AO3: -0.08558167 | AP3: 0 | AQ3: -0.015314691 | AR3: 0 | AS3: 0.36627777 | AT3: 0 | AU3: -0.32640286 | AV3: 0 | AW3: 0.24913621 | AX3: 0 | AY3: -0.082211276 | AZ3: 0 | BA3: -0.15079475 | BB3: 0 | BC3: 0.26336881 | BD3: 0 | BE3: -0.054941725 | BF3: 0 | BG3: 0.044050206 | BH3: 0 | BI3: -0.10905538 | BJ3: 0 | BK3: -0.042015818 | BL3: 0 | BM3: -0.058701955 | BN3: 0 | BO3: 0.19981499 | BP3: 0 | BQ3: -0.1241562 | BR3: 0 | BS3: -0.20886697 | BT3: 0 | BU3: -0.00055502382 | BV3: 0 | BW3: 0.012007398 | BX3: 0 | BY3: 0.038599939 | BZ3: 0 | CA3: 0.094147368 | CB3: 0 | CC3: -0.046614722 | CD3: 0 | CE3: 0.032532766 | CF3: 0 | CG3: 0.067794067 | CH3: 0 | CI3: 0.15397943 | CJ3: 0 | CK3: 0.067709005 | CL3: 0 | CM3: 0.096935528 | CN3: 0 | CO3: 0.055435247 | CP3: 0 | CQ3: 0.20736065 | CR3: 0 | CS3: 0.16170544 | CT3: 0 | CU3: 0.039542485 | CV3: 0 | CW3: 0.063339463 | CX3: 0 | CY3: -0.02611513 | CZ3: 0 | DA3: -0.088837612 | DB3: 0 | DC3: -0.0099461269 | DD3: 0 | DE3: 0.37905106 | DF3: 0 | DG3: 0.1925357 | DH3: 0 | DI3: 0.21954441 | DJ3: 0 | DK3: -0.0098963497 | DL3: 0 | DM3: 0.14628894 | DN3: 0 | DO3: 0.18220448 | DP3: 0 | DQ3: -0.16660827 | DR3: 0 | DS3: -0.027799844
A4: 4 | B4: PROP_TOTAL_RETURN | C4: =B4&A4 -> PROP_TOTAL_RETURN4 | D4: 0 | E4: 0.020197603 | F4: 0 | G4: 0.06886834 | H4: 0 | I4: -0.052008561 | J4: 0 | K4: 0.03697366 | L4: 0 | M4: 0.23607045 | N4: 0 | O4: -0.09163767 | P4: 0 | Q4: -0.0857962 | R4: 0 | S4: -0.002667475 | T4: 0 | U4: 0.073093903 | V4: 0 | W4: 0.15240952 | X4: 0 | Y4: -0.062497537 | Z4: 0 | AA4: -0.042622778 | AB4: 0 | AC4: -0.16580893 | AD4: 0 | AE4: 0.2031781 | AF4: 0 | AG4: -0.042481779 | AH4: 0 | AI4: 0.019760666 | AJ4: 0 | AK4: 0.14769583 | AL4: 0 | AM4: 0.26143704 | AN4: 0 | AO4: 0.13582179 | AP4: 0 | AQ4: 0.040702602 | AR4: 0 | AS4: -0.14238974 | AT4: 0 | AU4: 0.33845677 | AV4: 0 | AW4: 0.04891692 | AX4: 0 | AY4: 0.15528685 | AZ4: 0 | BA4: 0.37535529 | BB4: 0 | BC4: 0.13036969 | BD4: 0 | BE4: 0.18048554 | BF4: 0 | BG4: 0.14551231 | BH4: 0 | BI4: 0.16122615 | BJ4: 0 | BK4: 0.078692963 | BL4: 0 | BM4: 0.080249742 | BN4: 0 | BO4: 0.19352388 | BP4: 0 | BQ4: 0.14807047 | BR4: 0 | BS4: 0.14031542 | BT4: 0 | BU4: 0.12902149 | BV4: 0 | BW4: 0.16511595 | BX4: 0 | BY4: 0.14339708 | BZ4: 0 | CA4: 0.11581078 | CB4: 0 | CC4: 0.40579847 | CD4: 0 | CE4: -0.078959147 | CF4: 0 | CG4: 0.26118832 | CH4: 0 | CI4: -0.12991124 | CJ4: 0 | CK4: 0.0040152206 | CL4: 0 | CM4: -0.045264304 | CN4: 0 | CO4: 0.06300243 | CP4: 0 | CQ4: 0.33404678 | CR4: 0 | CS4: 0.044822665 | CT4: 0 | CU4: 0.34054475 | CV4: 0 | CW4: 0.076108625 | CX4: 0 | CY4: 0.063569908 | CZ4: 0 | DA4: 0.015313078 | DB4: 0 | DC4: 0.13482988 | DD4: 0 | DE4: 0.27860462 | DF4: 0 | DG4: 0.0094094042 | DH4: 0 | DI4: 0.050626124 | DJ4: 0 | DK4: -0.043236281 | DL4: 0 | DM4: 0.05784542 | DN4: 0 | DO4: -0.0069193172 | DP4: 0 | DQ4: 0.0098128766 | DR4: 0 | DS4: -0.069992241
A5: 5 | B5: PROP_TOTAL_RETURN | C5: =B5&A5 -> PROP_TOTAL_RETURN5 | D5: 0 | E5: 0.19974498 | F5: 0 | G5: -0.081086262 | H5: 0 | I5: -0.31743812 | J5: 0 | K5: -0.012672388 | L5: 0 | M5: -0.16824228 | N5: 0 | O5: -0.1551012 | P5: 0 | Q5: 0.16604643 | R5: 0 | S5: 0.12833201 | T5: 0 | U5: -0.10297058 | V5: 0 | W5: 0.0084203739 | X5: 0 | Y5: -0.041112116 | Z5: 0 | AA5: 0.22112494 | AB5: 0 | AC5: 0.25154972 | AD5: 0 | AE5: 0.049215116 | AF5: 0 | AG5: 0.088421071 | AH5: 0 | AI5: 0.13385769 | AJ5: 0 | AK5: 0.31309144 | AL5: 0 | AM5: -0.046567697 | AN5: 0 | AO5: 0.17795313 | AP5: 0 | AQ5: 0.10397673 | AR5: 0 | AS5: -0.0067595067 | AT5: 0 | AU5: 0.039273667 | AV5: 0 | AW5: -0.041276261 | AX5: 0 | AY5: 0.10905205 | AZ5: 0 | BA5: 0.28877442 | BB5: 0 | BC5: 0.17121397 | BD5: 0 | BE5: 0.26330758 | BF5: 0 | BG5: -0.017707771 | BH5: 0 | BI5: 0.24412356 | BJ5: 0 | BK5: 0.10626541 | BL5: 0 | BM5: 0.28718697 | BN5: 0 | BO5: 0.25741546 | BP5: 0 | BQ5: 0.16058387 | BR5: 0 | BS5: 0.18197056 | BT5: 0 | BU5: 0.089619624 | BV5: 0 | BW5: 0.37414778 | BX5: 0 | BY5: 0.23045048 | BZ5: 0 | CA5: 0.0047414432 | CB5: 0 | CC5: 0.32627202 | CD5: 0 | CE5: 0.026741088 | CF5: 0 | CG5: 0.27359873 | CH5: 0 | CI5: 0.49486932 | CJ5: 0 | CK5: -0.014859044 | CL5: 0 | CM5: 0.44686921 | CN5: 0 | CO5: 0.23825788 | CP5: 0 | CQ5: 0.33473436 | CR5: 0 | CS5: 0.38504893 | CT5: 0 | CU5: 0.19676144 | CV5: 0 | CW5: 0.35127897 | CX5: 0 | CY5: 0.42478302 | CZ5: 0 | DA5: 0.33191636 | DB5: 0 | DC5: 0.31615399 | DD5: 0 | DE5: 0.0799511 | DF5: 0 | DG5: -0.059813717 | DH5: 0 | DI5: -0.071330605 | DJ5: 0 | DK5: 0.26306961 | DL5: 0 | DM5: 0.039113964 | DN5: 0 | DO5: 0.23140912 | DP5: 0 | DQ5: 0.2760549 | DR5: 0 | DS5: 0.29342653
A6: 6 | B6: PROP_TOTAL_RETURN | C6: =B6&A6 -> PROP_TOTAL_RETURN6 | D6: 0 | E6: -0.10376977 | F6: 0 | G6: 0.005912136 | H6: 0 | I6: -0.15591563 | J6: 0 | K6: 0.18827198 | L6: 0 | M6: -0.021574843 | N6: 0 | O6: -0.10135446 | P6: 0 | Q6: -0.011415629 | R6: 0 | S6: -0.11579143 | T6: 0 | U6: 0.077551302 | V6: 0 | W6: 0.27692952 | X6: 0 | Y6: -0.019048053 | Z6: 0 | AA6: -0.11052199 | AB6: 0 | AC6: -0.016433155 | AD6: 0 | AE6: -0.02818926 | AF6: 0 | AG6: 0.058437971 | AH6: 0 | AI6: 0.039400736 | AJ6: 0 | AK6: 0.086034981 | AL6: 0 | AM6: 0.10427269 | AN6: 0 | AO6: -0.080616721 | AP6: 0 | AQ6: -0.029000671 | AR6: 0 | AS6: 0.10798992 | AT6: 0 | AU6: -0.10296651 | AV6: 0 | AW6: 0.086903911 | AX6: 0 | AY6: 0.075271916 | AZ6: 0 | BA6: 0.068597507 | BB6: 0 | BC6: -0.083101466 | BD6: 0 | BE6: 8.2150855e-06 | BF6: 0 | BG6: 0.19371913 | BH6: 0 | BI6: 0.2442799 | BJ6: 0 | BK6: 0.27093069 | BL6: 0 | BM6: 0.087667286 | BN6: 0 | BO6: 0.27518268 | BP6: 0 | BQ6: 0.1549443 | BR6: 0 | BS6: 0.35703538 | BT6: 0 | BU6: -0.10587165 | BV6: 0 | BW6: -0.054460775 | BX6: 0 | BY6: 0.057062491 | BZ6: 0 | CA6: 0.078407262 | CB6: 0 | CC6: 0.13018839 | CD6: 0 | CE6: 0.25392176 | CF6: 0 | CG6: 0.11910804 | CH6: 0 | CI6: 0.16368046 | CJ6: 0 | CK6: -0.00038950748 | CL6: 0 | CM6: -0.089556299 | CN6: 0 | CO6: 0.018478605 | CP6: 0 | CQ6: 0.089409649 | CR6: 0 | CS6: 0.074144625 | CT6: 0 | CU6: 0.33512696 | CV6: 0 | CW6: 0.11966258 | CX6: 0 | CY6: -0.014041392 | CZ6: 0 | DA6: 0.11273371 | DB6: 0 | DC6: 0.15983527 | DD6: 0 | DE6: 0.030121432 | DF6: 0 | DG6: 0.094318321 | DH6: 0 | DI6: 0.31332405 | DJ6: 0 | DK6: 0.0048668306 | DL6: 0 | DM6: 0.047958911 | DN6: 0 | DO6: 0.15015765 | DP6: 0 | DQ6: 0.10427161 | DR6: 0 | DS6: 0.07788365
A7: 7 | B7: PROP_TOTAL_RETURN | C7: =B7&A7 -> PROP_TOTAL_RETURN7 | D7: 0 | E7: 0.061728487 | F7: 0 | G7: 0.08335584 | H7: 0 | I7: -0.051476314 | J7: 0 | K7: 0.26646453 | L7: 0 | M7: -0.21022945 | N7: 0 | O7: -0.036099911 | P7: 0 | Q7: -0.089574374 | R7: 0 | S7: 0.03208963 | T7: 0 | U7: 0.13447586 | V7: 0 | W7: 0.04370606 | X7: 0 | Y7: 0.01600819 | Z7: 0 | AA7: -0.16839308 | AB7: 0 | AC7: -0.23701885 | AD7: 0 | AE7: 0.059717377 | AF7: 0 | AG7: -0.25979913 | AH7: 0 | AI7: 0.05953038 | AJ7: 0 | AK7: -0.044329599 | AL7: 0 | AM7: 0.00088039159 | AN7: 0 | AO7: -0.019775703 | AP7: 0 | AQ7: 0.029046452 | AR7: 0 | AS7: -0.10082774 | AT7: 0 | AU7: 0.23267017 | AV7: 0 | AW7: 0.17782943 | AX7: 0 | AY7: -0.07827495 | AZ7: 0 | BA7: -0.0082380305 | BB7: 0 | BC7: -0.058794707 | BD7: 0 | BE7: 0.14009974 | BF7: 0 | BG7: -0.011882017 | BH7: 0 | BI7: 0.14729808 | BJ7: 0 | BK7: 0.13860501 | BL7: 0 | BM7: 0.21618541 | BN7: 0 | BO7: -0.19964338 | BP7: 0 | BQ7: -0.140007 | BR7: 0 | BS7: 0.072087084 | BT7: 0 | BU7: 0.093729522 | BV7: 0 | BW7: -0.18740783 | BX7: 0 | BY7: -0.096863642 | BZ7: 0 | CA7: -0.028669858 | CB7: 0 | CC7: -0.068515666 | CD7: 0 | CE7: -0.03774249 | CF7: 0 | CG7: -0.063384426 | CH7: 0 | CI7: -0.17843487 | CJ7: 0 | CK7: 0.10977424 | CL7: 0 | CM7: 0.0072504695 | CN7: 0 | CO7: -0.0019200516 | CP7: 0 | CQ7: -0.094247642 | CR7: 0 | CS7: -0.042540158 | CT7: 0 | CU7: 0.011547375 | CV7: 0 | CW7: -0.11093329 | CX7: 0 | CY7: 0.074911187 | CZ7: 0 | DA7: -0.15989393 | DB7: 0 | DC7: 0.1470529 | DD7: 0 | DE7: 0.05125909 | DF7: 0 | DG7: 0.0092802667 | DH7: 0 | DI7: 0.035737869 | DJ7: 0 | DK7: 0.016133474 | DL7: 0 | DM7: 0.011153358 | DN7: 0 | DO7: 0.16454207 | DP7: 0 | DQ7: 0.0009612285 | DR7: 0 | DS7: -0.035559004
A8: 8 | B8: PROP_TOTAL_RETURN | C8: =B8&A8 -> PROP_TOTAL_RETURN8 | D8: 0 | E8: 0.076918339 | F8: 0 | G8: -0.079591734 | H8: 0 | I8: -0.083142887 | J8: 0 | K8: -0.20279636 | L8: 0 | M8: 0.17297949 | N8: 0 | O8: -0.031081338 | P8: 0 | Q8: -0.10292153 | R8: 0 | S8: 0.16902031 | T8: 0 | U8: 0.08324623 | V8: 0 | W8: -0.081614341 | X8: 0 | Y8: 0.029105901 | Z8: 0 | AA8: 0.012900376 | AB8: 0 | AC8: -0.11885363 | AD8: 0 | AE8: 0.046740768 | AF8: 0 | AG8: -0.059028102 | AH8: 0 | AI8: 0.086353807 | AJ8: 0 | AK8: 0.0075296113 | AL8: 0 | AM8: 0.12754663 | AN8: 0 | AO8: 0.13387057 | AP8: 0 | AQ8: 0.064061842 | AR8: 0 | AS8: -0.22959275 | AT8: 0 | AU8: 0.57233151 | AV8: 0 | AW8: -0.14397145 | AX8: 0 | AY8: 0.17050397 | AZ8: 0 | BA8: 0.2659869 | BB8: 0 | BC8: -0.14195937 | BD8: 0 | BE8: 0.15239321 | BF8: 0 | BG8: 0.050817946 | BH8: 0 | BI8: 0.23527064 | BJ8: 0 | BK8: 0.15350472 | BL8: 0 | BM8: 0.17404723 | BN8: 0 | BO8: -0.07620319 | BP8: 0 | BQ8: 0.27536579 | BR8: 0 | BS8: 0.4049863 | BT8: 0 | BU8: 0.12195673 | BV8: 0 | BW8: 0.11462299 | BX8: 0 | BY8: 0.086887612 | BZ8: 0 | CA8: 0.034754225 | CB8: 0 | CC8: 0.19081869 | CD8: 0 | CE8: 0.10508276 | CF8: 0 | CG8: 0.071070306 | CH8: 0 | CI8: -0.0080053263 | CJ8: 0 | CK8: 0.077955806 | CL8: 0 | CM8: 0.046885201 | CN8: 0 | CO8: 0.08943381 | CP8: 0 | CQ8: -0.039990356 | CR8: 0 | CS8: -0.00099408466 | CT8: 0 | CU8: 0.12638861 | CV8: 0 | CW8: 0.096790005 | CX8: 0 | CY8: 0.20137744 | CZ8: 0 | DA8: 0.29139514 | DB8: 0 | DC8: 0.19260033 | DD8: 0 | DE8: -0.14497172 | DF8: 0 | DG8: -0.0089954048 | DH8: 0 | DI8: -0.025718053 | DJ8: 0 | DK8: 0.19726117 | DL8: 0 | DM8: 0.041908764 | DN8: 0 | DO8: 0.013472964 | DP8: 0 | DQ8: 0.43549278 | DR8: 0 | DS8: 0.23794929
A9: 9 | B9: PROP_TOTAL_RETURN | C9: =B9&A9 -> PROP_TOTAL_RETURN9 | D9: 0 | E9: -0.03688777 | F9: 0 | G9: -0.082798974 | H9: 0 | I9: 0.040126084 | J9: 0 | K9: -0.045905526 | L9: 0 | M9: -0.19390149 | N9: 0 | O9: 0.1015734 | P9: 0 | Q9: 0.10032838 | R9: 0 | S9: 0.016536296 | T9: 0 | U9: -0.053391461 | V9: 0 | W9: -0.11345332 | X9: 0 | Y9: 0.095906006 | Z9: 0 | AA9: 0.073650621 | AB9: 0 | AC9: 0.23498075 | AD9: 0 | AE9: -0.1441501 | AF9: 0 | AG9: 0.081872231 | AH9: 0 | AI9: 0.010777409 | AJ9: 0 | AK9: -0.10395394 | AL9: 0 | AM9: -0.18301052 | AN9: 0 | AO9: -0.08525255 | AP9: 0 | AQ9: 0.0061214319 | AR9: 0 | AS9: 0.22446297 | AT9: 0 | AU9: -0.2077769 | AV9: 0 | AW9: 0.018083014 | AX9: 0 | AY9: -0.069350238 | AZ9: 0 | BA9: -0.21749331 | BB9: 0 | BC9: -0.039865628 | BD9: 0 | BE9: -0.080790462 | BF9: 0 | BG9: -0.049464578 | BH9: 0 | BI9: -0.056641714 | BJ9: 0 | BK9: 0.02325258 | BL9: 0 | BM9: 0.01952137 | BN9: 0 | BO9: -0.068591103 | BP9: 0 | BQ9: -0.028195063 | BR9: 0 | BS9: -0.021108028 | BT9: 0 | BU9: -0.0060646935 | BV9: 0 | BW9: -0.032095439 | BX9: 0 | BY9: -0.011918911 | BZ9: 0 | CA9: 0.013952528 | CB9: 0 | CC9: -0.19278111 | CD9: 0 | CE9: 0.23519599 | CF9: 0 | CG9: -0.097432949 | CH9: 0 | CI9: 0.31741009 | CJ9: 0 | CK9: 0.14203677 | CL9: 0 | CM9: 0.20358054 | CN9: 0 | CO9: 0.088448865 | CP9: 0 | CQ9: -0.13412098 | CR9: 0 | CS9: 0.10806907 | CT9: 0 | CU9: -0.13108812 | CV9: 0 | CW9: 0.083603899 | CX9: 0 | CY9: 0.097453765 | CZ9: 0 | DA9: 0.15697188 | DB9: 0 | DC9: 0.038838652 | DD9: 0 | DE9: -0.076314966 | DF9: 0 | DG9: 0.16974062 | DH9: 0 | DI9: 0.13192649 | DJ9: 0 | DK9: 0.23963833 | DL9: 0 | DM9: 0.13035255 | DN9: 0 | DO9: 0.20822251 | DP9: 0 | DQ9: 0.18191173 | DR9: 0 | DS9: 0.28957552
A10: 10 | B10: PROP_TOTAL_RETURN | C10: =B10&A10 -> PROP_TOTAL_RETURN10 | D10: 0 | E10: -0.18256564 | F10: 0 | G10: 0.070399834 | H10: 0 | I10: 0.44142503 | J10: 0 | K10: 0.0017892965 | L10: 0 | M10: 0.19718805 | N10: 0 | O10: 0.19062456 | P10: 0 | Q10: -0.13692579 | R10: 0 | S10: -0.10136496 | T10: 0 | U10: 0.13784138 | V10: 0 | W10: 0.017423594 | X10: 0 | Y10: 0.071447568 | Z10: 0 | AA10: -0.15567354 | AB10: 0 | AC10: -0.17527456 | AD10: 0 | AE10: -0.01814679 | AF10: 0 | AG10: -0.048922741 | AH10: 0 | AI10: -0.092221296 | AJ10: 0 | AK10: -0.21525938 | AL10: 0 | AM10: 0.087352092 | AN10: 0 | AO10: -0.11876179 | AP10: 0 | AQ10: -0.052757636 | AR10: 0 | AS10: 0.0629038 | AT10: 0 | AU10: 0.020867257 | AV10: 0 | AW10: 0.11516553 | AX10: 0 | AY10: -0.033149879 | AZ10: 0 | BA10: -0.16433016 | BB10: 0 | BC10: -0.076240221 | BD10: 0 | BE10: -0.14248177 | BF10: 0 | BG10: 0.11176595 | BH10: 0 | BI10: -0.11422413 | BJ10: 0 | BK10: -0.0028076489 | BL10: 0 | BM10: -0.13954493 | BN10: 0 | BO10: -0.11854748 | BP10: 0 | BQ10: -0.041218463 | BR10: 0 | BS10: -0.055593821 | BT10: 0 | BU10: 0.032182713 | BV10: 0 | BW10: -0.17965817 | BX10: 0 | BY10: -0.082674659 | BZ10: 0 | CA10: 0.12636789 | CB10: 0 | CC10: -0.1445577 | CD10: 0 | CE10: 0.11251565 | CF10: 0 | CG10: -0.10750173 | CH10: 0 | CI10: -0.23399973 | CJ10: 0 | CK10: 0.16235194 | CL10: 0 | CM10: -0.20356174 | CN10: 0 | CO10: -0.069129317 | CP10: 0 | CQ10: -0.13611795 | CR10: 0 | CS10: -0.16687548 | CT10: 0 | CU10: -0.031580594 | CV10: 0 | CW10: -0.13454032 | CX10: 0 | CY10: -0.17900507 | CZ10: 0 | DA10: -0.11935894 | DB10: 0 | DC10: -0.10630694 | DD10: 0 | DE10: 0.093209524 | DF10: 0 | DG10: 0.25409069 | DH10: 0 | DI10: 0.27190132 | DJ10: 0 | DK10: -0.060204676 | DL10: 0 | DM10: 0.14668686 | DN10: 0 | DO10: -0.030329249 | DP10: 0 | DQ10: -0.058079294 | DR10: 0 | DS10: -0.070138882
D11: =AVERAGE(D1:D10) -> 0 | E11: =AVERAGE(E1:E10) -> -0.0032787096 | F11: =AVERAGE(F1:F10) -> 0 | G11: =AVERAGE(G1:G10) -> -0.0067752739 | H11: =AVERAGE(H1:H10) -> 0 | I11: =AVERAGE(I1:I10) -> 0.0098279206 | J11: =AVERAGE(J1:J10) -> 0 | K11: =AVERAGE(K1:K10) -> 0.0090025447 | ... DS11: =AVERAGE(DS1:DS10) -> 0.10446072
B14: 0
B15: -0.0032787096
B16: -0.0067752739
B17: 0.0098279206
B18: 0.0090025447
B19: 0.014124245
B20: 0.0063448313
B21: 0.0075804706
B22: 0.012704498
B23: 0.014016116
B24: 0.01962919
B25: 0.014992378
... B74: 0.10446072

Sheet ZC_1to5
A1: ZC_1 | B1: 1.0016623 | C1: 1.001471 | D1: 1.0012205 | E1: 0.99851264 | F1: 0.99580476 | G1: 0.98416337 | H1: 0.97252197 | I1: 0.97048214 | J1: 0.96844231 | K1: 0.96594474 | L1: 0.96344717 | M1: 0.96278986 | N1: 0.96213255 | O1: 0.96724475 | P1: 0.97235696 | Q1: 0.97468001 | R1: 0.97700306 | S1: 0.98337115 | T1: 0.98973925 | U1: 0.98955314 | V1: 0.98936704 | W1: 0.98543799 | X1: 0.98150894 | Y1: 0.98505906 | Z1: 0.98860919 | AA1: 0.9900223 | AB1: 0.99143541 | AC1: 0.99366715 | AD1: 0.99589889 | AE1: 0.98893635 | AF1: 0.98197381 | AG1: 0.98564249 | AH1: 0.98931117 | AI1: 0.98980808 | AJ1: 0.990305 | AK1: 0.98569922 | AL1: 0.98109345 | AM1: 0.97774894 | AN1: 0.97440442 | AO1: 0.97067967 | AP1: 0.96695492 | AQ1: 0.97550472 | AR1: 0.98405452 | AS1: 0.9811135 | AT1: 0.97817248 | AU1: 0.97649856 | AV1: 0.97482463 | AW1: 0.97264979 | AX1: 0.97047494 | AY1: 0.97662424 | AZ1: 0.98277353 | BA1: 0.97284214 | BB1: 0.96291075 | BC1: 0.95397943 | BD1: 0.94504811 | BE1: 0.94743782 | BF1: 0.94982753 | BG1: 0.94874264 | BH1: 0.94765775 | BI1: 0.94668339 | BJ1: 0.94570904 | BK1: 0.94840809 | BL1: 0.95110714 | BM1: 0.94960836 | BN1: 0.94810958 | BO1: 0.94964661 | BP1: 0.95118363 | BQ1: 0.9516832 | BR1: 0.95218278 | BS1: 0.95663588 | BT1: 0.96108899 | BU1: 0.96512899 | BV1: 0.969169 | BW1: 0.97653336 | BX1: 0.98389772 | BY1: 0.97858902 | BZ1: 0.97328032 | CA1: 0.97107809 | CB1: 0.96887585 | CC1: 0.96362124 | CD1: 0.95836663 | CE1: 0.95991775 | CF1: 0.96146888 | CG1: 0.96568574 | CH1: 0.9699026 | CI1: 0.96755645 | CJ1: 0.9652103 | CK1: 0.96763562 | CL1: 0.97006093 | CM1: 0.97400524 | CN1: 0.97794954 | CO1: 0.98058792 | CP1: 0.9832263 | CQ1: 0.97580792 | CR1: 0.96838955 | CS1: 0.96520592 | CT1: 0.96202229 | CU1: 0.95743814 | CV1: 0.95285398 | CW1: 0.95126902 | CX1: 0.94968406 | CY1: 0.94898597 | CZ1: 0.94828789 | DA1: 0.95384332 | DB1: 0.95939875 | DC1: 0.9630709 | DD1: 0.96674305 | DE1: 0.9622728 | DF1: 0.95780256 | DG1: 0.95788687 | DH1: 0.95797119 | DI1: 0.96115034 | DJ1: 0.96432949 | DK1: 0.95592877 | DL1: 0.94752805 | DM1: 0.94727171 | DN1: 0.94701537 | DO1: 0.94091323 | DP1: 0.93481108 | DQ1: 0.94011401 | DR1: 0.94541693
A2: ZC_2 | B2: 1.002568 | C2: 1.0019066 | D2: 1.0011897 | E2: 0.9952111 | F2: 0.98923251 | G2: 0.96645162 | H2: 0.94367073 | I2: 0.93942258 | J2: 0.93517444 | K2: 0.93043733 | L2: 0.92570022 | M2: 0.92445305 | N2: 0.92320587 | O2: 0.93329727 | P2: 0.94338868 | Q2: 0.94811393 | R2: 0.95283917 | S2: 0.96536723 | T2: 0.97789529 | U2: 0.97770273 | V2: 0.97751017 | W2: 0.96977128 | X2: 0.9620324 | Y2: 0.96946785 | Z2: 0.9769033 | AA2: 0.98008742 | AB2: 0.98327155 | AC2: 0.98775744 | AD2: 0.99224333 | AE2: 0.97827041 | AF2: 0.9642975 | AG2: 0.97071636 | AH2: 0.97713523 | AI2: 0.97779144 | AJ2: 0.97844766 | AK2: 0.96888332 | AL2: 0.95931898 | AM2: 0.95258266 | AN2: 0.94584634 | AO2: 0.93892462 | AP2: 0.93200289 | AQ2: 0.94839545 | AR2: 0.96478801 | AS2: 0.95952944 | AT2: 0.95427088 | AU2: 0.95075453 | AV2: 0.94723818 | AW2: 0.94346611 | AX2: 0.93969405 | AY2: 0.95145701 | AZ2: 0.96321997 | BA2: 0.9441824 | BB2: 0.92514484 | BC2: 0.90824726 | BD2: 0.89134969 | BE2: 0.89596652 | BF2: 0.90058334 | BG2: 0.89855128 | BH2: 0.89651921 | BI2: 0.89455684 | BJ2: 0.89259447 | BK2: 0.8978133 | BL2: 0.90303213 | BM2: 0.90037337 | BN2: 0.89771462 | BO2: 0.90032162 | BP2: 0.90292862 | BQ2: 0.90403108 | BR2: 0.90513353 | BS2: 0.91359488 | BT2: 0.92205623 | BU2: 0.92980218 | BV2: 0.93754813 | BW2: 0.95163352 | BX2: 0.96571892 | BY2: 0.95580065 | BZ2: 0.94588239 | CA2: 0.94109713 | CB2: 0.93631188 | CC2: 0.92684025 | CD2: 0.91736862 | CE2: 0.91995981 | CF2: 0.922551 | CG2: 0.93062518 | CH2: 0.93869935 | CI2: 0.93441075 | CJ2: 0.93012215 | CK2: 0.93457991 | CL2: 0.93903767 | CM2: 0.9468804 | CN2: 0.95472313 | CO2: 0.95941166 | CP2: 0.96410019 | CQ2: 0.95020344 | CR2: 0.93630669 | CS2: 0.93000209 | CT2: 0.92369749 | CU2: 0.91499978 | CV2: 0.90630207 | CW2: 0.90308345 | CX2: 0.89986484 | CY2: 0.89901654 | CZ2: 0.89816824 | DA2: 0.90845619 | DB2: 0.91874413 | DC2: 0.92550628 | DD2: 0.93226843 | DE2: 0.92424654 | DF2: 0.91622465 | DG2: 0.91588706 | DH2: 0.91554948 | DI2: 0.92186429 | DJ2: 0.92817909 | DK2: 0.91226237 | DL2: 0.89634565 | DM2: 0.89560358 | DN2: 0.8948615 | DO2: 0.88373758 | DP2: 0.87261366 | DQ2: 0.88223409 | DR2: 0.89185452
A3: ZC_3 | B3: 1.0021081 | C3: 1.0005469 | D3: 0.99875115 | E3: 0.98951368 | F3: 0.98027621 | G3: 0.94667303 | H3: 0.91306985 | I3: 0.90684479 | J3: 0.90061973 | K3: 0.89386575 | L3: 0.88711177 | M3: 0.88561257 | N3: 0.88411337 | O3: 0.89895866 | P3: 0.91380396 | Q3: 0.92086052 | R3: 0.92791709 | S3: 0.94643598 | T3: 0.96495486 | U3: 0.96469869 | V3: 0.96444251 | W3: 0.95356369 | X3: 0.94268486 | Y3: 0.95422476 | Z3: 0.96576465 | AA3: 0.97074025 | AB3: 0.97571586 | AC3: 0.98210722 | AD3: 0.98849859 | AE3: 0.96702296 | AF3: 0.94554734 | AG3: 0.95426708 | AH3: 0.96298682 | AI3: 0.96322597 | AJ3: 0.96346512 | AK3: 0.94896839 | AL3: 0.93447166 | AM3: 0.92483255 | AN3: 0.91519344 | AO3: 0.90525048 | AP3: 0.89530751 | AQ3: 0.91935903 | AR3: 0.94341055 | AS3: 0.93571644 | AT3: 0.92802233 | AU3: 0.92321033 | AV3: 0.91839833 | AW3: 0.913029 | AX3: 0.90765968 | AY3: 0.92473147 | AZ3: 0.94180326 | BA3: 0.91438333 | BB3: 0.8869634 | BC3: 0.86316016 | BD3: 0.83935691 | BE3: 0.84591956 | BF3: 0.85248222 | BG3: 0.84949751 | BH3: 0.8465128 | BI3: 0.84382702 | BJ3: 0.84114124 | BK3: 0.84871344 | BL3: 0.85628564 | BM3: 0.85234051 | BN3: 0.84839539 | BO3: 0.8520868 | BP3: 0.85577821 | BQ3: 0.85742391 | BR3: 0.85906961 | BS3: 0.87110932 | BT3: 0.88314902 | BU3: 0.89409319 | BV3: 0.90503737 | BW3: 0.92573762 | BX3: 0.94643788 | BY3: 0.9316789 | BZ3: 0.91691993 | CA3: 0.91031939 | CB3: 0.90371886 | CC3: 0.89008805 | CD3: 0.87645724 | CE3: 0.87997974 | CF3: 0.88350224 | CG3: 0.8952789 | CH3: 0.90705557 | CI3: 0.90080901 | CJ3: 0.89456246 | CK3: 0.90108716 | CL3: 0.90761187 | CM3: 0.91863594 | CN3: 0.92966001 | CO3: 0.93671311 | CP3: 0.94376621 | CQ3: 0.92365058 | CR3: 0.90353496 | CS3: 0.89440543 | CT3: 0.88527589 | CU3: 0.87269724 | CV3: 0.86011859 | CW3: 0.85590875 | CX3: 0.85169891 | CY3: 0.85051359 | CZ3: 0.84932826 | DA3: 0.86356172 | DB3: 0.87779518 | DC3: 0.88782879 | DD3: 0.89786241 | DE3: 0.88616337 | DF3: 0.87446434 | DG3: 0.87399276 | DH3: 0.87352117 | DI3: 0.88265936 | DJ3: 0.89179756 | DK3: 0.8689626 | DL3: 0.84612765 | DM3: 0.84521169 | DN3: 0.84429573 | DO3: 0.82862936 | DP3: 0.81296298 | DQ3: 0.82678479 | DR3: 0.84060659
A4: ZC_4 | B4: 0.99947957 | C4: 0.99679274 | D4: 0.99386545 | E4: 0.98114499 | F4: 0.96842454 | G4: 0.92477099 | H4: 0.88111745 | I4: 0.87311261 | J4: 0.86510777 | K4: 0.85681924 | L4: 0.84853072 | M4: 0.84702073 | N4: 0.84551075 | O4: 0.86475232 | P4: 0.88399389 | Q4: 0.89335856 | R4: 0.90272322 | S4: 0.92682631 | T4: 0.95092941 | U4: 0.95109796 | V4: 0.95126651 | W4: 0.93778376 | X4: 0.92430102 | Y4: 0.93984324 | Z4: 0.95538547 | AA4: 0.96180919 | AB4: 0.96823291 | AC4: 0.97571287 | AD4: 0.98319284 | AE4: 0.95423297 | AF4: 0.9252731 | AG4: 0.9356012 | AH4: 0.94592929 | AI4: 0.94550808 | AJ4: 0.94508687 | AK4: 0.92623182 | AL4: 0.90737678 | AM4: 0.89497877 | AN4: 0.88258075 | AO4: 0.87033341 | AP4: 0.85808606 | AQ4: 0.8888594 | AR4: 0.91963273 | AS4: 0.91009112 | AT4: 0.9005495 | AU4: 0.89442275 | AV4: 0.88829599 | AW4: 0.88157523 | AX4: 0.87485446 | AY4: 0.89679704 | AZ4: 0.91873962 | BA4: 0.88380186 | BB4: 0.8488641 | BC4: 0.8190399 | BD4: 0.78921569 | BE4: 0.79733155 | BF4: 0.8054474 | BG4: 0.80176804 | BH4: 0.79808867 | BI4: 0.79492778 | BJ4: 0.79176689 | BK4: 0.80111549 | BL4: 0.81046409 | BM4: 0.80554634 | BN4: 0.80062859 | BO4: 0.8052702 | BP4: 0.80991182 | BQ4: 0.81204362 | BR4: 0.81417542 | BS4: 0.82921724 | BT4: 0.84425907 | BU4: 0.85841988 | BV4: 0.87258069 | BW4: 0.89886028 | BX4: 0.92513987 | BY4: 0.90645035 | BZ4: 0.88776084 | CA4: 0.87916193 | CB4: 0.87056302 | CC4: 0.8532109 | CD4: 0.83585878 | CE4: 0.84039732 | CF4: 0.84493585 | CG4: 0.85986499 | CH4: 0.87479413 | CI4: 0.86698342 | CJ4: 0.85917271 | CK4: 0.86716856 | CL4: 0.87516441 | CM4: 0.88952475 | CN4: 0.90388508 | CO4: 0.91293194 | CP4: 0.92197881 | CQ4: 0.89614502 | CR4: 0.87031123 | CS4: 0.85842776 | CT4: 0.8465443 | CU4: 0.8309744 | CV4: 0.81540449 | CW4: 0.81013884 | CX4: 0.80487318 | CY4: 0.80318202 | CZ4: 0.80149085 | DA4: 0.81961914 | DB4: 0.83774743 | DC4: 0.8502448 | DD4: 0.86274217 | DE4: 0.84800099 | DF4: 0.83325981 | DG4: 0.8326772 | DH4: 0.8320946 | DI4: 0.84349658 | DJ4: 0.85489855 | DK4: 0.82623551 | DL4: 0.79757246 | DM4: 0.79626995 | DN4: 0.79496743 | DO4: 0.77594273 | DP4: 0.75691803 | DQ4: 0.7735658 | DR4: 0.79021357
A5: ZC_5 | B5: 0.99445428 | C5: 0.99034668 | D5: 0.98597933 | E5: 0.96997465 | F5: 0.95396997 | G5: 0.90104653 | H5: 0.84812309 | I5: 0.83878987 | J5: 0.82945664 | K5: 0.82001548 | L5: 0.81057432 | M5: 0.80915228 | N5: 0.80773025 | O5: 0.83107145 | P5: 0.85441265 | Q5: 0.86584529 | R5: 0.87727794 | S5: 0.90709037 | T5: 0.9369028 | U5: 0.93786637 | V5: 0.93882993 | W5: 0.92293179 | X5: 0.90703365 | Y5: 0.92613228 | Z5: 0.9452309 | AA5: 0.95230618 | AB5: 0.95938145 | AC5: 0.96758922 | AD5: 0.975797 | AE5: 0.93920134 | AF5: 0.90260569 | AG5: 0.91415884 | AH5: 0.925712 | AI5: 0.9248988 | AJ5: 0.9240856 | AK5: 0.90111409 | AL5: 0.87814258 | AM5: 0.86366558 | AN5: 0.84918857 | AO5: 0.83465593 | AP5: 0.82012328 | AQ5: 0.85733591 | AR5: 0.89454854 | AS5: 0.88319111 | AT5: 0.87183368 | AU5: 0.86461322 | AV5: 0.85739275 | AW5: 0.8494495 | AX5: 0.84150626 | AY5: 0.8680097 | AZ5: 0.89451315 | BA5: 0.852787 | BB5: 0.81106084 | BC5: 0.77593108 | BD5: 0.74080132 | BE5: 0.75035046 | BF5: 0.7598996 | BG5: 0.75576727 | BH5: 0.75163493 | BI5: 0.74783695 | BJ5: 0.74403896 | BK5: 0.75502946 | BL5: 0.76601997 | BM5: 0.76028249 | BN5: 0.75454501 | BO5: 0.76001101 | BP5: 0.765477 | BQ5: 0.76789031 | BR5: 0.77030361 | BS5: 0.78827519 | BT5: 0.80624676 | BU5: 0.82279704 | BV5: 0.83934732 | BW5: 0.87126059 | BX5: 0.90317386 | BY5: 0.88052404 | BZ5: 0.85787421 | CA5: 0.84747168 | CB5: 0.83706915 | CC5: 0.8166011 | CD5: 0.79613305 | CE5: 0.80139816 | CF5: 0.80666327 | CG5: 0.82459916 | CH5: 0.84253505 | CI5: 0.83294485 | CJ5: 0.82335465 | CK5: 0.83305955 | CL5: 0.84276445 | CM5: 0.85996711 | CN5: 0.87716977 | CO5: 0.88805991 | CP5: 0.89895005 | CQ5: 0.86768483 | CR5: 0.83641961 | CS5: 0.82250915 | CT5: 0.8085987 | CU5: 0.790229 | CV5: 0.7718593 | CW5: 0.76548483 | CX5: 0.75911036 | CY5: 0.75739931 | CZ5: 0.75568826 | DA5: 0.77676431 | DB5: 0.79784035 | DC5: 0.81273701 | DD5: 0.82763367 | DE5: 0.81021455 | DF5: 0.79279542 | DG5: 0.79188583 | DH5: 0.79097624 | DI5: 0.80460158 | DJ5: 0.81822691 | DK5: 0.78427913 | DL5: 0.75033135 | DM5: 0.74916299 | DN5: 0.74799462 | DO5: 0.72551641 | DP5: 0.70303819 | DQ5: 0.72269902 | DR5: 0.74235985
